Workbook

Sheet 1
A1: Capitolo 1 Introduzione
A3: 1.1. I forwards a 1 anno sono contratti in cui una parte ha
A4: (a) il diritto di comprare il sottostante, tra un anno, a un prezzo prefissato;
A5: (b) l’obbligo di comprare il sottostante, tra un anno, a un prezzo prefissato;
A6: (c) l’obbligo di comprare il sottostante, entro un anno, a un prezzo prefissato;
A7: (d) l’obbligo di comprare il sottostante, tra un anno, al prezzo di mercato.
A9: (b)
A10: I forwards a 1 anno sono contratti in cui una parte si impegna a comprare e l’altra a vendere il sottostante, tra 1 anno, a un prezzo prefissato.
A11: Invece, le opzioni sono contratti in cui una delle due parti acquista il diritto di comprare o vendere il sottostante.
A13: 1.2. Solo una delle seguenti affermazioni non è corretta. Quale?
A14: (a) Quando alla CBOE viene esercitata un’opzione sull’IBM, l’IBM emette nuove azioni.
A15: (b) Le opzioni americane possono essere esercitate in qualsiasi momento della loro vita.
... A31: (a)
A33: c | B33: 3
A34: p | B34: 4
A35: K | B35: 30
A36: N_calls | B36: 2
A37: N_puts | B37: 1
A39: ST | B39: =B35+(B36*B33+B37*B34)/B36 -> 35
A41: 1.4. Una call ad 1 anno, con prezzo d’esercizio di $30, costa $3. Una put ad 1 anno, con prezzo d’esercizio di $30, scritta sulla stessa azione costa $4. Supponete che un trader acquisti 2 calls e 1 put.
A42: Qual è il prezzo “soglia” al di sotto del quale il trader consegue un profitto?
A43: (a) $25
A44: (b) $28
A45: (c) $26
A46: (d) $20
A48: (d)
A50: c | B50: 3
A51: p | B51: 4
A52: K | B52: 30
A53: N_calls | B53: 2
A54: N_puts | B54: 1
A56: ST | B56: =B52-(B53*B50+B54*B51)/B54 -> 20
A58: 1.5. Considerate le dimensioni dei mercati dei derivati alla fine di dicembre del 2025, misurate in termini di valori nozionali dei contratti OTC e di valori delle attività sottostanti i derivati di borsa. Solo una delle seguenti affermazioni è corretta, in prima approssimazione. Quale?
A59: (a) Il mercato di borsa è pari al doppio di quello OTC.
A60: (b) Il mercato OTC è pari al doppio di quello di borsa.
A61: (c) Il mercato di borsa è pari a otto volte quello OTC.
A62: (d) Il mercato OTC è pari a otto volte quello di borsa.
A64: (d)
A66: In base ai dati riportati nel Libro, alla fine di dicembre del 2025 le dimensioni del mercato OTC e del mercato di borsa erano pari, rispettivamente, a $844.578 miliardi e a $107.113 miliardi.
A67: Il rapporto tra le due dimensioni è pari a 7,88 (= $844.578 / $107.113). Pertanto, in prima approssimazione, il mercato OTC è pari a otto volte quello di borsa. La risposta corretta è quella sub (d).
A69: 1.6. Quale delle seguenti frasi descrive meglio il «prezzo a pronti» (spot price)?
A70: (a) Il prezzo per consegna immediata.
A71: (b) Il prezzo per consegna in una data futura.
A72: (c) Il prezzo di un’attività deteriorata.
... A99: Chi vende il futures guadagna quando il prezzo scende e perde quando il prezzo sale. Nell’esempio in questione, il prezzo sale da $1.500 a $1.540 e la perdita dell’investitore è pari a –$4.000 [ = ($1.500 – $1.540) × 100].
A100: F0 | B100: 1500
A101: F1 | B101: 1540
A102: N | B102: 100
A104: Π | B104: =(B100-B101)*B102 -> -4000
A106: 1.9. Solo una delle seguenti frasi caratterizza le opzioni europee. Quale?
A107: (a) Vendute in Europa.
A108: (b) Valutate in euro.
A109: (c) Esercitabili solo a scadenza.
A110: (d) Solo di tipo call (non di tipo put).
A112: (c)
A114: Le opzioni europee possono essere esercitate solo a scadenza, diversamente dalle opzioni americane che possono invece essere esercitate in un qualsiasi momento della loro vita.
A115: Il termine “europee” non ha nulla a che fare con la collocazione geografica, la valuta di denominazione o la tipologia di opzione (call o put).
A117: 1.10. Solo una delle seguenti affermazioni non è corretta. Quale?
A118: (a) La call dà al possessore il diritto di comprare il sottostante a un certo prezzo, entro una certa data.
A119: (b) La put dà al possessore il diritto di vendere il sottostante a un certo prezzo, entro una certa data.
A120: (c) Chi detiene una call o una put deve esercitare il diritto d’acquisto o di vendita previsto dal contratto.
... A146: Il payoff delle calls è pari a $500 [= 100 × ($65 − $60)]. Il costo delle opzioni è pari a $200 (= $2 × 100). Pertanto, il profitto netto è pari a $300 (= $500 − $200).
A148: S0 | B148: 57
A149: N | B149: 100
A150: K | B150: 60
A151: c | B151: 2
A152: ST | B152: 65
A154: Π | B154: =B149*(B152-B150-B151) -> 300
A156: 1.13. Il 1° febbraio, il prezzo corrente di un’azione è pari a $124. Un trader vende 200 opzioni put, con strike $120, scritte sull’azione quando il prezzo unitario delle puts è pari a $5.
A157: Le opzioni vengono esercitate quando il prezzo dell’azione sottostante è pari a $110. Qual è il profitto netto (o la perdita netta) del trader?
A158: (a) +$1.000
A159: (b) −$2.000
A160: (c) −$2.800
A161: (d) −$1.000
A163: (d)
A165: Il payoff delle opzioni è pari a $2.000 [= 200 × ($120 − $110)]. Il premio originariamente incassato è pari a $1.000 (= $5 × 200). Pertanto, la perdita netta è pari a −$1.000 (= $1.000 − $2.000).
A167: S0 | B167: 124
A168: N | B168: -200
A169: K | B169: 120
A170: p | B170: 5
A171: ST | B171: 110
A173: Π | B173: =B168*(B169-B171-B170) -> -1000
A175: 1.14. Il 1° febbraio, il prezzo corrente di un’azione è pari a $84. Un trader compra 200 opzioni put, con strike $90, scritte sull’azione quando il prezzo unitario delle puts è pari a $10.
A176: Le opzioni vengono esercitate quando il prezzo dell’azione sottostante è pari a $85. Qual è il profitto netto (o la perdita netta) del trader?
A177: (a) −$1.000
A178: (b) −$2.000
A179: (c) +$200
A180: (d) +$1.000
A182: (a)
A184: Il payoff delle puts è pari a $1.000 [= 200 × ($90 − $85)]. Il costo delle opzioni è pari a $2.000 (= $10 × 200). Pertanto, la perdita netta è pari a −$1.000 (= $1.000 − $2.000).
A186: S0 | B186: 84
A187: N | B187: 200
A188: K | B188: 90
A189: p | B189: 10
A190: ST | B190: 85
A192: Π | B192: =B187*(B188-B190-B189) -> -1000
A194: 1.15. Il 1° febbraio, il prezzo corrente di un’azione è pari a $48. Un trader vende 200 opzioni put, con strike $40, scritte sull’azione quando il prezzo unitario delle puts è pari a $2.
A195: Le opzioni vengono esercitate quando il prezzo dell’azione sottostante è pari a $39. Qual è il profitto netto (o la perdita netta) del trader?
A196: (a) −$800
A197: (b) −$200
...

Sheet 2
A1: Capitolo 2 Mercati dei Futures e Controparti Centralizzate
A3: 2.1. Solo una delle seguenti affermazioni è corretta. Quale?
A4: (a) Sia i forwards sia i futures sono negoziati in borsa.
A5: (b) I forwards sono negoziati in borsa ma i futures no.
A6: (c) I futures sono negoziati in borsa ma i forwards no.
A7: (d) Né i forwards né i futures sono negoziati in borsa.
A9: (c)
A11: I futures vengono trattati solo in borsa. I forwards vengono trattati solo nei mercati OTC.
A13: 2.2. Solo una delle seguenti affermazioni non è corretta. Quale?
A14: (a) I contratti futures durano quasi sempre più dei forward.
A15: (b) I contratti futures sono standardizzati, i contratti forward no.
A16: (c) I contratti forward si concludono con la consegna o con la liquidazione per contanti; in genere, ciò non è vero per i contratti futures.
... A45: Il prezzo futures corrente è pari a ¢70. Ci sarà quindi una richiesta di integrazione dei margini se il prezzo futures supera i ¢72.
A47: Posizione | B47: -1
A48: Dimensione | B48: 50000
A49: F0 | B49: 0.7
A50: Margine iniziale | B50: 4000
A51: Margine di mantenimento | C51: 3000
A53: St | B53: =B49+(B50-C51)/B48 -> 0.72
A55: 2.5. Una società entra in un contratto futures lungo per acquistare 1.000 barili di petrolio a $60 per barile. Il margine iniziale è di $6.000 ed il margine di mantenimento è di $4.000.
A56: Quale prezzo futures del petrolio consentirà di prelevare $2.000 dal conto di deposito?
A57: (a) $58
A58: (b) $62
A59: (c) $64
A60: (d) $66
A62: (b)
A64: Dal deposito di garanzia può essere prelevato il denaro in eccesso rispetto al margine iniziale. L’aumento di $1 del prezzo futures comporta un guadagno di $1.000 (= 1.000 × $1). Pertanto, l’aumento di $2 comporta un guadagno di $2.000 che può essere prelevato dal conto.
A65: Il prezzo futures corrente è pari a $60. Ci sarà quindi la possibilità di prelevare $2.000 dal deposito di garanzia se il prezzo futures raggiunge i $62.
A67: Posizione | B67: 1
A68: Dimensione | B68: 1000
A69: F0 | B69: 60
A70: Margine iniziale | B70: 6000
A71: Margine di mantenimento | C71: 4000
A72: Prelievo | B72: 2000
A74: St | B74: =B69+B67*(B72/B68) -> 62
A76: 2.6. Sul floor di una borsa viene negoziato un contratto che serve ad entrambe le controparti per chiudere le posizioni in essere. Come si modifica l’open interest?
A77: (a) Non c’è nessuna variazione.
A78: (b) Scende di 1 unità.
A79: (c) Scende di due unità.
A80: (d) Aumenta di 1 unità.
A82: (b)
A84: L’open interest misura il numero delle posizioni in essere, lunghe o corte. Se entrambe le controparti chiudono un contratto, ci sarà una posizione lunga in meno e una posizione corta in meno. L’open interest scende quindi di 1 unità.
A86: 2.7. Chi decide, in un contratto futures sul grano, quando effettuare la consegna? Solo una delle seguenti affermazioni è corretta. Quale?
A87: (a) La parte con la posizione lunga.
A88: (b) La parte con la posizione corta.
A89: (c) Ognuna delle due parti può specificare la data di consegna.
A90: (d) L’esatta data di consegna viene specificata dalla borsa.
... A106: Il prezzo futures è aumentato di $2 (= $1.012 − $1.010). Dato che avete una posizione corta, perdete $200 (= 100 × $2). Pertanto, il saldo del deposito di garanzia scende da $2.000 a $1.800.
A108: N | B108: 100
A109: Margine iniziale | B109: 2000
A110: Margine di man. | B110: 1500
A111: F0 | B111: 1010 | D111: F1 | E111: 1012
A112: Saldo | B112: =B109+B108*(B111-E111) -> 1800
A114: 2.9. Il 2 novembre 2026, un hedger assume una posizione lunga su un futures al fine di coprire un’esposizione per il 1° marzo 2027.
A115: Il prezzo futures iniziale è di $60. Il 31 dicembre 2026, il prezzo futures è di $61. Il 1° marzo 2027 è di $64 e il contratto viene chiuso. Ogni contratto riguarda la consegna di 1.000 unità.
A116: Supponete che si applichi l’hedge accounting, con imputazione del risultato della copertura al conto economico nello stesso esercizio dell’operazione coperta. Qual è il profitto di competenza dell’esercizio che va dal 1° gennaio al 31 dicembre 2027?
A117: (a) $0
A118: (b) $1.000
A119: (c) $3.000
A120: (d) $4.000
A122: (d)
A124: Si applica la «contabilità per le coperture» (hedge accounting). Pertanto, l’intero guadagno sul futures viene imputato al conto economico del 2027, insieme agli effetti dell’operazione coperta. Il guadagno unitario è pari a $4 (= $64 − $60) e quello complessivo è pari a $4.000: 1.000 × ($64 − $60) = $4.000. La risposta corretta è quella sub (d).
A126: Posizione | B126: 1
A127: Dimensione | B127: 1000
A128: F0 | B128: 60
A129: F_fine anno | B129: 61
A130: FT | B130: 64
A132: =B126*B127*(B130-B128) -> 4000
A134: 2.10. Qual è la vostra risposta alla Domanda 2.9 se chi assume la posizione sul futures è uno speculatore piuttosto che un hedger e non si applica l’hedge accounting?
A135: (a) $0
A136: (b) $1.000
A137: (c) $3.000
A138: (d) $4.000
A140: (c)
A142: In questo caso non si applica l’hedge accounting. I guadagni o le perdite vengono imputati al conto economico via via che maturano. Nel 2027, il prezzo futures aumenta da $61 a $64. Pertanto, il guadagno di competenza del 2027 è pari a $3.000: 1.000 × ($64 − $61) = $3.000. La risposta corretta è quella sub (c).
A144: =B126*B127*(B130-B129) -> 3000
A146: 2.11. La frequenza con cui viene aggiornato il saldo dei depositi di garanzia dei futures è
A147: (a) giornaliera;
A148: (b) settimanale;
A149: (c) mensile;
A150: (d) trimestrale.
A152: (a)
A154: I guadagni e le perdite sui contratti futures vengono accreditati e addebitati giornalmente.
A156: 2.12. Quali effetti comportano i depositi di garanzia previsti per i contratti futures?
A157: (a) Ridurre il rischio che una parte non onori gli impegni presi.
A158: (b) Assicurare la disponibilità dei fondi da versare ai traders che fanno profitti.
A159: (c) Ridurre il rischio sistemico di collasso dei mercati futures.
A160: (d) Tutte le precedenti affermazioni sono corrette.
... A215: Siano W, X, Y e Z i 4 dealers (n = 4). I contratti conclusi sono quelli tra W e X, W e Y, W e Z, X e Y, X e Z, Y e Z. Pertanto, il numero dei contratti da compensare è pari a 6.
A217: n | B217: 4
A219: Contratti | B219: =COMBIN(4,2) -> 6
A221: 2.18. Quale delle seguenti frasi descrive meglio le central clearing parties?
A222: (a) Aiutano gli operatori a valutare i derivati;
A223: (b) Devono essere utilizzate per tutti i contratti OTC;
A224: (c) Vengono utilizzate per i regolare i contratti futures;
A225: (d) Svolgono un ruolo simile a quello delle clearinghouses di borsa.
A227: (d)
A229: Le «controparti per la compensazione centralizzata delle posizioni» (central clearing parties - CCPs) svolgono – per il mercato OTC – un ruolo simile a quello delle clearinghouses di borsa. Pertanto, la risposta corretta è quella sub (d).
A230: Le CCPs devono essere utilizzate per regolare la maggior parte dei derivati standard negoziati sui mercati OTC, ma non tutti i derivati OTC.
A232: 2.19. Quali contratti vengono liquidati per contanti?
...

Sheet 3
A1: Capitolo 3 Strategie di Copertura mediante Futures
A3: 3.1. La base è definita come differenza tra prezzo spot e prezzo futures. Considerate uno short hedger. La base si rafforza inaspettatamente. Quale delle seguenti affermazioni è corretta?
A4: (a) La posizione dell’hedger migliora.
A5: (b) La posizione dell’hedger peggiora.
A6: (c) La posizione dell’hedger a volte peggiora e a volte migliora.
A7: (d) La posizione dell’hedger né peggiora né migliora.
A9: (a)
A11: Il prezzo incassato dal trader dopo la copertura è pari al prezzo futures originario più la base. Ne segue che la posizione del trader migliora quando la base si rafforza.
A13: 3.2.Una società dovrà acquistare una certa attività il 15 giugno e desidera coprirsi. Su quale futures deve assumere una posizione lunga? Solo una delle seguenti risposte è corretta. Quale?
A14: (a) il futures per giugno;
A15: (b) il futures per luglio;
A16: (c) il futures per maggio;
... A34: Il costo post-copertura può anche essere calcolato come somma tra il prezzo futures del 1° marzo ($59) e la base del 1° giugno ($0,50)
A36: S0 | B36: 60
A37: F0 | B37: 59
A38: S1 | B38: 64
A39: F1 | B39: 63.5
A40: Posizione | B40: 1
A42: S1 − (F1 − F0) | C42: =B38-(B39-B37) -> 59.5
A43: F0 + b1 | B43: =B37+(B38-B39) -> 59.5
A45: 3.4. Il 1° marzo, una società che produce una certa merce entra in un contratto futures per dicembre, al fine di coprire una vendita che intende effettuare il 1° novembre. Il 1° novembre, la società chiude la posizione.
A46: Il 1° marzo, il prezzo spot della merce è di $1.000 e il prezzo futures per dicembre è di $1.015. Il 1° novembre, il prezzo spot della merce è di $980 e il prezzo futures per dicembre è di $981.
A47: Tenendo conto della copertura, qual è il ricavo effettivo per la società?
A48: (a) $1.016
A49: (b) $1.001
A50: (c) $981
A51: (d) $1.014
A53: (d)
A55: Per coprirsi, la società vende il futures a $1.015. Il guadagno sul futures è pari a $34 (= $1.015 − $981). Pertanto, il ricavo effettivo (tenendo conto della copertura) è pari a $1.014.
A56: Il ricavo post-copertura può anche essere calcolato come somma tra il prezzo futures del 1° marzo ($1.015) e la base del 1° novembre (−$1).
A58: S0 | B58: 1000
A59: F0 | B59: 1015
A60: S1 | B60: 980
A61: F1 | B61: 981
A62: Posizione | B62: -1
A64: S1 − (F1 − F0) | C64: =B60-(B61-B59) -> 1014
A65: F0 + b1 | B65: =B59+(B60-B61) -> 1014
A67: 3.5. La deviazione standard delle variazioni mensili del prezzo spot della merce A è pari a $2. La deviazione standard delle variazioni mensili del prezzo futures della merce B (simile alla merce A) è pari a $3.
A68: La correlazione tra il prezzo futures di B e il prezzo spot di A è pari a 0,9. Quale rapporto di copertura si dovrebbe utilizzare per coprire un’esposizione di un mese verso il prezzo spot della merce A?
A69: (a) 0,60
A70: (b) 0,67
A71: (c) 1,45
A72: (d) 0,90
A74: (a)
A76: Il rapporto di copertura ottimale è pari a 0,6.
A78: σS | B78: 2
A79: sF | B79: 3
A80: ρ | B80: 0.9
A82: h | B82: =B78/B79*B80 -> 0.6
A84: 3.6. Una società ha un portafoglio del valore di $36 milioni con un beta di 1,2. Il prezzo futures dell’indice di mercato è $900. In borsa vengono negoziati futures scritti su 250 volte il prezzo spot dell’indice.
A85: Che posizione la società dovrà assumere sui futures per ridurre il beta a 0,9?
A86: (a) Lunga su 192 contratti.
A87: (b) Corta su 192 contratti.
A88: (c) Lunga su 48 contratti.
A89: (d) Corta su 48 contratti.
A91: (d)
A93: Per ridurre il beta di 0,3 (= 1,2 − 0,9), la società dovrà vendere 48 contratti.
A95: Posizione | B95: 1
A96: P | B96: 36000000
A97: beta | B97: 1.2
A98: F0 | B98: 900
A99: Size futures | B99: 250
A100: β*1 | B100: 0
A101: b*2 | B101: 0.9
A102: β*3 | B102: 1.8
A104: N* | B104: =-$B$95*($B$97-B101)*$B$96/($B$98*$B$99) -> -48
A106: 3.7. Una società ha un portafoglio del valore di $36 milioni con un beta di 1,2. Il prezzo futures dell’indice di mercato è $900. In borsa vengono negoziati futures scritti su 250 volte il prezzo spot dell’indice.
A107: Che posizione la società dovrà assumere sui futures per aumentare il beta a 1,8?
A108: (a) Lunga su 192 contratti.
A109: (b) Corta su 192 contratti.
A110: (c) Lunga su 96 contratti.
A111: (d) Corta su 96 contratti.
A113: (c)
A115: Per aumentare il beta di 0,6 (= 1,8 − 1,2), la società dovrà acquistare 96 contratti:
A117: Posizione | B117: 1
A118: P | B118: 36000000
A119: beta | B119: 1.2
A120: F0 | B120: 900
A121: Size futures | B121: 250
A122: β*1 | B122: 0
A123: b*2 | B123: 0.9
A124: β*3 | B124: 1.8
A126: N* | B126: =-$B$95*($B$97-B124)*$B$96/($B$98*$B$99) -> 96
A128: 3.8. Solo una delle seguenti affermazioni è corretta. Quale?
A129: (a) il rapporto di copertura ottimale è il coefficiente angolare della retta che misura la regressione del prezzo spot (asse y) sul prezzo futures (asse x);
A130: (b) il rapporto di copertura ottimale è il coefficiente angolare della retta che misura la regressione del prezzo futures (asse y) sul prezzo spot (asse x);
A131: (c) il rapporto di copertura ottimale è il coefficiente angolare della retta che misura la regressione della variazione del prezzo spot (asse y) sulla variazione del prezzo futures (asse x);
A132: (d) il rapporto di copertura ottimale è il coefficiente angolare della retta che misura la regressione della variazione del prezzo futures (asse y) sulla variazione del prezzo spot (asse x).
A134: (c)
A136: Il rapporto di copertura ottimale è il coefficiente angolare della retta che misura le variazioni del prezzo spot in funzione delle variazioni del prezzo futures.
A138: 3.9. Cosa s’intende per tailing the hedge? Solo una delle seguenti risposte è corretta. Quale?
A139: (a) Una strategia che prevede di aumentare la dimensione dell’hedge in prossimità della scadenza della copertura.
A140: (b) Una strategia che prevede di aumentare la dimensione dell’hedge in prossimità della scadenza del futures utilizzato per la copertura.
A141: (c) Una strategia che utilizza un calcolo più preciso dell’hedge ratio quando la copertura viene attuata mediante contratti forward.
A142: (d) Nessuna delle precedenti risposte è corretta.
... A264: Pertanto, il prezzo medio effettivamente pagato per la merce è pari a $96 (= 0,8 × $92 + 0,2 × $112).
A266: N | B266: 1000
A267: α | B267: 0.8
A268: S0 | B268: 100
A269: F0 | B269: 90
...

Sheet 4
A1: Capitolo 4 Tassi d’Interesse
A3: 4.1. La frequenza con cui un tasso d’interesse viene composto definisce
A4: (a) la frequenza con cui si pagano gli interessi;
A5: (b) l’unità di misura del tasso d’interesse;
A6: (c) la relazione tra il tasso d’interesse annuo e quello mensile;
A7: (d) nessuna delle precedenti risposte è corretta.
A9: (b)
A11: La frequenza con cui un tasso d’interesse viene composto è la sua unità di misura. La fre-quenza con cui si pagano gli interessi può essere diversa da quella con cui il tasso d’interes¬se viene composto.
A13: 4.2. Un tasso d’interesse composto annualmente è pari al 6 per cento annuo. Qual è il tasso equivalente composto continuamente?
A14: (a) 5,79%
A15: (b) 6,21%
A16: (c) 5,83%
... A21: Il tasso equivalente composto continuamente è pari al 5,83%.
A23: R | B23: 0.06
A24: m | B24: 1
A26: r | B26: =LN(1+B23) -> 0.058268908
A28: 4.3. Un tasso d’interesse composto continuamente è pari al 5 per cento annuo. Qual è il tasso equivalente composto semestralmente?
A29: (a) 5,06%
A30: (b) 5,03%
A31: (c) 4,97%
A32: (d) 4,94%
A34: (a)
A36: Il tasso equivalente composto semestralmente è pari al 5,06%.
A38: r | B38: 0.05
A39: m | B39: 2
A41: R | B41: =B39*(EXP(B38/B39)-1) -> 0.050630241
A43: 4.4. Un tasso d’interesse composto semestralmente è pari al 12% annuo. Qual è il tasso equivalente composto trimestralmente?
A44: (a) 11,83%
A45: (b) 11,66%
A46: (c) 11,77%
A47: (d) 11,92%
A49: (a)
A51: Il tasso equivalente composto trimestralmente è pari all’11,83%.
A53: R_m1 | B53: 0.12
A54: m1 | B54: 2
A55: m2 | B55: 4
A57: R_m2 | B57: =B55*((1+B53/B54)^(B54/B55)-1) -> 0.11825206
A59: 4.5. Lo zero rate a 2 anni è pari al 6% annuo e lo zero rate a 3 anni è pari al 6,5% annuo. Qual è il tasso forward per il 3° anno? Tutti i tassi sono composti continuamente.
A60: (a) 6,75%
A61: (b) 7,0%
A62: (c) 7,25%
A63: (d) 7,5%
A65: (d)
A67: Il tasso forward per il 3° anno è pari al 7,5%.
A69: T1 | B69: 2
A70: T2 | B70: 3
A71: R1 | B71: 0.06
A72: R2 | B72: 0.065
A74: RF | B74: =(B72*B70-B71*B69)/(B70-B69) -> 0.075
A76: 4.6. Lo zero rate a 6 mesi è pari all’8% annuo (composto semestralmente). Il prezzo di un coupon bond con scadenza tra 1 anno, valore nominale di $100 e tasso cedolare annuo del 6%, pagabile semestralmente, è di $97.
A77: Qual è lo zero rate ad 1 anno (composto continuamente)?
A78: (a) 8,02%
A79: (b) 8,52%
A80: (c) 9,02%
A81: (d) 9,52%
A83: (c)
A85: Se R è lo zero rate a 1 anno, deve essere soddisfatta la seguente equazione: | K85: Pertanto, lo zero rate a 1 anno è pari al 9,02%:
A87: L | B87: 100
A88: T1 | B88: 0.5
A89: T2 | B89: 1
A90: R1 | B90: 0.08
A91: m1 | B91: 2
A92: B | B92: 97
A93: c | B93: 0.06
A95: R2 | B95: =LN((B87*(1+B93/B91))/(B92-B87*B93/B91/(1+B90/2)^B89)) -> 0.090207463
A97: 4.7. La curva degli OIS zero rates è piatta al livello del 6% annuo.
A98: Qual è il valore corrente di un one-period OIS in cui si riceve il tasso fisso dell’8% annuo e si paga il tasso di riferimento overnight composto, su un capitale di $1.000, per il semestre che inizierà tra 2 anni? Il pagamento netto avverrà alla fine del semestre. Tutti i tassi sono composti semestralmente.
A99: (a) $9,12
A100: (b) $9,02
A101: (c) $8,88
A102: (d) $8,63
A104: (d)
A106: Il valore corrente del one-period OIS è pari a $8,63.
A108: y | B108: 0.06
A109: m | B109: 2
A110: T1 | B110: 2
A111: T2 | B111: 2.5
A112: Rk | B112: 0.08
A113: L | B113: 1000
A115: VOIS | B115: =B113*(B112-B108)*(B111-B110)*(1+B108/B109)^(-B111*B109) -> 8.6260878
A117: 4.8. Secondo la teoria della preferenza per la liquidità una sola delle seguenti affermazioni è esatta. Quale?
A118: (a) Il tasso forward per una certa scadenza è maggiore del tasso spot per quella scadenza.
A119: (b) I tassi forward sono previsori corretti dei futuri tassi spot.
A120: (c) Il tasso spot per una certa scadenza è maggiore del par yield per quella scadenza.
A121: (d) I tassi forward sono maggiori del valore atteso dei futuri tassi spot.
A123: (d)
A125: La teoria della preferenza per la liquidità sostiene che le imprese preferiscono indebitarsi a lungo termine, mente le famiglie preferiscono investire a breve termine. Per indurre le famiglie a spostarsi verso orizzonti d’investimento più lunghi, i tassi forward sono più alti dei livelli attesi dei futuri tassi a breve.
A127: 4.9. La zero curve è inclinata verso l’alto. Siano X, Y e Z, rispettivamente, il par yield a 1 anno, lo zero rate a 1 anno e il tasso forward a 6 mesi tra 1 anno. Solo una delle seguenti affermazioni è corretta. Quale?
A128: (a) X è minore di Y che è minore di Z.
A129: (b) Y è minore di X che è minore di Z.
A130: (c) X è minore di Z che è minore di Y.
A131: (d) Z è minore di Y che è minore di X.
... A155: Quando i tassi d’interesse aumentano i prezzi delle obbligazioni diminuiscono. La riduzione è pari alla duration modificata per l’incremento dei tassi d’interesse, ossia a $2,500
A157: P | B157: 1000000
A158: D | B158: 5
A159: Δy | B159: =5/10000 -> 0.0005
A161: ΔP | B161: =-B157*B158*B159 -> -2500
A163: 4.12. Una società investe $1.000 in uno zero-coupon bond a 5 anni e $4.000 in uno zero-coupon bond a 10 anni. Qual è la duration del portafoglio?
A164: (a) 6 anni
A165: (b) 7 anni
...

Sheet 5
A1: Capitolo 5 Determinazione dei Prezzi Forward e dei Prezzi Futures
A3: 5.1. Solo una delle seguenti attività rappresenta un bene di consumo. Quale?
A4: (a) L’indice S&P 500.
A5: (b) Il dollaro canadese.
A6: (c) Il rame.
A7: (d) Le azioni IBM.
A9: (c)
A11: Le attività menzionate sub (a), (b) e (d) sono beni d’investimento, detenuti da alcuni soggetti solo per fini d’investimento. Invece, il rame, menzionato sub (c), è un bene di consumo.
A13: 5.2. Un investitore vende allo scoperto 100 azioni quando il prezzo è di $50 e chiude la posizione 6 mesi dopo quando il prezzo è di $43.
A14: Nel corso del semestre, le azioni pagano un dividendo unitario di $3. Qual è il profitto dell’investitore?
A15: (a) $1.000
A16: (b) $400
... A23: Pertanto, il profitto netto è pari a $4 (= $7 − $3) per azione. Dato che le azioni vendute allo scoperto sono 100, il profitto complessivo è pari a $400 (= $4 × 100)
A25: Posizione | B25: -1
A26: Dimensione | B26: 100
A27: S0 | B27: 50
A28: T | B28: 0.5
A29: ST | B29: 43
A30: d | B30: 3
A32: Profitto | B32: =B25*B26*(B29+B30-B27) -> 400
A34: 5.3. Il prezzo spot di un bene d’investimento che non offre redditi è di $30 e il tasso d’interesse privo di rischio per tutte le scadenze è del 10% (composto continuamente).
A35: Qual è il prezzo forward a 3 anni?
A36: (a) $40,50
A37: (b) $22,22
A38: (c) $33,00
A39: (d) $33,16
A41: (a)
A43: Il prezzo forward a 3 anni, che si ottiene capitalizzando il prezzo spot per tre anni al tasso d’interesse privo di rischio, è pari a $40,50
A45: S0 | B45: 30
A46: r | B46: 0.1
A47: T | B47: 3
A49: F0 | B49: =B45*EXP(B46*B47) -> 40.495764
A51: 5.4. Il prezzo spot di un bene d’investimento è di $30 e il tasso d’interesse privo di rischio per tutte le scadenze è del 10% (composto continuamente).
A52: Il bene d’investimento offre un reddito di $2 alla fine del primo e del secondo anno. Qual è il prezzo forward a 3 anni?
A53: (a) $19,67
A54: (b) $35,84
A55: (c) $45,15
A56: (d) $40,50
A58: (b)
A60: Il valore attuale del reddito è pari a $3,45 (= 2e−0.1×1 + 2e−0.1×2).
A61: Il prezzo spot teorico del bene d’investimento che verrà consegnato tra 3 anni è pari alla differenza tra il livello corrente del prezzo spot di mercato e il valore attuale del reddito offerto durante la vita del contratto forward. È pari a $26,55 (= $30 − $3,45).
A62: Il prezzo forward a 3 anni si ottiene capitalizzando il prezzo spot teorico per tre anni al tasso d’interesse privo di rischio. È pari a $35,84.
A64: S0 | B64: 30
A65: r | B65: 0.1
A66: T | B66: 3
A67: d1 | B67: 2
A68: d2 | B68: 2
A69: t1 | B69: 1
A70: t2 | B70: 2
A72: I | B72: =B67*EXP(-B46*B69)+B68*EXP(-B46*B70) -> 3.4471363
A73: S0 − I | B73: =B64-B72 -> 26.552864
A74: F0 | B74: =(B45-B67*EXP(-B46*B69)-B68*EXP(-B46*B70))*EXP(B46*B47) -> 35.842617
A76: 5.5. Un tasso di cambio spot è pari a $0,7000 e i tassi d’interesse interni ed esteri privi di rischio sono pari, rispettivamente, al 5 e al 7 per cento annuo (composto continuamente).
A77: Qual è il tasso di cambio forward a 6 mesi?
A78: (a) $0,7070
A79: (b) $0,7177
A80: (c) $0,7249
A81: (d) $0,6930
A83: (d)
A85: Il tasso di cambio forward a 6 mesi è pari a $0,6930.
A87: S0 | B87: 0.7
A88: r | B88: 0.05
A89: rf | B89: 0.07
A90: T | B90: 0.5
A92: F0 | B92: =B87*EXP((B88-B89)*B90) -> 0.69303488
A94: 5.6. Una sola delle seguenti affermazioni è esatta. Quale?
A95: (a) Il convenience yield è sempre positivo o nullo.
A96: (b) Il convenience yield è sempre positivo nel caso dei beni d’investimento.
A97: (c) Il convenience yield è sempre negativo nel caso dei beni di consumo.
A98: (d) Il convenience yield misura il tasso di rendimento che si riceve in media da una posizione lunga su futures.
A100: (a)
A102: Il convenience yield misura il beneficio derivante dalla disponibilità immediata di una certa attività, invece della disponibilità futura conseguente a una posizione lunga su un forward / futures scritto sull’attività.
A103: Il convenience yield di un bene d’investimento è sempre nullo. Può essere invece positivo nel caso dei beni di consumo.
A105: 5.7. Un contratto forward corto, che è stato negoziato qualche tempo fa e scadrà tra 3 mesi, ha un prezzo di consegna di $40. Il prezzo forward corrente a 3 mesi è di $42.
A106: Il tasso d’interesse a 3 mesi privo di rischio è dell’8 per cento annuo (composto continuamente). Qual è il valore del contratto forward corto?
A107: (a) +$2,00
A108: (b) −$2,00
... A114: Il contratto forward corto obbliga il venditore a vendere l'attività sottostante a $40 tra 3 mesi, mentre un contratto forward negoziato oggi comporterebbe l'obbligo di vendere a $42. Il valore del contratto forward è pari al valore attuale di −$2 (= $40 − $42), ossia −$1,96.
A116: Posizione | B116: -1
A117: K | B117: 40
A118: T | B118: 0.25
A119: F0 | B119: =42 -> 42
A120: r | B120: 0.08
A122: -f | B122: =B116*(B119-B117)*EXP(-B120*B118) -> -1.9603973
A124: 5.8. Il prezzo spot di un’attività è correlato positivamente con il mercato. Una sola delle seguenti affermazioni è esatta. Quale?
A125: (a) Il prezzo forward è uguale al valore atteso del futuro prezzo spot.
A126: (b) Il prezzo forward è maggiore del valore atteso del futuro prezzo spot.
A127: (c) Il prezzo forward è minore del valore atteso del futuro prezzo spot.
A128: (d) Il prezzo forward è a volte maggiore e a volte minore del valore atteso del futuro prezzo spot.
A130: (c)
A132: Dato che l’attività è correlata positivamente con il mercato, il capital asset pricing model richiede che il tasso di rendimento atteso sia maggiore del tasso d’interesse privo di rischio.
A133: Pertanto, il prezzo forward − che è pari al prezzo spot capitalizzato al tasso d’interesse privo di rischio − è minore del valore atteso del futuro prezzo spot.
A135: 5.9. Quale delle seguenti frasi descrive meglio il modo in cui i prezzi futures delle valute estere vengono quotati al CME Group?
A136: (a) Numero di dollari statunitensi per un’unità di valuta estera.
A137: (b) Numero di unità di valuta estera per un dollaro statunitense.
A138: (c) Alcuni prezzi futures sono quotati come numero di dollari statunitensi per un’unità di valuta estera e altri sono quotati come numero di unità di valuta estera per un dollaro sta-tunitense.
... A259: Le argomentazioni di arbi-traggio non forniscono quindi un corrispondente limite inferiore. La risposta corretta è quella sub (c).

Sheet 6
A1: Capitolo 6 Futures su Tassi d’Interesse
A3: 6.1. Negli Stati Uniti, quale regola di calcolo giorni si applica ai corporate bonds?
A4: (a) Effettivi / 360.
A5: (b) Effettivi / effettivi.
A6: (c) 30 /360.
A7: (d) Effettivi /365.
A9: (c)
A11: Negli Stati Uniti, i corporate bonds vengono in genere quotati in base alla regola di calcolo giorni 30/360. In altri termini, quando si calcolano gli interessi maturati, si assume che ogni mese sia composto da 30 giorni e che ci siano quindi 360 giorni in un anno.
A13: 6.2. È il 1° maggio. Il prezzo quotato di un Treasury bond, con valore nominale di $100 e tasso cedolare del 12 per cento pagabile due volte l’anno (il 1° aprile e il 1° ottobre), è di $105.
A14: Qual è il prezzo effettivo?
A15: (a) $106,00
A16: (b) $106,02
... A23: In questo caso, il prezzo quotato è $105 e l’interesse maturato è pari a $0,98 (= 30 / 183 × 0,12 / 2 × $100). Pertanto, la risposta corretta è $105,98.
A25: T0 | B25: 38108
A26: Last coupon | B26: 38078
A27: Next coupon | B27: 38261
A28: L | B28: 100
A29: coupon rate | B29: 0.12
A30: m | B30: 2
A31: Clean price | B31: 105
A33: Prezzo effettivo | B33: =B31+B28*(B29/B30)*(B25-B26)/(B27-B26) -> 105.98361
A35: 6.3. È il 1° maggio. Il prezzo quotato di un corporate bond, con valore nominale di $100 e tasso cedolare del 12% pagabile due volte l’anno (il 1° aprile e il 1° ottobre), è di $105. Qual è il prezzo effettivo?
A36: (a) $106,00
A37: (b) $106,02
A38: (c) $105,98
A39: (d) $106,04
A41: (a)
A43: Il prezzo effettivo è pari al prezzo quotato più gli interessi maturati. Si assume che i giorni tra il 1° aprile e il 1° maggio siano 30 e quelli tra il 1° aprile e il 1° ottobre siano 180.
A44: In questo caso, il prezzo quotato è $105 e l’interesse maturato è pari a $1,00 (= 30 / 180 × 0,12 / 2 × $100). Pertanto, la risposta corretta è $106,00.
A46: T0 | B46: 38108
A47: Last coupon | B47: 38078
A48: Next coupon | B48: 38261
A49: L | B49: 100
A50: coupon rate | B50: 0.12
A51: m | B51: 2
A52: Clean price | B52: 105
A54: Prezzo effettivo | B54: =B52+B49*(B50/B51)*(DAYS360(B47,B46))/180 -> 106
A56: 6.4. Il prezzo quotato dei futures su Treasury bonds è di $103,5. Quale dei seguenti titoli è il cheapest to deliver?
A57: (a) | B57: Prezzo quotato: | C57: 110 | D57: fattore di conversione: | F57: 1.04
A58: (b) | B58: Prezzo quotato: | C58: 160 | D58: fattore di conversione: | F58: 1.52
A59: (c) | B59: Prezzo quotato: | C59: 131 | D59: fattore di conversione: | F59: 1.25
A60: (d) | B60: Prezzo quotato: | C60: 143 | D60: fattore di conversione: | F60: 1.35
A62: (c)
A64: Il costo di consegna del Treasury bond è pari al prezzo quotato del titolo meno il prodotto tra il prezzo quotato del futures e il fattore di conversione.
A65: I valori in questione sono $2,36; $2,68; $1,625 e $3,275 per i titoli sub (a), (b), (c) e (d), rispettivamente. Pertanto, il titolo sub (c) è il cheapest to deliver
A67: F0 | B67: 103.5
A68: Gross basis | B68: =C57-$B$67*F57 -> 2.36 | C68: (a)
B69: =C58-$B$67*F58 -> 2.68 | C69: (b)
B70: =C59-$B$67*F59 -> 1.625 | C70: (c)
B71: =C60-$B$67*F60 -> 3.275 | C71: (d)
A73: 6.5. Il futures su T-bond è disegnato in modo da assegnare alla parte con la posizione corta diverse opzioni. Una sola delle seguenti opzioni non è prevista. Quale?
A74: (a) La possibilità di consegnare un qualsiasi T-bond all’interno di un certo paniere.
A75: (b) La possibilità di avvalersi del «gioco della matta» (wild card play).
A76: (c) La possibilità di effettuare la consegna in un qualsiasi giorno del mese di consegna.
A77: (d) La possibilità di modificare il tasso d’interesse utilizzato per il calcolo dei fattori di conversione.
A79: (d)
A81: Le opzioni sub (a), (b) e (c) sono tutte opzioni effettivamente previste per la parte corta. L’opzione (d) no.
A83: 6.6. Un trader assume una posizione lunga sul futures sul Sofr a 3 mesi. Quanto guadagna se il prezzo futures quotato aumenta di 6 punti base?
A84: (a) $6
A85: (b) $150
A86: (c) $60
A87: (d) $600
... A91: Il trader guadagna $25 per ogni punto base. Pertanto, il guadagno complessivo è pari a $150
A93: Posizione | B93: 1
A94: Thick value | B94: 25
A95: Variazione | B95: 6 | C95: punti base
A97: Profitto | B97: =B93*B94*B95 -> 150
A99: 6.7. Nei futures su T-bonds, i titoli consegnabili sono:
A100: (a) attività che non offrono redditi;
A101: (b) attività che offrono un reddito noto;
A102: (c) attività che offrono un tasso di rendimento noto.
A103: (d) Nessuna delle precedenti risposte è corretta.
A105: (b)
A107: I T-bonds sono attività che offrono un reddito noto (le cedole).
A109: 6.8. Un ultra T-bond futures è un contratto in cui si possono consegnare
A110: (a) T-bonds con vita residua minore di 3 anni;
A111: (b) T-bonds con vita residua minore di 10 anni;
A112: (c) T-bonds con vita residua maggiore di 15 anni;
A113: (d) T-bonds con vita residua maggiore di 25 anni.
... A128: Il valore del titolo sottostante il futures su T-Notes è pari a $110.000. Pertanto, per proteggere il portafoglio, il numero dei contratti futures da vendere è pari a 200
A130: VA | B130: 24000000
A131: DA | B131: 5.5
A132: F0 | B132: 110
A133: Size | B133: 100000
A134: VF | B134: =B132*B133/100 -> 110000
A135: DF | B135: 6
A137: N* | B137: =B130*B131/(B134*B135) -> 200
A139: 6.10. Considerate un futures sul Sofr a 3 mesi e supponete che l’aggiustamento per la convessità sia positivo. Solo una delle seguenti affermazioni è corretta. Quale?
A140: (a) Il tasso futures calcolato in base alla quotazione del contratto è minore del corrispondente tasso forward.
A141: (b) Il tasso futures calcolato in base alla quotazione del contratto è maggiore del corrisponden-te tasso forward.
A142: (c) Il tasso futures calcolato in base alla quotazione del contratto è uguale al corrispondente tasso forward.
A143: (d) Il tasso futures calcolato in base alla quotazione del contratto può essere sia minore sia maggiore del corrispondente tasso forward.
A145: (b)
A147: Per ottenere il tasso forward, si sottrae dal tasso futures l’«aggiustamento per la convessità» (convexity adjustment): tasso forward = tasso futures − c. Dato che, per ipotesi, c > 0, il tasso forward è minore del tasso futures. Pertanto, la risposta corretta è quella sub (b).
A149: 6.11. A quanto equivale un punto base?
A150: (a) 1,0%
A151: (b) 0,1%
A152: (c) 0,01%
A153: (d) 0,001%
... A188: La duration del titolo è pari alla media ponderata del tempo mancante ai futuri pagamenti, con pesi pari al valore attuale dei pagamenti. In questo caso, la duration è pari a 1,88 anni.
...

Sheet 7
A1: Capitolo 7 Swaps
A3: 7.1. Una società può investire fondi per 5 anni al Sofr a 3 mesi – 30 p.b. Il tasso swap a 5 anni è pari al 3%. Se utilizza lo swap, qual è il tasso fisso che la società riesce a realizzare?
A4: (a) 2,4%
A5: (b) 2,7%
A6: (c) 3,0%
A7: (d) 3,3%
A9: (b)
A11: La società riceve il Sofr a 3 mesi – 30 p.b. ed entra in uno swap in cui paga il Sofr a 3 mesi e riceve il 3%. Il flusso netto annuo che riceve è pari al 2,7%:
A13: Rfl | B13: Sofr a 3 mesi | C13: =-30/10000 -> -0.003
A14: T | B14: 5
A15: Rswap | B15: 0.03
A17: Rfx | B17: =C13+B15 -> 0.027
A19: 7.2. Solo una delle seguenti affermazioni è corretta Quale?
A20: (a) Di solito, nei currency swaps non si scambiano i capitali.
A21: (b) Di solito, nei currency swaps i capitali viaggiano nella direzione opposta degli interessi all’inizio e nella stessa direzione degli interessi alla fine.
A22: (c) Di solito, nei currency swaps i capitali viaggiano nella stessa direzione degli interessi all’inizio e nella direzione opposta degli interessi alla fine.
A23: (d) Di solito, nei currency swaps non si specificano i capitali.
A25: (b)
A27: La risposta corretta è quella sub (b). Nei currency swaps sono presenti due capitali, uno per ogni valuta. I capitali viaggiano nella direzione opposta degli interessi all’inizio dello swap e nella stessa direzione degli interessi alla fine dello swap.
A29: 7.3. Considerate un interest rate swap, con decorrenza futura, in cui si scambia un tasso fisso con il Sofr a 3 mesi. Trascurando il rischio di credito, quale dei seguenti metodi di valutazione è appropriato?
A30: (a) Calcolare i pagamenti variabili in base ai corrispondenti Sofr a 3 mesi forward correnti e attualizzare i pagamenti netti in base agli OIS spot zero rates.
A31: (b) Calcolare tutti i pagamenti variabili utilizzando lo stesso Sofr a 3 mesi spot corrente e attua-lizzare i pagamenti netti in base agli OIS spot zero rates.
A32: (c) Calcolare i pagamenti variabili in base ai corrispondenti Sofr a 3 mesi forward correnti e attualizzare i pagamenti netti in base al tasso fisso contrattuale dello swap.
A33: (d) Calcolare tutti i pagamenti variabili utilizzando lo stesso Sofr a 3 mesi spot corrente e attua-lizzare i pagamenti netti in base al tasso fisso contrattuale dello swap.
... A172: Pertanto, il valore dello swap è pari a $2,66 (= $100 − $97,34), ossia al 2,66% del nozionale.
A174: Rswap | B174: 0.03
A175: L | B175: 100
A176: m | B176: 1
B177: t1 | C177: t2 | D177: t3
A178: Date | B178: 1 | C178: 2 | D178: 3
A179: Pagamenti | B179: =B174*B175 -> 3 | C179: =B174*B175 -> 3 | D179: =B175+B174*B175 -> 103
A180: Zero rates | B180: 0.02 | C180: 0.03 | D180: 0.04
A182: Val. attuale | B182: =B179/(1+B180)^B178*B176 -> 2.9411765 | C182: =C179/(1+C180)^C178*B176 -> 2.8277877 | D182: =D179/(1+D180)^D178*B176 -> 91.566625 | E182: =SUM(B182:D182) -> 97.335589
A183: Vswap | B183: =B175-E182 -> 2.6644109
A185: 7.16. Un interest rate swap, in cui si riceve il 5% (composto semestralmente) e si paga il Sofr a 6 mesi, ha 9 mesi di vita residua.
A186: I pagamenti vengono scambiati con frequenza semestrale. L’ultimo scambio è avvenuto 3 mesi fa e i prossimi avverranno tra 3 e 9 mesi.
A187: Il tasso annuo calcolato in base ai tassi Sofr giornalieri osservati negli ultimi 3 mesi è pari al 4,85% (composto continuamente).
A188: Gli OIS spot zero rates a 3 e a 9 mesi sono pari, rispettivamente, al 5,3% e al 5,8% annuo (entrambi composti continuamente).
A189: Se il capitale nozionale è pari a $15.000.000, qual è il valore dello swap per la parte che riceve il fisso? Trascurate il rischio di credito e le regole di calcolo giorni.
A190: (a) $74.250
A191: (b) −$92.393
A192: (c) −$11.250
A193: (d) $103.790.
A195: (b)
A197: Il semestre relativo al primo pagamento variabile è già trascorso per metà.
A198: Il tasso composto continuamente da utilizzare per stimare questo pagamento è pari al 5,075% [= (4,85% × 0,25 + 5,3% × 0,25) / 0,5].
... A201: I corrispondenti pagamenti variabili, da effettuare alle stesse date, vengono stimati capitalizzando per un semestre i tassi del 5,075% e del 6,05%.
A203: L | B203: 15000000
A204: Rswap | B204: 0.05
A205: R0 | B205: 0.0485
A206: m | B206: 2
B207: t1 | C207: t2
A208: Date | B208: =3/12 -> 0.25 | C208: =9/12 -> 0.75
A209: Zero rates | B209: 0.053 | C209: 0.058
A210: Forward rate | B210: =(B205*B208+B209*B208)*B206 -> 0.05075 | C210: =(C209*C208-B209*B208)/(C208-B208) -> 0.0605
A211: Interessi fissi | B211: =B203*B204/B206 -> 375000 | C211: =B203*B204/B206 -> 375000
A212: Interessi variabili | B212: =B203*(EXP(B210/B206)-1) -> 385495.29 | C212: =B203*(EXP(C210/B206)-1) -> 460682.7
A213: Vswap | B213: =(B211-B212)*EXP(-B209*B208) -> -10357.142 | C213: =(C211-C212)*EXP(-C209*C208) -> -82035.403 | D213: =SUM(B213:C213) -> -92392.545
A215: 7.17. Considerate un OIS basato sul Sofr, con pagamenti semestrali. Solo una delle seguenti affermazioni sul tasso variabile relativo a un certo semestre è corretta. Quale?
A216: (a) Si determina alla fine del semestre, sulla base dei tassi Sofr giornalieri osservati durante quel semestre.
A217: (b) Viene fissato all’inizio del semestre ed è pari al tasso Sofr overnight osservato in quel giorno.
A218: (c) Viene fissato al momento della negoziazione dello swap e rimane invariato per tutta la sua durata.
A219: (d) Si determina utilizzando i tassi Sofr giornalieri osservati nel semestre precedente.
A221: (a)
A223: Il Sofr a 6 mesi viene calcolato capitalizzando giornalmente gli interessi in base ai tassi Sofr osservati durante il semestre di riferimento.
A224: È quindi noto solo quando sono stati osservati tutti i tassi giornalieri necessari per il calcolo, alla fine del semestre. Si tratta di un tasso «rivolto al passato» (backward looking), non di un tasso fissato all’inizio del periodo. Pertanto, la risposta corretta è quella sub (a).
A226: 7.18. Quale delle seguenti descrizioni è appropriata per un overnight indexed swap a 3 mesi?
A227: (a) Un contratto in cui si scambia ogni giorno, per 3 mesi, un tasso fisso con il tasso over-night.
A228: (b) Un contratto in cui si scambia ogni giorno, per 3 mesi, il Libor con il tasso overnight.
A229: (c) Un contratto in cui si scambia, tra 3 mesi, un tasso fisso con la media aritmetica dei tassi overnight osservata nei 3 mesi precedenti.
... A255: Il debitore può cambiare da un periodo all’altro, così da mantenere invariato il merito di credito iniziale dei nuovi prestiti. In questo senso, il tasso è «continuamente aggiornato» (continually refreshed). La risposta corretta è quella sub (c).

Sheet 8
A1: Capitolo 8 Cartolarizzazioni e Crisi Finanziaria del 2007-8
A3: 8.1. Solo uno dei seguenti eventi tende a far aumentare il prezzo delle case. Quale?
A4: (a) L’aumento dei tassi d’interesse.
A5: (b) La fissazione di un tetto al loan-to-value ratio dei mutui da parte delle autorità di vigilanza.
A6: (c) La riduzione del livello minimo del FICO score richiesto dalle banche per la concessione dei mutui.
A7: (d) L’aumento dei pignoramenti immobiliari.
A9: (c)
A11: L’aumento dei tassi d’interesse tende a far diminuire i prezzi delle case perché i compratori devono sostenere costi di finanziamento più elevati.
A12: La fissazione di un tetto al «rapporto tra l’importo del mutuo e il valore di mercato della casa» (loan to value ratio) fa sì che alcuni possibili acquirenti non riescano a ottenere i mutui che desiderano. Di conseguenza, la minore domanda di case ha un effetto depressivo sui prezzi.
A13: L’aumento dei «pignoramenti immobiliari» (foreclosures) fa aumentare l’offerta di case e anche questo si traduce in una riduzione dei prezzi degli immobili.
A14: Invece, se le banche allentano i propri standard nella concessione dei mutui (ad es. riducendo livello minimo del FICO score) la domanda di case aumenta perché più gente può ottenere un mutuo. Di conseguenza, i prezzi aumentano.
A16: 8.2. Solo una delle seguenti affermazioni sui mutui «senza rivalsa» (non-recourse) è esatta. Quale?
... A49: L’equity tranche assorbe il 10% delle perdite. Il restante 6% (= 16% − 10%) viene assorbito dalla mezzanine tranche. La dimensione della mezzanine tranche è pari al 10%. Pertanto, le perdite per la mezzanine tranche dell’ABS sono pari al 60% (= 6% / 10%) del capitale.
A51: LS / L | B51: 0.8
A52: LM / L | B52: 0.1
A53: LE / L | B53: 0.1
A54: Perdite sul portafoglio di mutui subprime | C54: Perdite sull'equity tranche dell’ABS | E54: Perdite sulla mezz. tranche dell’ABS | G54: Perdite sulla senior tranche dell’ABS
A56: 0.16 | C56: =MIN(A56,B53)/B53 -> 1 | E56: =MAX(MIN(A56-B53,B52),0)/B52 -> 0.6 | G56: =MAX(MIN(A56-B53-B52,B51),0)/B51 -> 0
A58: 8.5. Supponete che vengano creati più ABSs sulla base di portafogli di mutui subprime.
A59: Le quote di capitale allocate alle singole tranches sono: senior 80%, mezzanine 10%, equity 10% (i portafogli di mutui subprime hanno gli stessi tassi d’insolvenza).
A60: Viene poi creata una ABS CDO sulla base delle mezzanine tranches dell’ABS.
A61: L’allocazione del capitale alle singole tranches dell’ABS CDO è uguale a quella degli ABSs.
A62: Ognuno dei portafogli di mutui subprime subisce perdite pari al 16% del capitale.
A63: In percentuale del capitale della tranche, quali sono le perdite per la mezzanine tranche dell’ABS CDO?
A64: (a) 50%
A65: (b) 60%
A66: (c) 80%
A67: (d) 100%
A69: (d)
A71: Come mostra la risposta alla precedente domanda, la mezzanine tranche dell’ABS viene «cancellata» (wiped out) per il 60%. Il primo 10% di questo 60% viene assorbito dall’equity tranche dell’ABS CDO.
A72: Il successivo 10% viene assorbito dalla mezzanine tranche dell’ABS CDO. Il restante 40% (= 60% − 10% − 10%) viene assorbito dalla senior tranche dell’ABS CDO. Pertanto, la mezzanine tranche dell’ABS CDO viene cancellata per il 100%:
A74: LS / L | C74: 0.8
A75: LM / L | C75: 0.1
A76: LE / L | C76: 0.1
A77: LABS CDO, S / LABS CDO | C77: 0.8
A78: LABS CDO, M / LABS CDO | C78: 0.1
A79: LABS CDO, E/ LABS CDO | C79: 0.1
A80: LABS CDO, S / L | C80: =C77*C75 -> 0.08
A81: LABS CDO, M / L | C81: =C78*C75 -> 0.01
A82: LABS CDO, E / L | C82: =C79*C75 -> 0.01
A83: LS/ L + LABS CDO, S / L | C83: =C74+C80 -> 0.88
A84: Perdite sul portafoglio di mutui subprime | B84: Perdite sull'equity tranche dell’ABS | C84: Perdite sulla mezzanine tranche dell’ABS | D84: Perdite sulla senior tranche dell’ABS | E84: Perdite sull'ABS CDO
E85: equity tranche | F85: mezzanine tranche | G85: senior tranche
A86: 0.16 | B86: =MIN(A86,C76)/C76 -> 1 | C86: =MAX(MIN(A86-C76,C75)/C75,0) -> 0.6 | D86: =MAX(MIN(A86-C76-C75,C74)/C74,0) -> 0 | E86: =MIN(C86,C79)/C79 -> 1 | F86: =MAX(MIN(C86-C79,C78)/C78,0) -> 1 | G86: =MAX(MIN(C86-C79-C78,C77)/C77,0) -> 0.5
A88: 8.6. Supponete che vengano creati più ABSs sulla base di portafogli di mutui subprime.
A89: Le quote di capitale allocate alle singole tranches sono: senior 80%, mezzanine 10%, equity 10% (i portafogli di mutui subprime hanno gli stessi tassi d’insolvenza).
A90: Viene poi creata una ABS CDO sulla base delle mezzanine tranches.
A91: L’allocazione del capitale alle singole tranches dell’ABS CDO è uguale a quella degli ABSs.
A92: Ognuno dei portafogli di mutui subprime subisce perdite pari al 16% del capitale.
A93: In percentuale del capitale della tranche, quali sono le perdite per la senior tranche dell’ABS CDO?
A94: (a) 50%
A95: (b) 60%
A96: (c) 80%
A97: (d) 100%
A99: (a)
A101: Come mostra la risposta alla precedente domanda, la senior tranche dell’ABS CDO assorbe il 40% delle perdite. Pertanto, la senior tranche dell’ABS CDO viene cancellata per il 50%.
A103: LS / L | C103: 0.8
A104: LM / L | C104: 0.1
A105: LE / L | C105: 0.1
A106: LABS CDO, S / LABS CDO | C106: 0.8
A107: LABS CDO, M / LABS CDO | C107: 0.1
A108: LABS CDO, E/ LABS CDO | C108: 0.1
A109: LABS CDO, S / L | C109: =C106*C104 -> 0.08
A110: LABS CDO, M / L | C110: =C107*C104 -> 0.01
A111: LABS CDO, E / L | C111: =C108*C104 -> 0.01
A112: LS/ L + LABS CDO, S / L | C112: =C103+C109 -> 0.88
A113: Perdite sul portafoglio di mutui subprime | B113: Perdite sull'equity tranche dell’ABS | C113: Perdite sulla mezzanine tranche dell’ABS | D113: Perdite sulla senior tranche dell’ABS | E113: Perdite sull'ABS CDO
E114: equity tranche | F114: mezzanine tranche | G114: senior tranche
A115: 0.16 | B115: =MIN(A115,C105)/C105 -> 1 | C115: =MAX(MIN(A115-C105,C104)/C104,0) -> 0.6 | D115: =MAX(MIN(A115-C105-C104,C103)/C103,0) -> 0 | E115: =MIN(C115,C108)/C108 -> 1 | F115: =MAX(MIN(C115-C108,C107)/C107,0) -> 1 | G115: =MAX(MIN(C115-C108-C107,C106)/C106,0) -> 0.5
A117: 8.7. Cos’è che ha determinato le perdite di AIG?
A118: (a) L’acquisto di tranches basate su mutui subprime.
A119: (b) I forti investimenti in immobili.
A120: (c) I forti investimenti sul mercato azionario.
A121: (d) L’assicurazione delle tranches AAA delle ABS CDOs.
A123: (d)
A125: AIG assicurava le tranches AAA delle ABS CDOs.
A127: 8.8. Quale delle seguenti banche è sopravvissuta alla crisi senza dichiarare fallimento e senza essere acquistata da un’altra istituzione finanziaria?
A128: (a) Bear Stearns
A129: (b) Morgan Stanley
A130: (c) Lehman Brothers
A131: (d) Merrill Lynch
... A214: Le perdite sulle mezzanine tranches degli ABSs sono pari al 5% quando le perdite sui portafogli di mutui subprime sono pari al 5,5% (= 5% + 5% × 10%).
A216: LS / L | C216: 0.85
A217: LM / L | C217: 0.1
A218: LE / L | C218: 0.05
A219: LABS CDO, S / LABS CDO | C219: 0.85
A220: LABS CDO, M / LABS CDO | C220: 0.1
A221: LABS CDO, E/ LABS CDO | C221: 0.05
A222: LABS CDO, S / L | C222: =C219*C217 -> 0.085
A223: LABS CDO, M / L | C223: =C220*C217 -> 0.01
A224: LABS CDO, E / L | C224: =C221*C217 -> 0.005
A225: LS/ L + LABS CDO, S / L | C225: =C216+C222 -> 0.935
A226: Perdite sul portafoglio di mutui subprime | B226: Perdite sull'equity tranche dell’ABS | C226: Perdite sulla mezzanine tranche dell’ABS | D226: Perdite sulla senior tranche dell’ABS | E226: Perdite sull'ABS CDO
E227: equity tranche | F227: mezzanine tranche | G227: senior tranche
A228: 0.055 | B228: =MIN(A228,C218)/C218 -> 1 | C228: =MAX(MIN(A228-C218,C217)/C217,0) -> 0.05 | D228: =MAX(MIN(A228-C218-C217,C216)/C216,0) -> 0 | E228: =MIN(C228,C221)/C221 -> 1 | F228: =MAX(MIN(C228-C221,C220)/C220,0) -> 0 | G228: =MAX(MIN(C228-C221-C220,C219)/C219,0) -> 0
A230: 8.16. Supponete che vengano creati più ABSs sulla base di portafogli di mutui subprime.
A231: Le quote di capitale allocate alle singole tranches sono: senior 85%, mezzanine 10%, equity 5% (i portafogli di mutui subprime hanno gli stessi tassi d’insolvenza).
A232: Viene poi creata una ABS CDO sulla base delle mezzanine tranches.
A233: L’allocazione del capitale alle singole tranches dell’ABS CDO è uguale a quella degli ABSs.
A234: In percentuale del capitale, a quanto devono ammontare le perdite sui mutui prima che la senior tranche dell’ABS CDO subisca perdite?
...

Sheet 9
A1: Capitolo 9 XVAs
A3: 9.1. Quale dei seguenti non è un aggiustamento di bilancio?
A4: (a) CVA.
A5: (b) MVA.
A6: (c) ZVA.
A7: (d) KVA.
A9: (c)
A11: CVA sta per credit value adjustment. MVA sta per margin valuation adjustment. KVA sta per capital valuation adjustment. ZVA non è un aggiustamento di bilancio.
A13: 9.2. CVA è l’acronimo di ...
A14: (a) collateral value adjustment;
A15: (b) credit value adjustment;
A16: (c) credit value agreement;
... A64: Il valore attuale delle perdite attese è pari a $450.000 (= $1.000.000 × 0,015 + $2.000.000 × 0,015). Questo è il CVA della banca.
A66: PV(EL1) | B66: 1000000
A67: PV(EL2) | B67: 2000000
A68: PD1 | B68: 0.015
A69: PD2 | B69: 0.015
A71: CVA | B71: =B66*B68+B67*B69 -> 45000
A73: 9.7. Una banca ha in essere, con una certa controparte, tre contratti non assistiti da garanzie. Il valore corrente dei tre contratti, per la banca, è pari a +$10, −$20 e +$25 milioni.
A74: Se è stata sottoscritta la clausola di netting, qual è la massima perdita che la banca può subire nel caso in cui la controparte fallisca oggi?
A75: (a) $15 milioni.
A76: (b) $35 milioni.
A77: (c) $20 milioni.
A78: (d) $0.
A80: (a)
A82: In base alla clausola di netting, i tre contratti vanno considerati alla stregua di un’unica transazione.
A83: Il valore netto dei tre contratti, per la banca, è pari a +$15 (= +$10 −$20 +$25) milioni. Questo è il massimo importo che la banca potrebbe perdere nel caso in cui la controparte fallisca oggi.
A84: V1 | B84: 10
A85: V2 | B85: -20
A86: V3 | B86: 25
A87: V | B87: =SUM(B84:B86) -> 15
A89: 9.8. Quale dei seguenti contratti comporta il maggior rischio di credito?
A90: (a) Un contratto negoziato in borsa.
A91: (b) Un contratto OTC con utilizzo di una central clearing party.
A92: (c) Un contratto OTC con bilateral clearing e collateral agreement.
A93: (d) Un contratto OTC con bilateral clearing, ma senza collateral agreement.
A95: (d)
A97: Nel caso dei contratti negoziati in borsa e in quelli OTC con utilizzo di una central clearing party, il meccanismo del marking to market fa sì che il rischio di credito sia molto basso. Il rischio è maggiore in caso di bilateral clearing, soprattutto quando non ci sono garanzie.
A99: 9.9. FVA è l’acronimo di un aggiustamento che riguarda ...
A100: (a) il costo del funding initial margin;
A101: (b) il costo del funding variation margin;
A102: (c) il costo del capitale regolamentare;
A103: (d) nessuno dei costi sopra menzionati.
... A218: La provvista (positiva o negativa) che dipende dai variation margins è additiva rispetto ai singoli contratti.

Sheet 10
A1: Capitolo 10 Funzionamento dei Mercati delle Opzioni
A3: 10.1. Solo una delle seguenti frasi descrive un’opzione call. Quale?
A4: (a) Il diritto di comprare una certa attività a un certo prezzo.
A5: (b) L’obbligo di comprare una certa attività a un certo prezzo.
A6: (c) Il diritto di vendere una certa attività a un certo prezzo.
A7: (d) L’obbligo di vendere una certa attività a un certo prezzo.
A9: (a)
A11: Le opzioni call danno al compratore il diritto, non l’obbligo, di comprare una certa attività a un certo prezzo.
A13: 10.2. Solo una delle seguenti affermazioni è corretta. Quale?
A14: (a) La long call equivale a una short put.
A15: (b) La short call equivale a una long put.
A16: (c) La call su un’azione più l’azione stessa equivale a una put.
... A32: Dopo un «frazionamento» (stock split), il numero delle azioni cresce e il prezzo d’esercizio diminuisce. In questo caso, dopo un frazionamento 2 × 1, il numero delle azioni raddoppia e il prezzo d’esercizio si dimezza.
A34: Nput | B34: 100
A35: K | B35: 20
A36: n1 | B36: 2
A37: m1 | B37: 1
A39: K | B39: Nput
A40: =B35*B37/B36 -> 10 | B40: =B34*B36/B37 -> 200
A42: 10.4. Considerate una put, negoziata in borsa, che dà a un investitore il diritto di vendere 100 azioni a $20 l’una. Qual è la posizione dell’investitore dopo uno stock dividend del 25%?
A43: (a) Ha una put che gli dà il diritto di vendere 100 azioni a $20 l’una.
A44: (b) Ha una put che gli dà il diritto di vendere 75 azioni a $25 l’una.
A45: (c) Ha una put che gli dà il diritto di vendere 125 azioni a $15 l’una.
A46: (d) Ha una put che gli dà il diritto di vendere 125 azioni a $16 l’una.
A48: (d)
A50: L’«assegnazione gratuita» (stock dividend) in misura pari al 25% delle azioni detenute equivale a un frazionamento 5 × 4. Il numero delle azioni cresce del 25% (125 = 100 × 5/4) e il prezzo d’esercizio si riduce a 4/5 del precedente valore ($16 = 4/5 × $20).
A52: Nput | B52: 100
A53: K | B53: 20
A54: n1 | B54: 5
A55: m1 | B55: 4
A57: K | B57: Nput
A58: =B53*B55/B54 -> 16 | B58: =B52*B54/B55 -> 125
A60: 10.5. Considerate una put, negoziata in borsa, che dà a un investitore il diritto di vendere 100 azioni a $20 l’una. Qual è la posizione dell’investitore dopo un dividendo di $1?
A61: (a) Ha una put che gli dà il diritto di vendere 100 azioni a $20 l’una.
A62: (b) Ha una put che gli dà il diritto di vendere 100 azioni a $19 l’una.
A63: (c) Ha una put che gli dà il diritto di vendere 105 azioni a $19 l’una.
A64: (d) Ha una put che gli dà il diritto di vendere 105 azioni a $19,05 l’una.
A66: (a)
A68: Le opzioni non sono protette contro lo stacco dei dividendi, a meno che i dividendi non siano di importo insolitamente elevato.
A70: 10.6. Solo una delle seguenti frasi descrive le posizioni corte su opzioni. Quale?
A71: (a) Posizioni su opzioni con vita residua inferiore a 1 mese.
A72: (b) Posizioni su opzioni con vita residua inferiore a 3 mesi.
A73: (c) Posizioni su opzioni con vita residua inferiore a 6 mesi.
A74: (d) Posizioni in cui le opzioni vengono vendute.
... A180: Il payoff unitario è di $1 (= $70 − $69). Il premio unitario incassato inizialmente è di $4. Pertanto, il profitto netto unitario è pari a $3 (= $4 − $1). In totale, le opzioni vendute sono 500 (= 5 × 100). Pertanto il profitto netto complessivo è pari a $1.500.
A182: S0 | B182: 67
A183: N | B183: 5
A184: n | B184: 100
A185: K | B185: 70
A186: p | B186: 4
A187: ST | B187: 69
A189: Π | B189: =B183*B184*(B186-(B185-B187)) -> 1500
A191: 10.17. Un trader compra una call e vende una put con lo stesso prezzo d’esercizio e la stessa scadenza. A cosa equivale la sua posizione?
A192: (a) Un forward lungo.
A193: (b) Un forward corto.
A194: (c) L’acquisto a pronti del sottostante.
A195: (d) Nessuna delle precedenti risposte è corretta.
A197: (a)
A199: Sommando algebricamente i payoffs delle due opzioni si vede che la risposta corretta è quella sub (a): max(ST − K, 0) − max(K − ST, 0) = max(ST − K, 0) + min(ST − K, 0) = ST − K.
A201: 10.18. Il prezzo corrente di un’azione è pari a $64. Un trader compra 1 contratto put, con strike $60, scritto sull’azione quando il prezzo unitario della put è pari a $10. Per quale livello del prezzo dell’azione sottostante il trader consegue un profitto netto?
A202: (a) Quando il prezzo dell’azione è minore di $60.
A203: (b) Quando il prezzo dell’azione è minore di $64.
A204: (c) Quando il prezzo dell’azione è minore di $54.
A205: (d) Quando il prezzo dell’azione è minore di $50.
... A209: Il payoff unitario della put deve essere maggiore del premio pagato, che è pari a $10. Pertanto, il prezzo dell’azione deve essere minore di $50 ( = $60 − $10).
A211: S0 | B211: 64
A212: N | B212: 1
A213: n | B213: 100
A214: K | B214: 60
A215: p | B215: 10
A217: ST | B217: =B214-B215 -> 50
A219: 10.19. Considerate una call e una put con lo stesso prezzo d’esercizio e la stessa scadenza. Solo una delle seguenti affermazioni è corretta. Quale?
A220: (a) Entrambe le opzioni possono essere in the money.
A221: (b) Entrambe le opzioni possono essere out of the money.
A222: (c) Una delle due opzioni deve essere in the money.
A223: (d) Una delle due opzioni deve essere at the money o in the money.
A225: (d)
A227: Se il prezzo dell’azione è maggiore del prezzo d’esercizio, la call è in the money e la put è out of the money.
A228: Se il prezzo dell’azione è minore del prezzo d’esercizio, la call è out of the money e la put è in the money.
A229: Se il prezzo dell’azione è uguale al prezzo d’esercizio, entrambe le opzioni sono at the money.
A231: 10.20. In quali dei seguenti casi non si configura una constructive sale?
A232: (a) Il proprietario vende l’attività a pronti.
A233: (b) Il proprietario compra una in-the-money put scritta sull’attività.
... A240: Nel caso sub (b), non si ha una «vendita presunta» (constructive sale). Pertanto, l’acquisto di una deep-in-the-money put rappresenta un modo per bloccare quasi certamente un profitto senza innescare un’immediata passività fiscale.

Sheet 11
A1: Capitolo 11 Proprietà Fondamentali delle Opzioni su Azioni
A3: 11.1. Quando il prezzo dell’azione sottostante aumenta, mentre tutto il resto rimane invariato, solo una delle seguenti affermazioni è corretta. Quale?
A4: (a) Il valore delle calls e delle puts aumenta.
A5: (b) Il valore delle calls e delle puts diminuisce.
A6: (c) Il valore delle calls aumenta, mentre il valore delle puts diminuisce.
A7: (d) Il valore delle calls diminuisce, mentre il valore delle puts aumenta.
A9: (c)
A11: Quando il prezzo dell’azione sottostante aumenta, il valore delle calls aumenta, mentre il valore delle puts diminuisce.
A13: 11.2. Quando il prezzo d’esercizio aumenta, mentre tutto il resto rimane invariato, solo una delle seguenti affermazioni è corretta. Quale?
A14: (a) Il valore delle calls e delle puts aumenta.
A15: (b) Il valore delle calls e delle puts diminuisce.
A16: (c) Il valore delle calls aumenta, mentre il valore delle puts diminuisce.
... A64: Di solito, quando la vita residua aumenta da X a Y, il valore delle opzioni europee aumenta. Tuttavia, non è sempre così. Se ci si aspetta che venga pagato un dividendo elevato tra X e Y, il valore delle calls europee potrebbe diminuire.
A65: 4
A66: 11.7. Qual è il limite inferiore per il prezzo di una call europea a 1 anno, scritta su un titolo che non paga dividendi, se il prezzo dell’azione sottostante è di $30, il prezzo d’esercizio è di $25
A67: e il tasso d’interesse privo di rischio (composto continuamente) è del 4 per cento annuo?
A68: (a) $5,00
A69: (b) $5,98
A70: (c) $4,98
A71: (d) $3,98
A73: (b)
A75: Il limite inferiore è pari a max(S0 − Ke−rT, 0). In questo caso è pari a $5,98.
A77: S0 | B77: 30
A78: K | B78: 25
A79: T | B79: 1
A80: r | B80: 0.04
A82: lim. inf. | B82: =MAX(B77-B78*EXP(-B80*B79),0) -> 5.980264
A84: 11.8. Qual è il limite inferiore per il prezzo di una put europea a 2 anni, scritta su un titolo che non paga dividendi, se il prezzo dell’azione sottostante è di $50, il prezzo d’esercizio è di $54
A85: e il tasso d’interesse privo di rischio (composto continuamente) è del 3 per cento annuo?
A86: (a) $4,00
A87: (b) $3,86
A88: (c) $2,86
A89: (d) $0,86
A91: (d)
A93: Il limite inferiore è pari a max(Ke−rT − S0, 0). In questo caso è pari a $0,86.
A95: S0 | B95: 50
A96: K | B96: 54
A97: T | B97: 2
A98: r | B98: 0.03
A100: lim. inf. | B100: =MAX(B96*EXP(-B98*B97)-B95,0) -> 0.85528481
A102: 11.9. Supponete che i valori attuali siano calcolati dalla fine all’inizio della vita dell’opzione. Solo una delle seguenti affermazioni non è corretta. Quale?
A103: (a) Il valore corrente di una put americana è sempre minore del valore attuale del prezzo d’esercizio.
A104: (b) Il valore corrente di una put europea è sempre minore del valore attuale del prezzo d’esercizio.
A105: (c) Il valore corrente di una call europea è sempre minore del prezzo del sottostante.
A106: (d) Il valore corrente di una call americana è sempre minore del prezzo del sottostante.
A108: (a)
A110: Se è ottimale esercitare una put americana oggi e il prezzo del sottostante è molto basso, il valore corrente delle put americana è maggiore del valore attuale del prezzo d’esercizio.
A112: 11.10. Quale delle seguenti frasi descrive meglio il valore intrinseco di un’opzione?
A113: (a) Il valore che l’opzione avrebbe se il possessore l’esercitasse subito o dovesse abbandonarla.
A114: (b) Il prezzo Black-Scholes-Merton dell’opzione.
A115: (c) Il limite inferiore del prezzo dell’opzione.
A116: (d) L’importo pagato per acquistare l’opzione.
... A172: In base alla put-call parity si ha c + Ke−rT = p + S0, , da cui p = c − S0 + Ke−rT. In questo caso, S0 = $51, K = $50, T = 1, r = 0,06 e c = $6. Pertanto, p = $2,09.
A174: c | B174: 6
A175: K | B175: 50
A176: T | B176: 1
A177: S0 | B177: 51
A178: r | B178: 0.06
A180: p | B180: =B174-B177+B175*EXP(-B178*B176) -> 2.0882267
A182: 11.16. Il prezzo di una call europea, con prezzo d’esercizio di $50 e scadenza tra 1 anno, è di $6. Il prezzo corrente dell’azione sottostante è di $51 e la zero curve è piatta al livello del 6% (composto continuamente).
A183: Ci si aspetta che tra 6 mesi verrà pagato un dividendo di $1. Qual è il valore di una put europea, con prezzo d’esercizio di $50 e scadenza tra 1 anno, scritta sullo stesso titolo?
A184: (a) $8,97
A185: (b) $6,97
A186: (c) $3,06
A187: (d) $1,12
A189: (c)
A191: In base alla put-call parity si ha c + Ke−rT = p + S0 − D, da cui p = c − (S0 − D) + Ke−rT. In questo caso, S0 = $51, K = $50, T = 1, r = 0,06, c = $6 e D = $1e−0,06×0,5. Pertanto, p = $3,06.
A193: c | B193: 6
A194: K | B194: 50
A195: T | B195: 1
A196: S0 | B196: 51
A197: r | B197: 0.06
A198: d | B198: 1
A199: t | B199: 0.5
A201: p | B201: =B193-(B196-B198*EXP(-B197*B199))+B194*EXP(-B197*B195) -> 3.0586722
A203: 11.17. Considerate una call e una put con lo stesso prezzo d’esercizio e la stessa scadenza. Alle 10 di un certo giorno il prezzo della call è di $3 e il prezzo della put è di $4.
A204: Alle 10:01 giunge sul mercato una notizia che non ha effetti sul prezzo dell’azione ma fa aumentare la sua volatilità, per cui il prezzo della call sale a $4,5. Solo una delle seguenti affermazioni è corretta. Quale?
A205: (a) Il prezzo della put sale a $6,0.
A206: (b) Il prezzo della put scende a $2,0.
A207: (c) Il prezzo della put sale a $5,5.
A208: (d) È possibile che non ci siano effetti sul prezzo della put.
A210: (c)
A212: Il prezzo della call sale di $1,5 (= $4,5 − $3). In base alla put-call parity, il prezzo della put deve aumentare nella stessa misura. Pertanto, il prezzo della put sale a $5,5.
A214: c1 | B214: 3
A215: p1 | B215: 4
A216: c2 | B216: 4.5
A218: p2 | B218: =B215+(B216-B214) -> 5.5
A220: 11.18. I tassi d’interesse sono nulli. Il prezzo corrente di una call, con strike di $50 e scadenza tra 1 anno, è pari a $6. Il prezzo corrente di una put, con strike di $50 e scadenza tra 1 anno, è pari a $7.
A221: Il prezzo corrente dell’azione sottostante è di $49. Solo una delle seguenti affermazioni è corretta. Quale?
A222: (a) Il prezzo della call è relativamente alto rispetto al prezzo della put.
A223: (b) Il prezzo della put è relativamente alto rispetto al prezzo della call.
A224: (c) Entrambe le opzioni non sono valutate correttamente.
A225: (d) Nessuna delle precedenti risposte è corretta.
A227: (d)
A229: Dato che i tassi d’interesse sono nulli, si ha c + K = p + S0. Il lato sinistro della put-call parity è pari a $56 (= $6 + $50). Anche il lato destro è pari a $56 (= $7 + $49). Non ci sono errori di valutazione.
A231: K | B231: 50
A232: T | B232: 1
A233: c | B233: 6
A234: p | B234: 7
A235: S0 | B235: 49
...

Sheet 12
A1: Capitolo 12 Strategie Operative mediante Opzioni
A3: 12.1. Solo una delle seguenti frasi definisce un bull spread. Quale?
A4: (a) Comprare una call con strike basso e vendere una call con strike alto.
A5: (b) Comprare una call con strike alto e vendere una call con strike basso.
A6: (c) Comprare una call con strike basso e vendere una put con strike alto.
A7: (d) Comprare una put con strike basso e vendere una call con strike alto.
A9: (a)
A11: Il bull spread si ottiene comprando una call con strike basso e vendendo una call con strike alto. In alternativa, può essere ottenuto comprando una put con strike basso e vendendo una put con strike alto.
A13: 12.2. Solo una delle seguenti frasi definisce un bear spread. Quale?
A14: (a) Comprare una call con strike basso e vendere una call con strike alto.
A15: (b) Comprare una call con strike alto e vendere una call con strike basso.
A16: (c) Comprare una call con strike basso e vendere una put con strike alto.
... A173: Lo zero-coupon bond a 1 anno vale circa $951 (= $1.000 e−0,05×1). Per acquistare la call, restano quindi $49.
A175: r | B175: 0.05
A176: T | B176: 1
A177: L | B177: 1000
A179: c | B179: =B177*(1-EXP(-B175*B176)) -> 48.770575
A181: 12.18. Tre opzioni europee, con strikes $60, $65 e $70, costano $18, $14 e $11, rispettivamente.
A182: Per creare un butterfly spread lungo vengono utilizzate 400 calls. Tenendo conto del costo delle opzioni, qual è il massimo profitto netto che si può realizzare?
A183: (a) $100
A184: (b) $200
A185: (c) $300
A186: (d) $400
A188: (d)
A190: Il butterfly spread lungo richiede l’acquisto di 100 calls con strike $60, la vendita di 200 calls con strike $65 e l’acquisto di 100 calls con strike $70.
A191: Il massimo profitto viene realizzato quando il prezzo dell’azione è pari allo strike intermedio, che è pari a $65.
A192: In questo caso, i payoffs delle opzioni sono pari a $500 [= 100 × ($65 − $60)], $0 e $0, rispettivamente.
A193: Il payoff complessivo è quindi pari a $500. Il costo sostenuto per acquistare il butterfly spread lungo è pari a $100 (= 100 × $18 − 200 × $14 + 100 × $11).
A194: Pertanto, il massimo profitto netto che si può realizzare è pari a $400 (= $500 − $100).
B196: K
B197: 60 | C197: 65 | D197: 70
A198: c | B198: 18 | C198: 14 | D198: 11
A199: N | B199: 100 | C199: -200 | D199: 100
A200: ST | B200: =C197 -> 65
A202: Costo | B202: =B199*B198 -> 1800 | C202: =C199*C198 -> -2800 | D202: =D199*D198 -> 1100 | E202: =SUM(B202:D202) -> 100
A203: Payoff | B203: =B199*MAX($B$200-B197,0) -> 500 | C203: =C199*MAX($B$200-C197,0) -> 0 | D203: =D199*MAX($B$200-D197,0) -> 0 | E203: =SUM(B203:D203) -> 500
A204: Π | B204: =E203-E202 -> 400
A206: 12.19. Tre opzioni europee, con strikes $60, $65 e $70, costano $18, $14 e $11, rispettivamente.
A207: Per creare un butterfly spread lungo vengono utilizzate 400 calls. Tenendo conto del costo delle opzioni, qual è la massima perdita netta che si può subìre?
A208: (a) $100
A209: (b) $200
A210: (c) $300
A211: (d) $400
A213: (a)
A215: Il butterfly spread lungo richiede l’acquisto di 100 calls con strike $60, la vendita di 200 calls con strike $65 e l’acquisto di 100 calls con strike $70.
A216: La massima perdita si ha quando il prezzo dell’azione è ST ≤ $60 o ST ≥ $70.
A217: In questi casi, il payoff complessivo è pari a $0. Il costo sostenuto per acquistare il butterfly spread lungo è pari a $100 (= 100 × $18 − 200 × $14 + 100 × $11).
A218: Pertanto, la massima perdita netta che si può subìre è pari a $100.
B220: K
B221: 60 | C221: 65 | D221: 70
A222: c | B222: 18 | C222: 14 | D222: 11
A223: N | B223: 100 | C223: -200 | D223: 100
A224: ST | B224: =B221 -> 60 | C224: =D221 -> 70
A226: Costo | B226: =B223*B222 -> 1800 | C226: =C223*C222 -> -2800 | D226: =D223*D222 -> 1100 | E226: =SUM(B226:D226) -> 100
A227: Payoff | B227: =B223*MAX($B$224-B221,0) -> 0 | C227: =C223*MAX($B$224-C221,0) -> 0 | D227: =D223*MAX($B$224-D221,0) -> 0 | E227: =SUM(B227:D227) -> 0
A228: Π | B228: =E227-E226 -> -100
A230: 12.20. Due opzioni call europee, con prezzi d’esercizio di $35 e $40 e scadenza tra 6 mesi, costano, rispettivamente, $6 e $4. Per creare un bull spread vengono utilizzate 200 calls. Qual è il massimo profitto che si può realizzare?
A231: (a) $100
A232: (b) $200
A233: (c) $300
A234: (d) $400
A236: (c)
A238: Il bull spread richiede l’acquisto di 100 calls con strike $35 e la vendita di 100 calls con strike $40. Il costo è pari a $200 (= 100 × $6 − 100 × $4).
A239: Il massimo profitto viene realizzato quando il prezzo dell’azione è ST ≥ $40. In tal caso, il payoff complessivo pari a $500. Pertanto, il massimo profitto che si può realizzare è pari a $300 (= $500 − $200).
B241: K
B242: 35 | C242: 40
A243: c | B243: 6 | C243: 4
A244: N | B244: 100 | C244: -100
A245: ST | B245: 40
A247: Costo | B247: =B244*B243 -> 600 | C247: =C244*C243 -> -400 | D247: =SUM(B247:C247) -> 200
A248: Payoff | B248: =B244*MAX($B$245-B242,0) -> 500 | C248: =C244*MAX($B$245-C242,0) -> 0 | D248: =SUM(B248:C248) -> 500
A249: Π | B249: =D248-D247 -> 300

Sheet 13
A1: Capitolo 13 Alberi Binomiali
A3: 13.1. Il prezzo corrente di un’azione è $30 e ci si aspetta che nei prossimi 6 mesi salga a $36 o scenda a $26.
A4: Il tasso d’interesse privo di rischio è nullo. Quale posizione sull’azione è necessaria per coprire una posizione corta su una call a 6 mesi con prezzo d’esercizio di $32?
A5: (a) Lunga su 0,6 azioni.
A6: (b) Lunga su 0,4 azioni.
A7: (c) Corta su 0,6 azioni.
A8: (d) Corta su 0,4 azioni.
A10: (b)
A12: Il valore della call a scadenza è pari a $4 [= max($36 − $32, $0)] in caso di rialzo o a $0 [= max($26 − $32, $0)] in caso di ribasso.
A13: Se Δ è la quantità di azioni da detenere, occorre che $36 Δ − $4 = $26 Δ − $0, da cui Δ = 0,4.
A14: Pertanto, occorre assumere una posizione lunga su 0,4 azioni.
A16: K | B16: 32
A17: T | B17: 0.5
A18: S0 | B18: 30
A19: u | B19: =36/B18 -> 1.2
A20: d | B20: =26/B18 -> 0.86666667
A21: r | B21: 0
A23: Δ | B23: =(MAX(B18*B19-B16,0)-MAX(B18*B20-B16,0))/(B18*B19-B18*B20) -> 0.4
A25: 13.2. Il prezzo corrente di un’azione è $30 e ci si aspetta che nei prossimi 6 mesi salga a $36 o scenda a $26.
A26: Il tasso d’interesse privo di rischio è nullo. Qual è la probabilità neutrale verso il rischio che il prezzo del titolo salga a $36?
A27: (a) 0,60
A28: (b) 0,50
A29: (c) 0,40
A30: (d) 0,30
A32: (c)
A34: La formula per calcolare la probabilità di rialzo, p, in un mondo neutrale verso il rischio, è:
A36: In questo caso si ha u = 1,2 (= $36 / $30) e d = 0,8667 (= $26 / $30). Inoltre, r = 0 e T = 0,5. Pertanto, in base alla formula, p = 0,40.
A38: K | B38: 32
A39: T | B39: 0.5
A40: S0 | B40: 30
A41: u | B41: =36/B40 -> 1.2
A42: d | B42: =26/B40 -> 0.86666667
A43: r | B43: 0
A45: p | B45: =(EXP(B43*B39)-B42)/(B41-B42) -> 0.4
A47: 13.3. Il prezzo corrente di un’azione è $30 e ci si aspetta che nei prossimi 6 mesi salga a $36 o scenda a $26.
A48: Il tasso d’interesse privo di rischio è nullo. Qual è il valore corrente di una call con prezzo d’esercizio di $32 e scadenza tra 6 mesi?
A49: (a) $1,6
A50: (b) $2,0
A51: (c) $2,4
A52: (d) $3,0
A54: (a)
A56: La formula per calcolare la probabilità di rialzo, p, in un mondo neutrale verso il rischio, è:
A58: In questo caso si ha u = 1,2 (= $36 / $30) e d = 0,8667 (= $26 / $30). Inoltre, r = 0 e T = 0,5. Pertanto, in base alla formula, p = 0,40.
A59: Il payoff della call è pari $4 [= max($36 − $32, 0)] in caso di rialzo e a $0 [= max($26 − $32, 0)] in caso di ribasso. Pertanto, il valore corrente è pari a $1,60.
A61: K | B61: 32
A62: T | B62: 0.5
A63: S0 | B63: 30
A64: u | B64: =36/B63 -> 1.2
A65: d | B65: =26/B63 -> 0.86666667
A66: r | B66: 0
A68: p | B68: =(EXP(B66*B62)-B65)/(B64-B65) -> 0.4
A69: call | B69: =(MAX(B63*B64-B61,0)*B68+MAX(B63*B65-B61,0)*(1-B68))*EXP(-B66*B62) -> 1.6
A71: 13.4. Il prezzo corrente di un’azione che non paga dividendi è $40 e ci si aspetta che nel prossimo anno salga a $42 o scenda a $37.
A72: Quale posizione sull’azione è necessaria per coprire una posizione lunga su una put a 1 anno con prezzo d’esercizio di $41?
A73: (a) Lunga su 0,2 azioni.
A74: (b) Corta su 0,2 azioni.
A75: (c) Lunga su 0,8 azioni.
A76: (d) Corta su 0,8 azioni.
A78: (c)
A80: Il valore della put a scadenza è pari a $0 [= max($41 − $42, $0)] in caso di rialzo o a $4 [= max($41 − $37, $0)] in caso di ribasso. Se Δ è la quantità di azioni da detenere, occorre che $42 Δ + $0 = $37 Δ + $4, da cui Δ = 0,8.
A81: Pertanto, occorre assumere una posizione lunga su 0,8 azioni.
A83: K | B83: 41
A84: T | B84: 1
A85: S0 | B85: 40
A86: u | B86: =42/B85 -> 1.05
A87: d | B87: =37/B85 -> 0.925
A89: Δ | B89: =(MAX(B83-B85*B87,0)-MAX(B83-B85*B86,0))/(B85*B86-B85*B87) -> 0.8
A91: 13.5. Il prezzo corrente di un’azione che non paga dividendi è $40 e ci si aspetta che nel prossimo anno salga a $42 o scenda a $37.
A92: Il tasso d’interesse privo di rischio è pari al 2%. Qual è il valore corrente di una put a 1 anno con prezzo d’esercizio di $41?
A93: (a) $3,93
A94: (b) $2,93
A95: (c) $1,93
A96: (d) $0,93
A98: (d)
A100: La formula per calcolare la probabilità di rialzo, p, in un mondo neutrale verso il rischio, è:
A102: In questo caso si ha u = 1,05 (= $42 / $40) e d = 0,925 (= $37 / $40). Inoltre, r = 0,02 e T = 1. Pertanto, in base alla formula, p = 0,7616.
A103: Il payoff della put è pari $0 [= max($41 − $42, 0)] in caso di rialzo e a $4 [= max($41 − $37, 0)] in caso di ribasso. Pertanto, il valore corrente è pari a $0,93.
A105: K | B105: 41
A106: T | B106: 1
A107: S0 | B107: 40
A108: u | B108: =42/B107 -> 1.05
A109: d | B109: =37/B107 -> 0.925
A110: r | B110: 0.02
A112: p | B112: =(EXP(B110*B106)-B109)/(B108-B109) -> 0.76161072
A113: put | B113: =(MAX(B105-B107*B108,0)*B112+MAX(B105-B107*B109,0)*(1-B112))*EXP(-B110*B106) -> 0.93467542
A115: 13.6. Considerate la procedura utilizzata per la valutazione delle opzioni americane con gli alberi binomiali. Solo una delle seguenti affermazioni è corretta. Quale?
A116: (a) Si deve verificare la convenienza dell’esercizio anticipato in tutti i nodi in cui l’opzione è in the money.
A117: (b) Si deve verificare la convenienza dell’esercizio anticipato in tutti i nodi finali.
A118: (c) Si deve verificare la convenienza dell’esercizio anticipato nei nodi finali e in quelli immediatamente precedenti.
A119: (d) Nessuna delle precedenti risposte è corretta.
A121: (a)
A123: Quando si valutano le opzioni americane con gli alberi binomiali, si deve verificare la convenienza dell’esercizio anticipato in tutti i nodi in cui l’opzione è in the money (è inutile effettuare la verifica quando l’opzione è out of the money).
A125: 13.7. Negli alberi binomiali utilizzati per valutare le opzioni su azioni, qual è il tasso di rendimento atteso delle azioni?
A126: (a) È pari a zero.
A127: (b) È pari al tasso di rendimento richiesto dal mercato.
A128: (c) È pari al tasso d’interesse privo di rischio.
A129: (d) È impossibile rispondere senza avere altre informazioni.
... A187: L’albero è il seguente:
E188: =C190*B204 -> 36.3
E189: =MAX(E188-B200,0) -> 4.3
...

Sheet 14
A1: Capitolo 14 Processi di Wiener e Lemma di Itô
A3: 14.1. Una variabile, x, il cui livello corrente è 10, segue un processo di Wiener generalizzato dx = adt + bdz dove a = 2, b = 3 e il tempo è misurato in anni.
A4: Qual è il valore atteso di x tra 3 anni?
A5: (a) 12
A6: (b) 14
A7: (c) 16
A8: (d) 18
A10: (c)
A12: Il «tasso di deriva» (drift rate) annuo è pari a 2. Pertanto, l’incremento atteso in tre anni è pari a 6 (= 2 × 3) e il valore atteso di x tra 3 anni è pari a 16 (= 10 + 6).
A14: x | B14: 10
A15: a | B15: 2
A16: b | B16: 3
A17: T | B17: 3
A19: a T | B19: =B15*B17 -> 6
A20: E(x) | B20: =B14+B15*B17 -> 16
A22: 14.2. Una variabile, x, il cui livello corrente è 10, segue un processo di Wiener generalizzato dx = adt + bdz dove a = 3, b = 4 e il tempo è misurato in anni.
A23: Qual è la deviazione standard di x tra 4 anni?
A24: (a) 4
A25: (b) 8
A26: (c) 12
A27: (d) 16
A29: (b)
A31: Il «tasso di varianza» (variance rate) annuo è pari a 16 (= 42). Pertanto, la varianza di x tra 4 anni è pari a 64 (= 16 × 4) e la deviazione standard di x tra 4 anni è pari a 8 (= √64).
A33: x | B33: 10
A34: a | B34: 3
A35: b | B35: 4
A36: T | B36: 4
A38: b2 | B38: =B35^2 -> 16
A39: var(x) | B39: =B35^2*B36 -> 64
A40: std(x) | B40: =SQRT(B35^2*B36) -> 8
A42: 14.3. Una variabile, x, il cui livello corrente è 10, segue un processo di Wiener generalizzato dx = adt + bdz dove a = 3, b = 4 e il tempo è misurato in anni.
A43: Qual è la deviazione standard di x tra 3 mesi?
A44: (a) 1
A45: (b) 2
A46: (c) 3
A47: (d) 4
A49: (b)
A51: Il «tasso di varianza» (variance rate) annuo è pari a 16 (= 42). Pertanto, la varianza di x tra 4 anni è pari a 64 (= 16 × 4) e la deviazione standard di x tra 4 anni è pari a 8 (= √64).
A53: x | B53: 10
A54: a | B54: 3
A55: b | B55: 4
A56: T | B56: =3/12 -> 0.25
A58: b2 | B58: =B55^2 -> 16
A59: var(x) | B59: =B55^2*B56 -> 4
A60: std(x) | B60: =SQRT(B55^2*B56) -> 2
A62: 14.4. Se x segue un processo di Wiener, qual è la varianza di x tra t anni?
A63: (a) t
A64: (b) t2
A65: (c) √t
A66: (d) t4
A68: (a)
A70: La varianza della variazione di x in un intervallo di tempo dt è pari a dt. Il «tasso di varianza» (variance rate), ossia la varianza per unità di tempo, è quindi pari a 1. Pertanto, la varianza di x tra t anni è pari a t (= t × 1).
A72: 14.5. Una variabile X segue il processo dX = mX dt + sX dz dove z segue un processo di Wiener. Qual è il coefficiente di dz nel processo seguito dalla variabile X2?
A73: (a) sX
A74: (b) sX2
A75: (c) 2sX2
A76: (d) msX
... A124: Nei 5 anni, il tasso di deriva complessivo è pari a 24 (= 6 + 18). Pertanto, dato che il valore iniziale di x è 0, il valore atteso di x tra 5 anni è pari a 24.
A126: x | B126: 0
A127: T1 | B127: 2
A128: T2 | B128: 3
A129: a1 | B129: 3
A130: a2 | B130: 6
A131: b1 | B131: 4
A132: b2 | B132: 3
A134: E(x) | B134: =B126+B129*B127+B130*B128 -> 24
A136: 14.10. Una variabile, x, il cui livello corrente è 0, segue un processo di Wiener generalizzato dx = adt + bdz dove il tempo è misurato in anni.
A137: Nei primi 2 anni a = 3 e b = 4. Nei 3 anni successivi a = 6 e b = 3. Qual è la deviazione standard di x tra 5 anni?
A138: (a) 6,2
A139: (b) 6,7
A140: (c) 7,2
A141: (d) 7,7
A143: (d)
A145: Il tasso di varianza annuo per i primi 2 anni è pari a 16 (= 42).
A146: Il tasso di varianza annuo per i successivi 3 anni è pari a 9 (= 32).
A147: Pertanto, la varianza di x tra 5 anni è pari a 59 (= 2 × 16 + 3 × 9) e la deviazione standard di x tra 5 anni è pari a 7,7 (= √59).
A149: x | B149: 0
A150: T1 | B150: 2
A151: T2 | B151: 3
A152: a1 | B152: 3
A153: a2 | B153: 6
A154: b1 | B154: 4
A155: b2 | B155: 3
A157: var(x) | B157: =B150*B154^2+B151*B155^2 -> 59
A158: std(x) | B158: =SQRT(B157) -> 7.6811457
A160: 14.11. Una variabile x segue il processo dx = b dz, dove z segue un processo di Wiener. Qual è il processo seguito da y = ex ?
A161: (a) dy = b y dz
A162: (b) dy = ½ b2 y dt + b y dz
A163: (c) dy = (y + ½ b2 y) dt + b y dz
A164: (d) dy = ½ b2 y dt + b dz
A166: (b)
A168: In base al lemma di Itô, il processo seguito da y è dy = ½ b2 ex dt + b ex dz. Sostituendo y = ex, si ottiene dy = ½ b2 y dt + b y dz.
A170: 14.12. Sia r il tasso d’interesse privo di rischio. Se il prezzo di un’azione cresce al tasso m con volatilità s, a quale tasso cresce il prezzo forward di un contratto forward, con scadenza T, scritto sull’azione?
A171: (a) m
A172: (b) m − s2/2
A173: (c) m − r
A174: (d) r − s2/2
... A219: La deviazione standard del prezzo dell’azione tra 1 giorno è pari a $0,26.
A221: μ | B221: 0.12
A222: σ | B222: 0.25
...

Sheet 15
A1: Capitolo 15 Modello Black-Scholes-Merton
A3: 15.1. Considerate le ipotesi del modello Black-Scholes-Merton. Solo una delle seguenti affermazioni è corretta. Quale?
A4: (a) Il tasso di rendimento dell’azione nel prossimo istante di tempo si distribuisce in modo log-normale.
A5: (b) Il prezzo dell’azione in un futuro istante di tempo si distribuisce in modo log-normale.
A6: (c) Il prezzo dell’azione in un futuro istante di tempo si distribuisce in modo normale.
A7: (d) Nessuna delle precedenti risposte è corretta.
A9: (b)
A11: Il modello Black-Scholes-Merton assume che il tasso di rendimento di un’azione nel prossimo istante di tempo si distribuisca in modo normale. Questo implica che il prezzo dell’azione in un futuro istante di tempo si distribuisce in modo log-normale.
A13: 15.2. In quale anno sono stati pubblicati gli articoli «fondamentali» (path-breaking) di Black & Scholes e Merton?
A14: (a) 1983
A15: (b) 1984
A16: (c) 1974
... A42: La stima della deviazione standard della variazione del prezzo dell’azione nella prossima settimana è $2,77.
A44: S0 | B44: 100
A45: σ | B45: 0.2
A46: T | B46: =1/52 -> 0.019230769
A48: S σ √T | B48: =B44*B45*SQRT(B46) -> 2.773501
A50: 15.5. Nel modello Black-Scholes-Merton, N(d1) indica:
A51: (a) l’area della funzione di densità della normale standardizzata compresa tra 0 e d1.
A52: (b) l’area della funzione di densità della normale standardizzata compresa tra –∞ e d1.
A53: (c) l’area della funzione di densità della normale standardizzata compresa tra d1 e +∞.
A54: (d) l’area della funzione di densità della normale standardizzata compresa tra –d1 e d1.
A56: (b)
A58: Il campo di definizione di una variabile casuale normale va da −∞ a +∞. N(d1) indica l’area compresa tra −∞ e d1.
A60: 15.6. Se l’azione sottostante stacca un dividendo durante la vita di una call:
A61: (a) l’esercizio anticipato della call non è mai ottimale.
A62: (b) l’esercizio anticipato della call può essere ottimale un qualsiasi momento della sua vita;
A63: (c) l’esercizio anticipato della call può essere ottimale solo immediatamente dopo la data di stacco del dividendo.
A64: (d) Nessuna delle precedenti risposte è corretta.
... A129: Il valore atteso del tasso di rendimento a 1 anno (composto continuamente) è pari a μ − σ2/2. In questo caso, è pari all’8% (= 0,1 − 0,22/2).
A131: μ | B131: 0.1
A132: σ | B132: 0.2
A134: μ − σ2/2 | B134: =B131-B132^2/2 -> 0.08
A136: 15.13. Un investitore ha ottenuto i seguenti tassi di rendimento (composti annualmente) in 3 anni consecutivi: 2%, 12%, −10%. Qual è il tasso medio annuo equivalente (composto annualmente)?
A137: (a) 1,33%
A138: (b) 1,23%
A139: (c) 1,13%
A140: (d) 0,93%
A142: (d)
A144: Alla fine dei 3 anni un capitale iniziale di $100 sarebbe diventato pari a $102,816 (= $100 × 1,02 × 1,12 × 0,90). Il tasso medio annuo equivalente (composto annualmente) è lo 0,93%:
A146: Il fattore di capitalizzazione calcolato in base al tasso medio equivalente, ossia 1,0093, è la media geometrica dei singoli montanti (1,02; 1,12; 0,90).
A148: 1 + R1 | B148: 1.02
A149: 1 + R2 | B149: 1.12
A150: 1 + R3 | B150: 0.9
A152: Montante | B152: =B148*B149*B150 -> 1.02816
A153: R | B153: =B152^(1/3)-1 -> 0.0092999102
A155: 15.14. Solo una delle seguenti affermazioni non è corretta. Quale?
A156: (a) Il principio della valutazione neutrale verso il rischio offre prezzi che sono corretti solo in un mondo in cui gli investitori sono neutrali verso il rischio.
A157: (b) Il valore delle opzioni può essere determinato assumendo che gli investitori siano neutrali verso il rischio.
A158: (c) Quando si applica il principio della valutazione neutrale verso il rischio, il tasso di ren-dimento atteso da una qualsiasi attività finanziaria è pari al tasso d’interesse privo di ri-schio.
A159: (d) Quando si applica il principio della valutazione neutrale verso il rischio, i pagamenti attesi vengono attualizzati in base al tasso d’interesse privo di rischio.
A161: (a)
A163: Il principio della valutazione neutrale verso il rischio offre prezzi che sono sempre corretti, quale che sia l’atteggiamento degli investitori nei confronti del rischio.
A164: Quando si applica il principio della valutazione neutrale verso il rischio, il tasso di rendimento atteso da una qualsiasi attività finanziaria è pari al tasso privo di rischio e i pagamenti attesi vengono attualizzati in base al tasso privo di rischio.
A166: 15.15. Quale metodo si usa per estendere la formula Black-Scholes-Merton al caso in cui l’azione sottostante la call europea paghi un dividendo di importo noto?
A167: (a) Ridurre la scadenza dell’opzione ponendola uguale alla data in cui il dividendo verrà pa-gato.
A168: (b) Sottrarre il dividendo dal prezzo dell’azione.
A169: (c) Aggiungere il dividendo al prezzo dell’azione.
... A196: In questo caso S0 = K = $20, r = 0,06, σ = 0,2 e T = 0,25 per cui Ke−rT = $20 e−0,06×0,25 = $19,7. Inoltre, d1 = [ln($20/$20) + (0,06 + 0,22/2) × 0,25]/(0,2 × √0,25) = 0,2 e d2 = 0,2 – 0,2 × √0,25 = 0,1. Pertanto, la risposta corretta è quella sub (b).
A198: S0 | B198: 20
A199: K | B199: 20
A200: r | B200: 0.06
A201: σ | B201: 0.2
A202: T | B202: =3/12 -> 0.25
A204: K e−rT | B204: =B199*EXP(-B200*B202) -> 19.702239
A205: d1 | B205: =(LN(B198/B199)+(B200+B201^2/2)*B202)/(B201*SQRT(B202)) -> 0.2
A206: d2 | B206: =B205-B201*SQRT(B202) -> 0.1
A208: 15.18. Il prezzo corrente di un titolo che non paga dividendi è pari a $20 e la sua volatilità è pari al 20%. Il tasso d’interesse privo di rischio è pari al 6%. Qual è il valore corrente di una put, con strike $20 e scadenza tra 3 mesi, scritta sul titolo?
A209: (a) $19,7 × N(−0,1) − $20 × N(−0,2)
A210: (b) $20 × N(−0,1) − $20 × N(−0,2)
A211: (c) $19,7 × N(−0,2) − $20 × N(−0,1)
A212: (d) $20 × N(−0,1) − $20 × N(−0,1)
A214: (a)
A216: La formula per la put è
A218: In questo caso S0 = K = $20, r = 0,06, σ = 0,2 e T = 0,25 per cui Ke−rT = $20 e−0,06×0,25 = $19,7. Inoltre, d1 = [ln($20/$20) + (0,06 + 0,22/2) × 0,25]/(0,2 × √0,25) = 0,2 e d2 = 0,2 – 0,2 × √0,25 = 0,1. Pertanto, la risposta corretta è quella sub (a).
A220: S0 | B220: 20
A221: K | B221: 20
A222: r | B222: 0.06
A223: σ | B223: 0.2
A224: T | B224: =3/12 -> 0.25
A226: K e−rT | B226: =B221*EXP(-B222*B224) -> 19.702239
A227: d1 | B227: =(LN(B220/B221)+(B222+B223^2/2)*B224)/(B223*SQRT(B224)) -> 0.2
A228: d2 | B228: =B227-B223*SQRT(B224) -> 0.1
A230: 15.19. In 6 consecutivi venerdì, il prezzo di un’azione è risultato pari a $20, $22, $19, $21, $24 e $24. In base a questi dati, qual è la stima della volatilità annua dell’azione?
A231: (a) 52%
A232: (b) 62%
A233: (c) 72%
A234: (d) 82%
A236: (d)
A238: Il rapporto tra i prezzi osservati nei primi due venerdì è 1,1 (= $22 / $20). Il tasso di rendi-mento logaritmico settimanale è pari al 9,53% [= ln(1,1)]. Analogamente, i tassi di rendimento logaritmici relativi alle altre settimane sono: −14,66%, 10,01%, 13,35% e 0%.
A239: La deviazione standard di 9,53%, −14,66%, 10,01%, 13,35% e 0% è pari all’11,38%. Pertanto, la volatilità settimanale dell’azione è pari all’11,38%. Questo livello corrisponde a una volatilità annua pari all’82% (= 11,38% × √52). Pertanto, la risposta corretta è quella sub (d).
B241: 1 | C241: 2 | D241: 3 | E241: 4 | F241: 5 | G241: 6
A242: S | B242: 20 | C242: 22 | D242: 19 | E242: 21 | F242: 24 | G242: 24
A243: St / St−1 | C243: =C242/B242 -> 1.1 | D243: =D242/C242 -> 0.86363636 | E243: =E242/D242 -> 1.1052632 | F243: =F242/E242 -> 1.1428571 | G243: =G242/F242 -> 1
A244: ln(St / St−2) | C244: =LN(C243) -> 0.09531018 | D244: =LN(D243) -> -0.14660347 | E244: =LN(E243) -> 0.10008346 | F244: =LN(F243) -> 0.13353139 | G244: =LN(G243) -> 0
A245: σw | B245: =_xlfn.STDEV.S(C244:G244) -> 0.11377138
A246: σ | B246: =B245*SQRT(52) -> 0.82041711
A248: 15.20. La volatilità di un’azione è pari al 18% annuo. Qual è la volatilità mensile?
A249: (a) 1,5%
A250: (b) 3,0%
...

Sheet 16
A1: Capitolo 16 Stock Options per Impiegati e Dirigenti
A3: 16.1. Solo una delle seguenti affermazioni è corretta. Quale?
A4: (a) In genere, le stock options vengono detenute fino alla scadenza.
A5: (b) Le stock options tendono a essere esercitate prima delle corrispondenti opzioni negoziate in borsa o sul mercato OTC.
A6: (c) Le stock options tendono a essere esercitate più tardi delle corrispondenti opzioni negoziate in borsa o sul mercato OTC.
A7: (d) In genere, le stock options tendono a essere esercitate il prima possibile.
A9: (b)
A11: Le stock options tendono a essere esercitate prima delle corrispondenti opzioni negoziate in borsa o sul mercato OTC.
A12: Dato che non possono essere cedute a terzi, l’esercizio rappresenta l’unico modo per monetizzare il valore delle stock options. Le risposte sub (a), (c) e (d) non sono corrette.
A14: 16.2. Solo una delle seguenti affermazioni sulle stock options non è corretta. Quale?
A15: (a) È previsto un vesting period.
A16: (b) Possono essere cedute a altri dipendenti.
... A204: Le risposte (a), (b) e (c) spiegano i motivi della popolarità delle stock options nel settore delle start-ups.

Sheet 17
A1: Capitolo 17 Opzioni su Indici Azionari e Valute
A3: 17.1. Una società sa che riceverà valuta estera e vuole coprire la sua esposizione valutaria con un range forward. Cosa dovrebbe fare? Solo una delle seguenti affermazioni è corretta.
A4: (a) Comprare una put e vendere una call scritte sulla valuta estera. Il prezzo d’esercizio del-la put deve essere più elevato di quello della call.
A5: (b) Comprare una put e vendere una call scritte sulla valuta estera. Il prezzo d’esercizio della put deve essere più basso di quello della call.
A6: (c) Comprare una call e vendere una put scritte sulla valuta estera. Il prezzo d’esercizio della put deve essere più elevato di quello della call.
A7: (d) Comprare una call e vendere una put scritte sulla valuta estera. Il prezzo d’esercizio della put deve essere più basso di quello della call.
A9: (b)
A11: La società vuole che il prezzo che riceverà in cambio della valuta estera sia compreso tra K1 e K2 (K1 < K2). Pertanto, compra una put con strike K1 e vende una call con strike K2.
A13: 17.2. Una società sa che dovrà acquistare valuta estera e vuole coprire la sua esposizione valutaria con un range forward. Cosa dovrebbe fare? Solo una delle seguenti affermazioni è corretta.
A14: (a) Comprare una put e vendere una call scritte sulla valuta estera. Il prezzo d’esercizio della put deve essere più elevato di quello della call.
A15: (b) Comprare una put e vendere una call scritte sulla valuta estera. Il prezzo d’esercizio della put deve essere più basso di quello della call.
A16: (c) Comprare una call e vendere una put scritte sulla valuta estera. Il prezzo d’esercizio della put deve essere più elevato di quello della call.
... A54: Il gestore dovrebbe comprare 200 [= $10.000.000 / ($500 × 100)] contratti. I contratti vanno comprati, e non venduti, perché devono offrire un payoff positivo quando il mercato scende.
A56: VA | B56: 10000000
A57: T | B57: 0.5
A58: Lim. inf. | B58: 9500000
A59: S0 | B59: 500
A60: Size | B60: 100
A61: r | B61: 0.1
A62: qA | B62: 0
A63: qS | B63: 0
A64: β | B64: 1
A65: β* | B65: 0
A67: N | B67: =(B64-B65)*B56/(B60*B59) -> 200
A69: 17.6. Il gestore di un portafoglio azionario del valore di $10 milioni teme che il mercato possa rapidamente scendere nei prossimi 6 mesi
A70: e vuole utilizzare le opzioni su un indice azionario per assicurare il portafoglio contro la possibilità che scenda al di sotto dei $9,5 milioni.
A71: Il livello corrente dell’indice è di $500. Ogni contratto put è scritto su 100 volte il livello dell’indice. Se il beta del portafoglio è pari a 1, quale dovrebbe essere lo strike delle opzioni put?
A72: (a) $425
A73: (b) $450
A74: (c) $475
A75: (d) $500
A77: (c)
A79: Quando il valore del portafoglio scende del 5%, ci si attende che anche l’indice scenda del 5%. Pertanto, lo strike dovrebbe essere pari a $475 (= 0,95 × $500).
A81: VA | B81: 10000000
A82: T | B82: 0.5
A83: Lim. inf. | B83: 9500000
A84: S0 | B84: 500
A85: r | B85: 0.1
A86: β | B86: 1
A88: K | B88: =B84*(1+(B83/B81-1-(1-B86)*B85*B82)/B86) -> 475
A91: 17.7. Il gestore di un portafoglio azionario del valore di $10 milioni teme che il mercato possa rapidamente scendere nei prossimi 6 mesi
A92: e vuole utilizzare le opzioni su un indice azionario per assicurare il portafoglio contro la possibilità che scenda al di sotto dei $9,5 milioni.
A93: Il livello corrente dell’indice è di $500. Ogni contratto put è scritto su 100 volte il livello dell’indice. Se il beta del portafoglio è pari a 0,5, che posizione dovrebbe assumere sulle opzioni put?
A94: (a) Vendere 200 contratti.
A95: (b) Acquistare 200 contratti.
A96: (c) Vendere 100 contratti.
A97: (d) Acquistare 100 contratti.
A99: (d)
A101: Il gestore dovrebbe acquistare 100 [= 0,5 × $10.000.000 / ($500 × 100)] contratti. I contratti vanno acquistati perché devono offrire un payoff positivo quando il mercato scende.
A103: VA | B103: 10000000
A104: T | B104: 0.5
A105: Lim. inf. | B105: 9500000
A106: S0 | B106: 500
A107: Size | B107: 100
A108: r | B108: 0.1
A109: β | B109: 0.5
A111: N | B111: =B109*B103/(B106*B107) -> 100
A113: 17.8. Il gestore di un portafoglio azionario del valore di $10 milioni teme che il mercato possa rapidamente scendere nei prossimi 6 mesi
A114: e vuole utilizzare le opzioni su un indice azionario per assicurare il portafoglio contro la possibilità che scenda al di sotto dei $9,5 milioni.
A115: Il livello corrente dell’indice è di $500. Ogni contratto put è scritto su 100 volte il livello dell’indice. Se il beta del portafoglio è pari a 0,5, quale dovrebbe essere lo strike delle opzioni put?
A116: Assumete che il tasso d’interesse privo di rischio sia pari al 10% annuo (composto continuamente) e che non vengano pagati dividendi né sul portafoglio né sui titoli su cui si basa l’indice.
A117: (a) $395
A118: (b) $405
A119: (c) $415
A120: (d) $425
A122: (d)
A124: Il tasso d’interesse privo di rischio è pari al 5% semestrale (=10%/2).
A125: Dato che il beta del portafoglio è pari a 0,5, un tasso di variazione dell’indice pari al −15% comporta una riduzione del 5% nel valore del portafoglio [−5% = 5% + 0,5 × (−15% − 5%)].
A126: Pertanto, lo strike delle opzioni put dovrebbe essere pari a $425 [= (1 − 0,15) × $500].
A128: VA | B128: 10000000
A129: T | B129: 0.5
A130: Lim. inf. | B130: 9500000
A131: S0 | B131: 500
A132: r | B132: 0.1
A133: β | B133: 0.5
A135: K | B135: =B131*(1+(B130/B128-1-(1-B133)*B132*B129)/B133) -> 425
A137: 17.9. Considerate una put europea, con prezzo d’esercizio di $1.050 e scadenza tra 6 mesi, scritta su un indice il cui livello corrente è di $1.000.
A138: Il dividend yield dell’indice è del 2% annuo e il tasso d’interesse privo di rischio è del 4% annuo.
A139: Qual è il limite inferiore per il prezzo della put?
A140: (a) $50,00
A141: (b) $43,11
A142: (c) $29,21
A143: (d) $39,16
A145: (d)
A147: Il limite inferiore per il prezzo della put è K e−rT − S0 e−qT. Il prezzo della put non può scendere al di sotto di questo livello perché altrimenti ci sarebbero opportunità di arbitraggio.
A148: Nel nostro caso, K = $1.050, S0 = $1.000, T = 0,5, r = 0,04 e q = 0,02. Pertanto, il limite inferiore della put è pari a $39,16.
A150: S0 | B150: 1000
A151: K | B151: 1050
A152: T | B152: 0.5
A153: q | B153: 0.02
A154: r | B154: 0.04
A156: Lim. inf. | B156: =B151*EXP(-B154*B152)-B150*EXP(-B153*B152) -> 39.158773
A158: 17.10. Considerate una call europea, con prezzo d’esercizio di $0,9100 e scadenza tra 1 anno, scritta su una valuta il cui tasso di cambio spot è di $1,0000.
A159: Il tasso d’interesse privo di rischio in dollari è del 5 per cento annuo e il tasso privo di rischio estero è del 3 per cento annuo.
A160: Qual è il limite inferiore per il prezzo della call?
A161: (a) $0,1048
A162: (b) $0,0900
A163: (c) $0,1344
A164: (d) $0,1211
A166: (a)
...

Sheet 18
A1: Capitolo 18 Opzioni su Futures e Modello di Black
A3: 18.1. Quale posizione assume chi esercita una put scritta su un contratto futures? Una sola delle seguenti affermazioni è esatta:
A4: (a) Una posizione lunga sul contratto futures.
A5: (b) Una posizione corta sul contratto futures.
A6: (c) Una posizione lunga sull’attività sottostante il contratto futures.
A7: (d) Nessuna delle precedenti risposte è corretta.
A9: (b)
A11: Chi esercita una futures put assume una posizione corta sul contratto futures. La posizione può essere immediatamente chiusa senza costi aggiuntivi.
A13: 18.2. Quale posizione assume chi esercita una call scritta su un contratto futures? Una sola delle seguenti affermazioni è esatta:
A14: (a) Una posizione lunga sul contratto futures.
A15: (b) Una posizione corta sul contratto futures.
A16: (c) Una posizione lunga sull’attività sottostante il contratto futures.
... A73: La probabilità di rialzo è pari a (1 − d)/(u − d). In questo caso, u = 1,1 (= ¢44 / ¢40) e d = 0,85 (= ¢34 / ¢40). Pertanto, la probabilità di rialzo è pari a 0,6.
A75: F0 | B75: 40
A76: F0 u | B76: 44
A77: F0 d | B77: 34
A78: r | B78: 0.06
A80: u | B80: =B76/B75 -> 1.1
A81: d | B81: =B77/B75 -> 0.85
A82: p | B82: =(1-B81)/(B80-B81) -> 0.6
A84: 18.8. Il prezzo futures corrente di una certa attività è di ¢40. Ci si aspetta che nei prossimi 6 mesi salga a ¢44 o scenda a ¢34.
A85: I tassi d’interesse privi di rischio sono al livello del 6 per cento. Qual è il valore di una put, con prezzo d’esercizio di ¢37 e scadenza tra 6 mesi, scritta sul futures?
A86: (a) ¢3,00
A87: (b) ¢2,91
A88: (c) ¢1,16
A89: (d) ¢1,20
A91: (c)
A93: La probabilità di rialzo è pari a (1 − d)/(u − d). In questo caso, u = 1,1 (= ¢44 / ¢40) e d = 0,85 (= ¢34 / ¢40). Pertanto, la probabilità di rialzo è pari a 0,6. La futures put paga ¢0 in caso di rialzo e ¢3 (= ¢37 − ¢34) in caso di ribasso. Pertanto, il suo valore è pari a ¢1,16.
A95: F0 | B95: 40
A96: F0 u | B96: 44
A97: F0 d | B97: 34
A98: r | B98: 0.06
A99: K | B99: 37
A100: T | B100: 0.5
A102: u | B102: =B96/B95 -> 1.1
A103: d | B103: =B97/B95 -> 0.85
A104: p | B104: =(1-B103)/(B102-B103) -> 0.6
A105: put | B105: =EXP(-B98*B100)*(MAX(B99-B95*B102,0)*B104+MAX(B99-B95*B103,0)*(1-B104)) -> 1.1645346
A107: 18.9. Il prezzo futures corrente di una certa attività è di ¢40. Ci si aspetta che nei prossimi 6 mesi salga a ¢44 o scenda a ¢34.
A108: I tassi d’interesse privi di rischio sono al livello del 6 per cento. Qual è il valore di una call, con prezzo d’esercizio di ¢39 e scadenza tra 6 mesi, scritta sul futures?
A109: (a) ¢5,00
A110: (b) ¢2,91
A111: (c) ¢3,00
A112: (d) ¢4,21
A114: (b)
A116: La probabilità di rialzo è pari a (1 − d)/(u − d). In questo caso, u = 1,1 (= ¢44 / ¢40) e d = 0,85 (= ¢34 / ¢40). Pertanto, la probabilità di rialzo è pari a 0,6. La futures call paga ¢5 (= ¢44 − ¢39) in caso di rialzo e ¢0 in caso di ribasso. Pertanto, il suo valore è pari a ¢2,91.
A118: F0 | B118: 40
A119: F0 u | B119: 44
A120: F0 d | B120: 34
A121: r | B121: 0.06
A122: K | B122: 39
A123: T | B123: 0.5
A125: u | B125: =B119/B118 -> 1.1
A126: d | B126: =B120/B118 -> 0.85
A127: p | B127: =(1-B126)/(B125-B126) -> 0.6
A128: call | B128: =EXP(-B121*B123)*(MAX(B118*B125-B122,0)*B127+MAX(B118*B126-B122,0)*(1-B127)) -> 2.9113366
A130: 18.10. Solo una delle seguenti affermazioni sulle futures options è corretta. Quale?
A131: (a) In borsa vengono negoziate esclusivamente futures options europee.
A132: (b) In borsa vengono negoziate esclusivamente futures options americane.
A133: (c) In borsa vengono negoziate sia futures options europee sia futures options americane.
A134: (d) Le futures options vengono negoziate esclusivamente nel mercato OTC.
A136: (c)
A138: In borsa vengono negoziate entrambe le tipologie di futures options, europee e americane.
A140: 18.11. Considerate le September futures options. Solo una delle seguenti affermazioni è corretta. Quale?
A141: (a) Le opzioni scadono a settembre.
A142: (b) Le opzioni iniziano ad essere quotate in settembre.
A143: (c) Il mese di consegna del futures sottostante è settembre.
A144: (d) Settembre è il primo mese in cui le opzioni possono essere esercitate.
... A203: In questo caso F0 = K = $50, r = 0,05, σ = 0,2 e T = 0,25 per cui F0 e−rT = Ke−rT = $50 e−0,05 × 0,25 = $49,38. Inoltre, d1 = [ln($50/$50) + (0,22/2) × 0,25]/(0,2 × √0,25) = 0,05 e d2 = 0,05 – 0,2 × √0,25 = −0,05. Pertanto, la risposta corretta è quella sub (a).
A205: F0 | B205: 50
A206: K | B206: 50
A207: r | B207: 0.05
A208: σ | B208: 0.2
A209: T | B209: =3/12 -> 0.25
A211: S0 e−rT | B211: =B205*EXP(-B207*B209) -> 49.37889
A212: K e−rT | B212: =B206*EXP(-B207*B209) -> 49.37889
A213: d1 | B213: =(LN(B205/B206)+(B208^2/2)*B209)/(B208*SQRT(B209)) -> 0.05
A214: d2 | B214: =B213-B208*SQRT(B209) -> -0.05
A216: 18.17. In un mondo neutrale verso il rischio, qual è il tasso di crescita atteso del prezzo futures di un indice azionario?
A217: (a) La differenza tra il tasso d’interesse privo di rischio e il dividend yield.
A218: (b) Il tasso d’interesse privo di rischio.
A219: (c) Il dividend yield.
A220: (d) Zero.
A222: (d)
A224: In un mondo neutrale verso il rischio, il tasso di crescita atteso di un qualsiasi prezzo futures è pari a zero.
A226: 18.18. Supponete di utilizzare il modello di Black per valutare un’opzione europea scritta sul prezzo spot di una certa attività finanziaria. Solo una delle seguenti affermazioni non è corretta. Quale?
A227: (a) È necessario conoscere il prezzo forward / futures relativo a un contratto che ha la stessa scadenza dell’opzione.
A228: (b) Non è necessario stimare il reddito del sottostante durante la vita dell’opzione.
A229: (c) Non è necessario stimare il tasso d’interesse privo di rischio.
A230: (d) Il sottostante può essere un bene d’investimento o un bene di consumo.
... A255: La put-call parity è c + K e -rT = p + F0 e -rT. Pertanto F0 = $18,95:
A257: c | B257: 3
A258: p | B258: 4
A259: S0 | B259: 20
A260: K | B260: 20
A261: T | B261: 1
A262: r | B262: 0.05
A264: F0 | B264: =B260+(B257-B258)*EXP(B262*B261) -> 18.948729

Sheet 19
A1: Capitolo 19 Lettere Greche
A3: 19.1. Il delta di una call è 0,3. Un trader ne ha vendute 1.000 e vuole che il suo portafoglio sia neutrale in termini di delta. Cosa dovrebbe fare?
A4: (a) Vendere 300 azioni.
A5: (b) Comprare 300 azioni.
A6: (c) Vendere 700 azioni.
A7: (d) Comprare 700 azioni.
A9: (b)
A11: Quando il prezzo dell’azione aumenta in misura pari a un piccolo importo, il prezzo della call aumenta in misura pari al 30% di tale importo. Dato che ha venduto 1.000 calls, il trader è immunizzato dalle variazioni di prezzo dell’azione se compra 300 azioni.
A12: In tal modo, il delta del portafoglio passa da −300 [= 0,3 × (−1.000)] a 0 [= 0,3 × (−1.000) + 1 × (+300)].
A14: Δc | B14: 0.3
A15: Nc | B15: -1000
A17: NS | B17: =-B14*B15 -> 300
A19: 19.2. Cos’è il theta?
A20: (a) Il theta è la derivata del delta rispetto al prezzo del sottostante.
A21: (b) Il theta è la derivata del valore del portafoglio rispetto al tempo.
A22: (c) Il theta è la derivata del valore del portafoglio rispetto al tasso d’interesse.
A23: (d) Nessuna delle precedenti risposte è corretta.
A25: (b)
A27: Il theta è la derivata del valore del portafoglio rispetto al tempo.
A29: 19.3. Cos’è il gamma?
A30: (a) Il gamma è la derivata del delta rispetto al prezzo del sottostante.
A31: (b) Il gamma è la derivata del valore del portafoglio rispetto al tempo.
A32: (c) Il gamma è la derivata del valore del portafoglio rispetto al tasso d’interesse.
A33: (d) Nessuna delle precedenti risposte è corretta.
... A76: (a)
A78: Delta | B78: 2400
A79: Gamma | B79: -10
A80: opz_delta | B80: 0.5
A81: opz_gamma | B81: 0.04
A83: lunga su | B83: =-B79/B81 -> 250 | C83: opzioni
A85: 19.8. Un trader segue una strategia stop loss per coprire una posizione corta su una call, con prezzo d’esercizio di $0,7000 e scadenza tra 3 mesi, scritta su un tasso di cambio.
A86: Il trader copre l’opzione quando il tasso di cambio è di $0,7005 e chiude la copertura, tornando a una posizione scoperta, quando il tasso di cambio è di $0,6995. Il valore dell’opzione è di $0,1. Solo una delle seguenti affermazioni non è corretta. Quale?
A87: (a) Il costo delle compravendite può risultare nullo, per cui il trader guadagna $0,1 per ogni call venduta.
A88: (b) Il costo delle compravendite può risultare sensibilmente maggiore di $0,1 per ogni call venduta, per cui il trader chiude l’operazione in perdita.
A89: (c) Il valore attuale dei profitti e delle perdite sulle compravendite dovrebbe essere all’incirca pari – in media – a $0,1 per ogni call venduta.
A90: (d) La copertura funziona ragionevolmente bene.
A92: (d)
A94: Le coperture funzionano ragionevolmente bene se il loro costo è sempre vicino al valore teorico delle opzioni.
A95: La strategia stop loss non gode di questa proprietà. Il suo costo può essere nullo o molto superiore al valore teorico dell’opzione.
A96: In media, il costo della copertura non si discosta molto dal valore Black-Scholes-Merton dell’opzione, ma gli scostamenti dalla media possono essere piuttosto ampi.
A98: 19.9. Assicurarsi che un portafoglio resti neutrale in termini di delta è un esempio di strategia:
A99: (a) stop-loss;
... A162: Il prezzo futures è pari a F0 = S0 e(r−q) T. Pertanto, il delta del futures rispetto al prezzo spot dell’indice è pari a e(r−q) T. Nel nostro caso, si ha e(0,05−0,02) × 1 = 1,03.
A164: r | B164: 0.05
A165: q | B165: 0.02
A166: T | B166: 1
A168: Δ | B168: =EXP((B164-B165)*B166) -> 1.0304545
A170: 19.15. Il gamma di un portafoglio delta neutral è pari a 500. Di quanto varia il valore del portafoglio in seguito a un jump di $3 nel prezzo del sottostante?
A171: (a) +$2.250
A172: (b) −$2.250
A173: (c) +$750
A174: (d) −$750
A176: (a)
A178: Il portafoglio aumenta di valore in misura pari a ½Γ(ΔS)2 = ½ × 500 × ($3)2 = $2.250.
A180: Γ | B180: 500
A181: ΔS | B181: 3
A183: ½Γ(ΔS)2 | B183: =(1/2)*B180*B181^2 -> 2250
A185: 19.16. Per quale delle seguenti opzioni il vega tende ad essere più elevato?
A186: (a) Opzioni at the money.
A187: (b) Opzioni out of the money.
A188: (c) Opzioni in the money.
A189: (d) Opzioni con vita residua molto breve.
A191: (a)
A193: Il vega tende ad essere più elevato per le opzioni at the money. Si veda la Figura 19.11.
A195: 19.17. Il delta di una call scritta su un titolo che non paga dividendi è pari a 0,4. Qual è il delta della corrispondente put?
A196: (a) −0,4
A197: (b) +0,4
A198: (c) −0,6
A199: (d) +0,6
... A203: Il delta di una call scritta su un titolo che non paga dividendi è N(d1), mentre il delta della corrispondente put è N(d1) − 1. Quando N(d1) = 0,4, N(d1) − 1 = 0,4 − 1 = −0,6.
A205: Δc | B205: 0.4
A207: Δp | B207: =B205-1 -> -0.6
A209: 19.18. Considerate una call, con strike $30 e scadenza 6 mesi, scritta su un titolo che non paga dividendi. Il prezzo corrente dell’azione è di $28 e la sua volatilità è del 25%. Il tasso d’in¬teresse privo di rischio è pari al 4%. Qual è il delta della call?
A210: (a) N(−0,1342)
A211: (b) N(−0,1888)
A212: (c) N(−0,2034)
A213: (d) N(−0,2241)
A215: (b)
A217: Il delta è pari a N(d1), dove
A219: In questo caso, si ha
A221: S0 | B221: 28
A222: K | B222: 30
A223: T | B223: =6/12 -> 0.5
A224: σ | B224: 0.25
A225: r | B225: 0.04
A227: d1 | B227: =(LN(B221/B222)+(B225+B224^2/2)*B223)/(B224*SQRT(B223)) -> -0.18875719
A229: 19.19. Quale delle seguenti non è una lettera dell’alfabeto greco?
A230: (a) delta
A231: (b) rho
A232: (c) vega
A233: (d) gamma
A235: (c)
A237: Il vega non è una lettera dell’alfabeto greco, anche se viene considerata una “greca” dagli option traders.
A239: 19.20. Considerate una posizione lunga su un’opzione. Solo una delle seguenti affermazioni è corretta. Quale?
A240: (a) Il gamma e il vega sono negativi.
A241: (b) Il gamma è negativo, mentre il vega è positivo.
A242: (c) Il gamma è positivo, mentre il vega è negativo.
A243: (d) Il gamma e il vega sono positivi.
... A247: Il gamma e il vega di una posizione lunga su un’opzione sono entrambi positivi. Non importa se l’opzione è di tipo call o put.

Sheet 20
A1: Capitolo 20 Volatility Smiles e Volatility Surfaces
A3: 20.1. Solo una delle seguenti affermazioni sui grafici che illustrano i volatility smiles è corretta. Quale?
A4: (a) Sull’asse orizzontale c’è la volatilità implicita e sull’asse verticale il prezzo d’esercizio.
A5: (b) Sull’asse orizzontale c’è la volatilità storica e sull’asse verticale il prezzo d’esercizio.
A6: (c) Sull’asse orizzontale c’è il prezzo d’esercizio e sull’asse verticale la volatilità implicita.
A7: (d) Sull’asse orizzontale c’è il prezzo d’esercizio e sull’asse verticale la volatilità storica.
A9: (c)
A11: I volatility smiles mostrano la volatilità implicita (che è sull’asse verticale) in funzione del prezzo d’esercizio (che è sull’asse orizzontale).
A13: 20.2. Una sola delle seguenti affermazioni è esatta. Quale?
A14: (a) Il volatility smile per le puts europee è uguale al volatility smile per le calls europee.
A15: (b) Il volatility smile per le puts europee è uguale al volatility smile per le puts americane.
A16: (c) Il volatility smile per le calls europee è uguale al volatility smile per le calls americane.
... A158: La tavola riportata nel testo suggerisce una frequenza pari allo 0,03%, ossia 3/10.000. Dato che i giorni lavorativi in un anno sono 252, un evento a 6 deviazioni standard si verifica 1 volta ogni 13 [= 1/(0,03% × 252) anni.
A160: prob | B160: 0.0003
A161: n | B161: 252
A163: Anni | B163: =1/(B160*B161) -> 13.227513
A165: 20.16. Confrontate i tassi di variazione logaritmici dei tassi di cambio giornalieri con quelli di una variabile casuale normale che ha uguale media e uguale varianza. Solo una delle seguenti affermazioni è corretta. Quale?
A166: (a) Ai tassi di variazione piccoli e grandi, ma non a quelli intermedi, sono associate probabilità più elevate rispetto a quelle della corrispondente distribuzione normale.
A167: (b) I tassi di variazione piccoli sono meno probabili e quelli grandi sono più probabili dei tassi di variazione della corrispondente variabile casuale normale.
A168: (c) I tassi di variazione grandi sono meno probabili e quelli piccoli sono più probabili dei tassi di variazione della corrispondente variabile casuale normale.
A169: (d) Ai tassi di variazione piccoli e grandi, ma non a quelli intermedi, sono associate probabilità meno elevate rispetto a quelle della corrispondente distribuzione normale.
A171: (a)
A173: I tassi di variazione piccoli e grandi si verificano con frequenza maggiore rispetto a quelli della corrispondente variabile casuale normale.
A175: 20.17. Cosa succede quando la vita residua delle opzioni su valute aumenta? Solo una delle seguenti affermazioni è corretta. Quale?
A176: (a) Il volatility smile tende a diventare più pronunciato.
A177: (b) Il volatility smile tende a diventare meno pronunciato.
A178: (c) Il volatility smile tende a diventare dapprima meno pronunciato e poi più pronunciato.
A179: (d) Il volatility smile resta più o meno invariato.
... A224: Poi interpoliamo tra le scadenze. La volatilità implicita in un’opzione a 10 mesi con strike $1,12 è pari al 19,52%:
C226: 6 | D226: 12 | F226: 10
A227: Surface | B227: 1.1 | C227: 0.2 | D227: 0.188 | F227: =C227+(F226-C226)/(D226-C226)*(D227-C227) -> 0.192
B228: 1.2 | C228: 0.22 | D228: 0.202 | F228: =C228+(F226-C226)/(D226-C226)*(D228-C228) -> 0.208
B230: 1.12 | C230: =C227+(B230-B227)/(B228-B227)*(C228-C227) -> 0.204 | D230: =D227+(B230-B227)/(B228-B227)*(D228-D227) -> 0.1908 | F230: =C230+(F226-C226)/(D226-C226)*(D230-C230) -> 0.1952 | G230: =F227+(B230-B227)/(B228-B227)*(F228-F227) -> 0.1952

Sheet 21
A1: Capitolo 21 Procedure Numeriche
A3: 21.1. Quanti nodi ci sono alla fine di un albero binomiale a 5 stadi, costruito secondo Cox-Ross-Rubinstein?
A4: (a) 4
A5: (b) 5
A6: (c) 6
A7: (d) 7
A9: (c)
A11: Il numero dei nodi finali in un albero binomiale a n stadi è pari a n + 1. Pertanto, la risposta corretta per un albero a n = 5 stadi, è 6 (= 5 + 1).
A13: n | B13: 5
A15: Nodi finali | B15: =B13+1 -> 6
A17: 21.2. Solo una delle seguenti lettere greche non può essere calcolata in base a un unico albero binomiale. Quale?
A18: (a) delta
A19: (b) gamma
A20: (c) theta
A21: (d) vega
A23: (d)
A25: Per calcolare il vega occorre aumentare leggermente la volatilità e costruire un nuovo albero. Le altre tre greche possono essere calcolate in base a un unico albero.
A27: 21.3. Considerate il parametro u nell’albero binomiale di Cox-Ross-Rubinstein. Solo una delle seguenti affermazioni è corretta. Quale?
A28: (a) Dipende dal tasso d’interesse e dalla volatilità.
A29: (b) Dipende dalla volatilità, ma non dal tasso d’interesse.
A30: (c) Dipende dal tasso d’interesse, ma non dalla volatilità.
A31: (d) Non dipende né dal tasso d’interesse né dalla volatilità.
... A97: In base alla tecnica della variabile di controllo, il valore dell’opzione americana è pari $3,06.
A99: Cbin | B99: 3.12
A100: cbin | B100: 3.04
A101: cbsm | B101: 2.98
A103: Cvc | B103: =B99+B101-B100 -> 3.06
A105: 21.10. Nel capitolo viene presentato un metodo di costruzione degli alberi binomiali alternativo a quello di Cox-Ross-Rubinstein (CRR). In questa alternativa, quale delle seguenti affermazioni è corretta?
A106: (a) La relazione tra u e d è u = 1/d.
A107: (b) La relazione tra u e d è u − 1 = 1 − d.
A108: (c) Le probabilità presenti nell’albero sono tutte uguali a 0,5.
A109: (d) Nessuna delle precedenti risposte è corretta.
A111: (c)
A113: Invece di utilizzare un grado di libertà per porre u = 1/d (come in CRR), il metodo alternativo utilizza un grado di libertà per fissare in 0,5 le probabilità di rialzo e di ribasso.
A115: 21.11. Solo una delle seguenti tipologie di opzioni non può essere valutata facilmente con il metodo Monte Carlo. Quale?
A116: (a) Le opzioni europee.
A117: (b) Le opzioni americane.
A118: (c) Le opzioni asiatiche, ossia le opzioni sul prezzo medio.
A119: (d) Le opzioni che pagano $100 se il prezzo dell’azione a scadenza è maggiore dello strike.
... A155: L’errore standard della stima è ω/√M. Nel nostro caso, l’errore standard della stima è pari a $0,045 (= $4,5/√10.000).
A157: M | B157: 10000
A158: μ | B158: 20
A159: ω | B159: 4.5
A161: ω/√M | B161: =B159/SQRT(B157) -> 0.045
A163: 21.15. In un albero binomiale, i prezzi dell’azione alla fine del secondo intervallo temporale sono $80, $100 e $125. I corrispondenti valori di un’opzione sono $0, $5 e $20, rispettivamente. Qual è la stima del gamma?
A164: (a) 0,0136
A165: (b) 0,0146
A166: (c) 0,0156
A167: (d) 0,0166
A169: (c)
A171: Le stime dei due delta sono 0,25 [= ($5 − $0)/($100 − $80)] e 0,6 [= ($20 − $5)/($125 − $100)]. I punti centrali dei prezzi di riferimento di queste due stime sono $90 [= ($100 + $80)/2] e $112,5 [= ($125 + $100)/2].
A172: Pertanto, la stima del gamma è 0,0156 [= (0,6 − 0,25)/(112,5 − 90)].
A174: S0 u | B174: 125 | D174: cu | E174: 20
A175: S0 | B175: 100 | D175: c | E175: 5
A176: S0 d | B176: 80 | D176: cd | E176: 0
A178: Δu | B178: =(E174-E175)/(B174-B175) -> 0.6 | D178: (S0u + S0)/2 | E178: =(B174+B175)/2 -> 112.5
A179: Δd | B179: =(E175-E176)/(B175-B176) -> 0.25 | D179: (S0 + S0d)/2 | E179: =(B175+B176)/2 -> 90
A180: Γ | B180: =(B178-B179)/(E178-E179) -> 0.015555556
A182: 21.16. Quando si utilizzano gli alberi binomiali per valutare le opzioni americane, quale accorgimento bisogna adottare rispetto alla valutazione delle opzioni europee?
A183: (a) Il valore di u è più elevato.
A184: (b) Il valore di u è più basso.
A185: (c) Gli intervalli temporali non hanno uguale lunghezza.
A186: (d) È necessario effettuare due calcoli nei nodi in cui l’opzione è in the money.
A188: (d)
A190: Quando si utilizzano gli alberi binomiali per valutare le opzioni americane, bisogna calcolare due valori nei nodi in cui l’opzione è in the money:
A191: il valore dell’opzione «morta» (dead), pari al «valore dell’opzione in caso d’esercizio» (exercise value), e il valore dell’opzione «viva» (alive), ottenuto attualizzando il valore atteso ai due nodi successivi.
A193: 21.17. Considerate un’opzione europea scritta su un titolo che paga un dividendo noto.
A194: Una prima stima del valore dell’opzione viene ottenuta sostituendo nella formula Black-Scholes-Merton il prezzo dell’azione con la differenza tra il prezzo dell’azione e il valore attuale del dividendo.
A195: Una seconda stima viene ottenuta con l’albero binomiale illustrato nel testo, utilizzando un numero molto elevato di intervalli temporali. Solo una delle seguenti affermazioni è corretta. Quale?
A196: (a) Il primo prezzo è più elevato del secondo.
... A233: La risposta corretta è quella sub (b) perché la call americana scritta su un titolo che non paga dividendi vale quanto la corrispondente opzione europea e può quindi essere valutata con la formula Black-Scholes-Merton.

Sheet 22
A1: Capitolo 22 Valore a Rischio ed Expected Shortfall
A3: 22.1. Considerate il VaR al 99,9%. Quale delle seguenti affermazioni è corretta?
A4: (a) C’è 1 probabilità su 10 che la perdita sia maggiore del VaR.
A5: (b) C’è 1 probabilità su 100 che la perdita sia maggiore del VaR.
A6: (c) C’è 1 probabilità su 1.000 che la perdita sia maggiore del VaR.
A7: (d) Nessuna delle precedenti affermazioni è corretta.
A9: (c)
A11: Se il VaR è al 99,9%, c’è una probabilità pari allo 0,1% (= 100% − 99,9%) che la perdita ecceda il VaR. Lo 0,1% è pari 1 su 1.000.
A13: 22.2. I profitti di un progetto d’investimento si distribuiscono in modo uniforme tra –$0,15 milioni e +$0,85 milioni. Qual è il VaR al 99%?
A14: (a) $0,145 milioni
A15: (b) $0,14 milioni
A16: (c) $0,13 milioni
... A22: Pertanto, c’è una probabilità del 99% che la perdita non sarà maggiore di $0,14 milioni. Questo è il VaR al 99%.
A24: a | B24: -0.15
A25: b | B25: 0.85
A26: α | B26: 0.99
A28: VaR | B28: =-(B25-B26*(B25-B24)) -> 0.14
A30: 22.3. I profitti di un progetto d’investimento si distribuiscono in modo uniforme tra –$0,15 milioni e +$0,85 milioni. Qual è l'Expected shortfall al 99%?
A31: (a) $0,145 milioni
A32: (b) $0,14 milioni
A33: (c) $0,13 milioni
A34: (d) $0,10 milioni
A36: (a)
A38: Come si è visto nella risposta al test precedente, il VaR al 99% è pari a $0,14 milioni. Se la perdita è maggiore di $0,14 milioni, è ugualmente probabile che sia compresa tra $0,14 e $0,15 milioni.
A39: Pertanto, il valore atteso della perdita, condizionato dal fatto che la perdita sia maggiore di $0,14 milioni, è pari a $0,145 milioni. Questa è l’expected shortfall al 99%.
A41: a | B41: -0.15
A42: b | B42: 0.85
A43: α | B43: 0.99
A45: VaR | B45: =-(B42-B43*(B42-B41)) -> 0.14
A46: Shortfall | B46: =AVERAGE(B45,-B41) -> 0.145
A48: 22.4. Considerate il metodo delle simulazioni storiche per il calcolo del VaR. Solo una delle seguenti affermazioni è corretta. Quale?
A49: (a) Il metodo delle simulazioni storiche consente di stimare una distribuzione normale sulla base dei dati storici di alcune variabili.
A50: (b) Il metodo delle simulazioni storiche consente di stimare una distribuzione log-normale sulla base dei dati storici di alcune variabili.
A51: (c) Il metodo delle simulazioni storiche assume che il futuro sia un campione casuale estratto dal quel che è successo in passato.
A52: (d) Il metodo delle simulazioni storiche utilizza le simulazioni Monte Carlo per generare futuri scenari probabilistici.
A54: (c)
A56: Il metodo delle simulazioni storiche assume che i tassi di variazione delle variabili di mercato che verranno osservati domani rappresentino un campione casuale estratto dalla distribuzione dei tassi di variazione osservati storicamente in un certo numero di giorni.
A58: 22.5. Spesso si assume che il VaR a 10 giorni sia equivalente a:
A59: (a) il VaR a 1 giorno moltiplicato per 10;
A60: (b) il VaR a 1 giorno moltiplicato per √10;
A61: (c) il VaR a 1 giorno diviso per 10;
A62: (d) il VaR a 1 giorno diviso per √10.
... A89: Pertanto, la deviazione standard della variazione di valore dell’intero portafoglio è pari a $76,16 (= √$25.800). Il VaR giornaliero al 99% è quindi pari a $177 ( = 2,326 × $76,16).
A91: σA | B91: 0.015
A92: σB | B92: 0.01
A93: ρ | B93: 0.8
A94: n | B94: 1
A95: α | B95: 0.99
A96: size_A | B96: 2000
A97: size_B | B97: 5000
A99: std(ΔVA) | B99: =B96*B91 -> 30
A100: std(ΔVB) | B100: =B97*B92 -> 50
A101: std(ΔV) | B101: =SQRT(((B96*B91)^2+(B97*B92)^2+2*B96*B91*B97*B92*B93)*B94) -> 76.157731
A102: N−1(α) | B102: =_xlfn.NORM.S.INV(B95) -> 2.3263479
A103: VaR | B103: =B102*B101 -> 177.16938
A105: 22.8. Come viene chiamato il metodo che consiste nel verificare ex post quante volte il VaR è stato superato?
A106: (a) Stress testing.
A107: (b) Back-testing.
A108: (c) EWMA.
A109: (d) Model-building approach.
A111: (b)
A113: Il back-testing consiste nel verificare retroattivamente la bontà di una certa metodologia di calcolo del VaR.
A114: In particolare, quando si effettua il back-testing di una certa metodologia, si calcola il numero delle eccezioni, ossia il numero delle volte in cui il VaR sarebbe stato superato nell’arco di un certo periodo storico.
A116: 22.9. Considerate il caso in cui il delta, ma non il gamma, venga utilizzato per calcolare il VaR di una certa posizione su opzioni. Solo una delle seguenti affermazioni è corretta. Quale?
A117: (a) Il VaR di una long call è troppo basso e il VaR di una long put è troppo basso.
A118: (b) Il VaR di una long call è troppo basso e il VaR di una long put è troppo alto.
A119: (c) Il VaR di una long call è troppo alto e il VaR di una long put è troppo basso.
... A238: L’expected shortfall e il VaR possono entrambi misurare il rischio di mercato. L’expected shortfall è la perdita attesa, condizionata dal fatto che la perdita sia maggiore del VaR. Pertanto, per definizione, l’expected shortfall è sempre maggiore del VaR.

Sheet 23
A1: Capitolo 23 Stima di Volatilità e Correlazioni
A3: 23.1. Quanti parametri sono necessari per definire il modello EWMA?
A4: (a) 1
A5: (b) 2
A6: (c) 3
A7: (d) 4
A9: (a)
A11: Per definire il modello EWMA è necessario un solo parametro.
A13: 23.2. Quanti parametri sono necessari per definire il modello GARCH(1, 1)?
A14: (a) 1
A15: (b) 2
A16: (c) 3
... A31: Alla fine di venerdì, la varianza del tasso di rendimento giornaliero di A è pari a 0,00045 [= 0,9 × 0,022 + (1 − 0,9) × 0,032]. Pertanto, la volatilità è pari al 2,12%.
A33: σt | B33: 0.02
A34: ut | B34: 0.03
A35: lambda | B35: 0.9
A37: σ2t+1 | B37: =B35*B33^2+(1-B35)*B34^2 -> 0.00045
A38: σt+1 | B38: =SQRT(B37) -> 0.021213203
A40: 23.4. Alla fine di giovedì, la volatilità giornaliera del titolo B è pari all’1%. Venerdì, il tasso di rendimento giornaliero di B è pari allo 0%. Utilizzate il modello EWMA con λ = 0,9. Qual è la stima della volatilità di B alla fine di venerdì?
A41: (a) 0,98%
A42: (b) 0,95%
A43: (c) 0,92%
A44: (d) 0,90%
A46: (b)
A48: Alla fine di venerdì, la varianza del tasso di rendimento giornaliero di B è pari a 0,00009 [= 0,9 × 0,012 + (1 − 0,9) × 0,002]. Pertanto, la volatilità è pari all0 0,95%.
A50: σt | B50: 0.01
A51: ut | B51: 0
A52: lambda | B52: 0.9
A54: σ2t+1 | B54: =B52*B50^2+(1-B52)*B51^2 -> 9e-05
A55: σt+1 | B55: =SQRT(B54) -> 0.009486833
A57: 23.5. Alla fine di giovedì, la covarianza tra i tassi di rendimento dei titoli A e B è di 0,0001.
A58: Venerdì, i tassi di rendimento giornalieri di A e B sono pari, rispettivamente, al 3% e allo 0%. Utilizzate il modello EWMA con λ = 0,9. Qual è la stima della covarianza tra i tassi di rendimento dei due titoli alla fine di venerdì?
A59: (a) 0,000090
A60: (b) 0,000081
A61: (c) 0,000100
A62: (d) 0,000095
A64: (a)
A66: Alla fine di venerdì, la covarianza tra i tassi di rendimento di A e B è pari a 0,000090.
A68: σA, B | B68: 0.0001
A69: uA | B69: 0.03
A70: uB | B70: 0
A71: lambda | B71: 0.9
A73: σA, B | B73: =B71*B68+(1-B71)*B69*B70 -> 9e-05
A75: 23.6. Considerate la covarianza tra X e Y. Solo una delle seguenti affermazioni è corretta. Quale?
A76: (a) La covarianza tra X e Y è pari alla correlazione tra X e Y per la varianza di X per la varianza di Y.
A77: (b) La covarianza tra X e Y è pari alla varianza di X per la varianza di Y.
A78: (c) La covarianza tra X e Y è pari alla correlazione tra X e Y divisa per il prodotto tra la de-viazione standard di X e la deviazione standard di Y.
A79: (d) La covarianza tra X e Y è pari alla correlazione tra X e Y moltiplicata per il prodotto tra la deviazione standard di X e la deviazione standard di Y.
A81: (d)
A83: La covarianza è pari al coefficiente di correlazione moltiplicato per il prodotto tra le due deviazioni standard.
A85: 23.7. Qual è il significato dell’acronimo EWMA?
A86: (a) Equally weighted moving average.
A87: (b) Equally weighted median approximation.
A88: (c) Exponentially weighted moving average.
A89: (d) Exponentially weighted median average.
... A121: La volatilità trimestrale è pari al 10%.
A123: σ12m | B123: 0.2
A124: T | B124: =3/12 -> 0.25
A126: σ3m | B126: =B123*SQRT(B124) -> 0.1
A128: 23.11. Considerate i modelli EWMA e GARCH. Solo una delle seguenti affermazioni è corretta. Quale?
A129: (a) Il GARCH incorpora la mean reversion, l’EWMA no.
A130: (b) L’EWMA incorpora la mean reversion, il GARCH no.
A131: (c) Sia l’EWMA sia il GARCH incorporano la mean reversion.
A132: (d) Né l’EWMA né il GARCH incorporano la mean reversion.
A134: (a)
A136: Il GARCH incorpora la mean reversion, l’EWMA no.
A138: 23.12. Considerate le volatilità implicite. Solo una delle seguenti affermazioni è corretta. Quale?
A139: (a) Le volatilità implicite nelle opzioni di qualsiasi scadenza tendono a muoversi in ugual misura da un giorno all’altro.
A140: (b) Le volatilità implicite nelle opzioni di più lunga scadenza tendono a muoversi di più rispetto a quelle implicite nelle opzioni di più breve scadenza.
A141: (c) Le volatilità implicite nelle opzioni di più breve scadenza tendono a muoversi di più rispetto a quelle implicite nelle opzioni di più lunga scadenza.
A142: (d) A volte vale l’affermazione sub (b), a volte quella sub (c).
... A177: Il nuovo tasso di varianza è pari a 0,000113 (= 0,000002 + 0,04 × 0,022 + 0,95 × 0,012). Pertanto, la nuova stima della volatilità è pari all’1,06%.
A179: ω | B179: 2e-06
A180: α | B180: 0.04
A181: β | B181: 0.95
A182: σ | B182: 0.01
A183: u | B183: 0.02
A185: σ2 | B185: =B179+B180*B183^2+B181*B182^2 -> 0.000113
A186: σ | B186: =SQRT(B185) -> 0.010630146
A188: 23.16. I parametri di un GARCH(1, 1) sono ω = 0,000002, α = 0,04 e β = 0,95. Qual è la volatilità media di lungo periodo?
A189: (a) 1,1%
A190: (b) 1,2%
A191: (c) 1,3%
A192: (d) 1,4%
A194: (d)
A196: Il tasso di varianza medio di lungo periodo è pari a 0,0002 [= 0,000002/(1 − 0,04 − 0,95)]. Pertanto, la volatilità media di lungo periodo è pari all’1,4%.
A198: ω | B198: 2e-06
A199: α | B199: 0.04
A200: β | B200: 0.95
A202: VL | B202: =B198/(1-B199-B200) -> 0.0002
A203: σL | B203: =SQRT(B202) -> 0.014142136
A205: 23.17. I parametri di un GARCH(1, 1) sono ω = 0,000002, α = 0,04 e β = 0,95. Il livello corrente della volatilità giornaliera è dell’1%. Qual è la volatilità attesa tra 20 giorni?
A206: (a) 1,09%
A207: (b) 1,10%
A208: (c) 1,11%
A209: (d) 1,12%
A211: (a)
A213: Il tasso di varianza medio di lungo periodo è pari a 0,0002 [= 0,000002/(1 − 0,04 − 0,95)]. Il tasso di varianza atteso tra 20 giorni è pari 0,000118 [= 0,0002 + (0,04 + 0,95)20 × (0,012 − 0,0002)]. Pertanto, la volatilità attesa tra 20 giorni è pari all’1,09%:
A215: ω | B215: 2e-06
A216: α | B216: 0.04
...

Sheet 24
A1: Capitolo 24 Rischio di Credito
A3: 24.1. Supponiamo che le probabilità d’insolvenza di una certa società a 1, 2, 3 e 4 anni siano pari, rispettivamente, al 3,0%, 6,5%, 10,0% e 14,5%.
A4: Qual è la probabilità d’insolvenza relativa al 4° anno condizionata dalla non insolvenza negli anni precedenti?
A5: (a) 4,5%
A6: (b) 5,0%
A7: (c) 5,5%
A8: (d) 6,0%
A10: (b)
A12: La probabilità d’insolvenza, non condizionata, relativa al 4° anno è pari al 4,5%.
A13: La probabilità che la società non risulti insolvente nei primi 3 anni è pari al 90% (= 100% − 10%). Pertanto, la probabilità d’insolvenza nel 4° anno, condizionata dalla non insolvenza negli anni precedenti, è pari al 5%.
A15: Q1 | B15: 0.03 | D15: q1 | E15: =B15 -> 0.03 | G15: S1 | H15: =1-B15 -> 0.97 | J15: λ1 | K15: =B15 -> 0.03
A16: Q2 | B16: 0.065 | D16: q2 | E16: =B16-B15 -> 0.035 | G16: S2 | H16: =1-B16 -> 0.935 | J16: λ2 | K16: =E16/H15 -> 0.036082474
A17: Q3 | B17: 0.1 | D17: q3 | E17: =B17-B16 -> 0.035 | G17: S3 | H17: =1-B17 -> 0.9 | J17: λ3 | K17: =E17/H16 -> 0.037433155
A18: Q4 | B18: 0.145 | D18: q4 | E18: =B18-B17 -> 0.045 | G18: S4 | H18: =1-B18 -> 0.855 | J18: λ4 | K18: =E18/H17 -> 0.05
A20: 24.2. In genere, come viene definito il recovery rate di un’obbligazione?
A21: (a) Il valore del titolo immediatamente dopo l’insolvenza, espresso in rapporto al valore nominale.
A22: (b) Il valore del titolo immediatamente dopo l’insolvenza, espresso in rapporto alla somma del valore nominale e del rateo d’interessi maturato.
A23: (c) Il valore del titolo realizzato alla fine dall’investitore, espresso in rapporto al valore nominale.
A24: (d) Il valore del titolo realizzato alla fine dall’investitore, espresso in rapporto alla somma del valore nominale e del rateo d’interessi maturato.
A26: (a)
A28: In genere, il «tasso di recupero» (recovery rate) di un’obbligazione è pari a un rapporto che vede al numeratore il valore del titolo immediatamente dopo l’insolvenza e al denominatore il valore nominale del titolo stesso.
A29: Questa definizione contrasta con il fatto che, in molte giurisdizioni, il credito vantato dal possessore del titolo sia pari al valore nominale più il rateo d’interessi maturato.
A31: 24.3. Considerate le probabilità neutrali verso il rischio. Solo una delle seguenti affermazioni è corretta. Quale?
A32: (a) Di solito, le probabilità neutrali verso il rischio sono molto più basse delle probabilità effettive.
A33: (b) Di solito, le probabilità neutrali verso il rischio sono molto più alte delle probabilità effettive.
A34: (c) Affinché non vi siano opportunità d’arbitraggio, le probabilità neutrali verso il rischio devono essere molto vicine alle probabilità effettive.
... A49: La probabilità di sopravvivenza fino alla fine del 2° anno è pari al 98,02% (= e−0,01×2). La probabilità, non condizionata, di fallire entro la fine del 2° anno è quindi pari all’1,98% (= 1 − 0,9802).
A51: λ | B51: 0.01
A52: T | B52: 2
A54: V(T) | B54: =EXP(-B51*B52) -> 0.98019867
A55: Q(T) | B55: =1-B54 -> 0.019801327
A57: 24.5. Considerate le probabilità d’insolvenza non condizionate. Solo una delle seguenti affermazioni è corretta. Quale?
A58: (a) Le probabilità d’insolvenza relative ai singoli anni crescono sempre col crescere della scadenza.
A59: (b) Le probabilità d’insolvenza relative ai singoli anni diminuiscono sempre col crescere della scadenza.
A60: (c) A volte è corretta l’affermazione sub (a), a volte quella sub (b).
A61: (d) Le probabilità d’insolvenza relative ai singoli anni restano più o meno stabili col crescere della scadenza.
A63: (c)
A65: Nel caso delle società investment grade, le probabilità d’insolvenza crescono col crescere della scadenza. Nel caso delle società speculative grade spesso è vero il contrario.
A67: 24.6. Considerate le probabilità d’insolvenza condizionate. Solo una delle seguenti affermazioni è corretta. Quale?
A68: (a) Le probabilità d’insolvenza condizionate sono almeno pari alle corrispondenti probabilità d’insolvenza non condizionate.
A69: (b) Le probabilità d’insolvenza condizionate non sono mai più elevate delle corrispondenti probabilità d’insolvenza non condizionate.
A70: (c) Le probabilità d’insolvenza condizionate sono a volte maggiori e a volte minori delle corrispondenti probabilità d’insolvenza non condizionate.
A71: (d) Non ci sono differenze tra le probabilità d’insolvenza condizionate e quelle non condi-zionate perché le società possono fallire solo una volta.
... A86: L’hazard rate medio, λ, è pari al credit spread diviso per il complemento a 1 del recovery rate. In questo caso si ha λ = 2,5%.
A88: spread | B88: 0.02
A89: RR | B89: 0.2
A91: λ | B91: =B88/(1-B89) -> 0.025
A93: 24.8. Considerate i recovery rates. Solo una delle seguenti affermazioni è corretta. Quale?
A94: (a) I recovery rates delle società investment grade sono più bassi di quelli delle altre società.
A95: (b) I recovery rates delle società non-investment grade sono più alti di quelli delle altre società.
A96: (c) I recovery rates sono correlati negativamente con i tassi d’insolvenza.
A97: (d) I recovery rates sono correlati positivamente con i tassi d’insolvenza.
A99: (c)
A101: Quando i tassi d’insolvenza sono elevati, i recovery rates tendono a essere bassi.
A103: 24.9. Considerate gli asset swaps indicizzati al Libor prima della sua cessazione. Quale delle seguenti affermazioni era corretta?
A104: (a) L’asset swap spread misurava la differenza tra il bond yield e l’OIS rate.
A105: (b) L’asset swap spread misurava la differenza tra il bond yield e il Libor/swap rate.
A106: (c) Negli asset swaps si scambiava il tasso di rendimento ex post dell’asset con il Libor maggiorato di uno spread.
A107: (d) Nessuna delle precedenti affermazioni era corretta.
... A113: 24.10. Qual è il rating che una società deve avere per essere considerata di «elevata qualità creditizia» (investment grade)?
A114: (a) | B114: AA o migliore.
A115: (b) | B115: A o migliore.
A116: (c) | B116: BBB o migliore.
A117: (d) | B117: BB o migliore.
A119: (c)
A121: 24.11. Nel modello della copula Gaussiana, solo una delle seguenti affermazioni sul time to default è corretta. Quale?
A122: (a) Il time to default si distribuisce in modo normale.
A123: (b) Il time to default si distribuisce in modo log-normale.
A124: (c) Il time to default viene trasformato in una variabile casuale normale.
A125: (d) Il time to default viene trasformato in una variabile casuale log-normale.
A127: (c)
A129: Il «tempo mancante all’insolvenza» (time to default) viene trasformato − percentile per percentile − in una variabile casuale normale.
A131: 24.12. Considerate il netting. Solo una delle seguenti affermazioni è corretta. Quale?
A132: (a) Il netting comporta sempre la riduzione dell’esposizione di una società verso una sua controparte.
A133: (b) Il netting fa sì che l’esposizione di una società verso una sua controparte si riduca o resti inalterata.
A134: (c) Il netting comporta sempre l’aumento dell’esposizione di una società verso una sua controparte.
... A216: Di conseguenza, la probabilità d’insolvenza, non condizionata, relativa al 6° anno è pari al 5,99% (= 77,88% − 71,89%).
A218: s5 | B218: 0.02
A219: s6 | B219: 0.022
A220: T5 | B220: 5
A221: T6 | B221: 6
A222: RR | B222: 0.6
A224: λ5 | B224: =B218/(1-B222) -> 0.05
A225: λ6 | B225: =B219/(1-B222) -> 0.055
A226: V5 | B226: =EXP(-B224*B220) -> 0.77880078
A227: V6 | B227: =EXP(-B225*B221) -> 0.71892373
A228: q6 | B228: =B226-B227 -> 0.05987705
A230: 24.20. Considerate il calcolo del VaR creditizio secondo CreditMetrics. Solo una delle seguenti affermazioni è corretta. Quale?
A231: (a) CreditMetrics tiene conto delle insolvenze, ma non dei downgrades.
A232: (b) CreditMetrics tiene conto dei downgrades, ma non delle insolvenze.
A233: (c) CreditMetrics non tiene conto né delle insolvenze né dei downgrades.
A234: (d) CreditMetrics tiene conto sia delle insolvenze sia dei downgrades.
A236: (d)
A238: Dato che utilizza le matrici delle transizioni di rating, CreditMetrics tiene conto sia delle insolvenze sia dei downgrades.

Sheet 25
A1: Capitolo 25 Derivati Creditizi
A3: 25.1. Qual è il numero di società su cui si basa l’indice CDX NA IG?
A4: (a) 50
A5: (b) 75
A6: (c) 100
A7: (d) 125
A9: (d)
A11: L’indice CDX NA IG si basa su 125 società investment grade.
A13: 25.2. Qual è il numero di società su cui si basa l’indice iTraxx?
A14: (a) 50
A15: (b) 75
A16: (c) 100
... A41: Il payoff del CDS è pari al prodotto tra il capitale nozionale e il complemento a 1 del tasso di recupero ossia, in questo caso, a $70 [= $100 × (1 − 0,30)] milioni.
A43: L | B43: 100
A44: R | B44: 0.3
A46: Payoff | B46: =B43*(1-B44) -> 70
A48: 25.5. Considerate un forward a 1 anno scritto su un CDS a 5 anni. Cosa succede se la reference entity del CDS fallisce nel corso del 1° anno?
A49: (a) Il compratore del forward riceve il payoff del CDS nel momento in cui si verifica l’insolvenza.
A50: (b) Il compratore del forward riceve il payoff del CDS alla fine del 1° anno.
A51: (c) Il compratore del forward riceve il payoff del CDS alla fine del 6° anno.
A52: (d) Il contratto forward cessa di esistere.
A54: (d)
A56: I forward CDSs cessano di esistere se la reference entity del CDS fallisce prima della scadenza del contratto.
A58: 25.6. Cosa succede quando aumenta la default correlation delle società sottostanti una CDO? Solo una delle seguenti affermazioni è corretta. Quale? Mettetevi nell’ottica del protection buyer.
A59: (a) Aumenta il valore sia della senior tranche sia dell’equity tranche.
A60: (b) Diminuisce il valore sia della senior tranche sia dell’equity tranche.
A61: (c) Diminuisce il valore della senior tranche e aumenta quello dell’equity tranche.
A62: (d) Aumenta il valore della senior tranche e diminuisce quello dell’equity tranche.
... A107: Il payoff di un CDS ordinario è pari al prodotto tra il payoff del corrispondente binary CDS e (1 − R), dove R è il recovery rate. Pertanto, nel nostro caso, il CDS spread del binary CDS è pari a 200 [= 120 / (1 − 0,4)] punti base.
A109: s | B109: 120 | C109: p.b.
A110: R | B110: 0.4
A112: sb | B112: =B109/(1-B110) -> 200
A114: 25.11. Qual è il range di perdite che viene assorbito dall’equity tranche dell’iTraxx Europe?
A115: (a) Da 0% al 10%.
A116: (b) Da 0% al 7%.
A117: (c) Da 0% al 6%.
A118: (d) Da 0% al 3%.
A120: (d)
A122: L’equity tranche copre il range di perdite compreso nella fascia dallo 0% al 3% del capitale complessivo.
A124: 25.12. Considerate i credit default swaps. Solo una delle seguenti affermazioni è corretta. Quale?
A125: (a) Le ristrutturazioni non rappresentano mai un credit event.
A126: (b) Le ristrutturazioni rappresentano sempre un credit event.
A127: (c) Certi tipi di ristrutturazione rappresentano un credit event, mentre altri no.
A128: (d) In certi CDSs le ristrutturazioni rappresentano un credit event, ma in altri no.
... A213: La base correlation è la correlazione utilizzata per valutare la tranche di una CDO con at-tachment point pari allo 0%.

Sheet 26
A1: Capitolo 26 Opzioni Esotiche
A3: 26.1. Considerate le opzioni asiatiche. Solo una delle seguenti definizioni è corretta. Quale?
A4: (a) Le opzioni asiatiche sono opzioni il cui payoff dipende dal fatto che una certa barriera venga attraversata oppure no.
A5: (b) Le opzioni asiatiche sono opzioni il cui payoff dipende dal valore medio di una variabile, osservata in un certo intervallo di tempo.
A6: (c) Le opzioni asiatiche sono opzioni negoziate in Estremo Oriente.
A7: (d) Le opzioni asiatiche sono opzioni con payoff fuori standard.
A9: (b)
A11: Le opzioni asiatiche sono opzioni il cui payoff dipende dal valore medio di una variabile, osservata in un certo intervallo di tempo.
A13: 26.2. Se aumenta la frequenza con cui il prezzo dell’azione viene osservato, qual è l’effetto sul valore di un’opzione knock out?
A14: (a) Il valore aumenta.
A15: (b) Il valore diminuisce.
A16: (c) Il valore resta inalterato.
... A52: Nel nostro caso, il payoff dell’opzione è pari a $10.
A54: K | B54: 30
A55: Sτ | B55: 40
A56: ST | B56: 35
A58: max(Sτ – K, ST – K) | C58: =MAX(B55-B54,B56-B54) -> 10
A60: 26.6. Qual è il payoff di una floating lookback call?
A61: (a) ST – Smin
A62: (b) Smax – ST
A63: (c) max(K – Smin, 0)
A64: (d) max(Smax – K, 0)
A66: (a)
A68: Il payoff di una floating lookback call è pari a ST − Smin.
A70: 26.7. Qual è il payoff di una fixed lookback put?
A71: (a) ST – Smin
A72: (b) Smax – ST
A73: (c) max(K – Smin, 0)
A74: (d) max(Smax – K, 0)
... A163: Pertanto, il valore corrente della cash-or-nothing call è pari a $99,25 × N(−0,0625).
A165: S0 | B165: 100
A166: K | B166: 100
A167: T | B167: 0.25
A168: r | B168: 0.03
A169: σ | B169: 0.4
A171: Ke−rT | B171: =B166*EXP(-B168*B167) -> 99.252805
A172: d2 | B172: =(LN(B165/B166)+(B168-B169^2/2)*B167)/(B169*SQRT(B167)) -> -0.0625
A174: 26.16. Considerate i volatility swaps. Solo una delle seguenti affermazioni è corretta. Quale?
A175: (a) I volatility swaps sono contratti in cui si scambia la variazione di valore di una variabile di mercato con un importo prefissato.
A176: (b) I volatility swaps sono contratti scritti su un’attività la cui volatilità è maggiore di un certo livello.
A177: (c) I volatility swaps sono contratti in cui si scambia una volatilità prefissata con la volatilità implicita di un’opzione che verrà osservata in una certa data futura.
A178: (d) I volatility swaps sono contratti in cui si scambia una volatilità prefissata con la volatilità di una certa attività che verrà osservata in un periodo di tempo futuro.
A180: (d)
A182: I volatility swaps sono contratti in cui si scambia una volatilità prefissata con la volatilità di una certa attività che verrà osservata in un periodo di tempo futuro. Entrambe le volatilità vengono moltiplicata per il valore nozionale del contratto.
A184: 26.17. Considerate le gap options. Quale delle seguenti affermazioni è corretta?
A185: (a) Il prezzo che determina l’esercizio dell’opzione non è uguale al prezzo che determina l’ammontare del payoff.
A186: (b) Le gap options vengono valutate con una formula simile a quella Black-Scholes-Merton.
A187: (c) L’esercizio delle gap options comporta il pagamento di un certo importo.
A188: (d) Tutte le precedenti affermazioni sono corrette.
... A223: Di solito, la copertura delle opzioni average price è più facile di quella delle opzioni ordinarie perché, col passare del tempo, la media diventa sempre meno incerta. La copertura delle opzioni con barriera è più difficile a causa delle discontinuità.

Sheet Risposte
A1: 1.1 | B1: ='1'!A9 -> (b) | D1: 2.1 | E1: ='2'!A9 -> (c) | G1: 3.1 | H1: ='3'!A9 -> (a) | J1: 4.1 | K1: ='4'!A9 -> (b) | M1: 5.1 | N1: ='5'!A9 -> (c) | P1: 6.1 | Q1: ='6'!A9 -> (c) | S1: 7.1 | T1: ='7'!A9 -> (b) | V1: 8.1 | W1: ='8'!A9 -> (c) | Y1: 9.1 | Z1: ='9'!A9 -> (c) | AB1: 10.1 | AC1: ='10'!A9 -> (a) | AE1: 11.1 | AF1: ='11'!A9 -> (c) | AH1: 12.1 | AI1: ='12'!A9 -> (a) | AK1: 13.1 | AL1: ='13'!A10 -> (b) | AN1: 14.1 | AO1: ='14'!A10 -> (c) | AQ1: 15.1 | AR1: ='15'!A9 -> (b) | AT1: 16.1 | AU1: ='16'!A9 -> (b) | AW1: 17.1 | AX1: ='17'!A9 -> (b) | AZ1: 18.1 | BA1: ='18'!A9 -> (b) | BC1: 19.1 | BD1: ='19'!A9 -> (b) | BF1: 20.1 | BG1: ='20'!A9 -> (c) | BI1: 21.1 | BJ1: ='21'!A9 -> (c) | BL1: 22.1 | BM1: ='22'!A9 -> (c) | BO1: 23.1 | BP1: ='23'!A9 -> (a) | BR1: 24.1 | BS1: ='24'!A10 -> (b) | BU1: 25.1 | BV1: ='25'!A9 -> (d) | BX1: 26.1 | BY1: ='26'!A9 -> (b)
A2: 1.2 | B2: ='1'!A19 -> (a) | D2: 2.2 | E2: ='2'!A19 -> (a) | G2: 3.2 | H2: ='3'!A19 -> (b) | J2: 4.2 | K2: ='4'!A19 -> (c) | M2: 5.2 | N2: ='5'!A20 -> (b) | P2: 6.2 | Q2: ='6'!A20 -> (c) | S2: 7.2 | T2: ='7'!A25 -> (b) | V2: 8.2 | W2: ='8'!A22 -> (b) | Y2: 9.2 | Z2: ='9'!A19 -> (b) | AB2: 10.2 | AC2: ='10'!A19 -> (d) | AE2: 11.2 | AF2: ='11'!A19 -> (d) | AH2: 12.2 | AI2: ='12'!A19 -> (b) | AK2: 13.2 | AL2: ='13'!A32 -> (c) | AN2: 14.2 | AO2: ='14'!A29 -> (b) | AQ2: 15.2 | AR2: ='15'!A19 -> (d) | AT2: 16.2 | AU2: ='16'!A20 -> (b) | AW2: 17.2 | AX2: ='17'!A19 -> (d) | AZ2: 18.2 | BA2: ='18'!A19 -> (a) | BC2: 19.2 | BD2: ='19'!A25 -> (b) | BF2: 20.2 | BG2: ='20'!A19 -> (a) | BI2: 21.2 | BJ2: ='21'!A23 -> (d) | BL2: 22.2 | BM2: ='22'!A19 -> (b) | BO2: 23.2 | BP2: ='23'!A19 -> (c) | BR2: 24.2 | BS2: ='24'!A26 -> (a) | BU2: 25.2 | BV2: ='25'!A19 -> (d) | BX2: 26.2 | BY2: ='26'!A19 -> (b)
A3: 1.3 | B3: ='1'!A31 -> (a) | D3: 2.3 | E3: ='2'!A29 -> (b) | G3: 3.3 | H3: ='3'!A31 -> (a) | J3: 4.3 | K3: ='4'!A34 -> (a) | M3: 5.3 | N3: ='5'!A41 -> (a) | P3: 6.3 | Q3: ='6'!A41 -> (a) | S3: 7.3 | T3: ='7'!A35 -> (a) | V3: 8.3 | W3: ='8'!A34 -> (d) | Y3: 9.3 | Z3: ='9'!A29 -> (a) | AB3: 10.3 | AC3: ='10'!A30 -> (c) | AE3: 11.3 | AF3: ='11'!A29 -> (a) | AH3: 12.3 | AI3: ='12'!A29 -> (a) | AK3: 13.3 | AL3: ='13'!A54 -> (a) | AN3: 14.3 | AO3: ='14'!A49 -> (b) | AQ3: 15.3 | AR3: ='15'!A29 -> (a) | AT3: 16.3 | AU3: ='16'!A30 -> (a) | AW3: 17.3 | AX3: ='17'!A29 -> (b) | AZ3: 18.3 | BA3: ='18'!A29 -> (a) | BC3: 19.3 | BD3: ='19'!A35 -> (a) | BF3: 20.3 | BG3: ='20'!A30 -> (d) | BI3: 21.3 | BJ3: ='21'!A33 -> (b) | BL3: 22.3 | BM3: ='22'!A36 -> (a) | BO3: 23.3 | BP3: ='23'!A29 -> (c) | BR3: 24.3 | BS3: ='24'!A37 -> (b) | BU3: 25.3 | BV3: ='25'!A29 -> (b) | BX3: 26.3 | BY3: ='26'!A29 -> (b)
A4: 1.4 | B4: ='1'!A48 -> (d) | D4: 2.4 | E4: ='2'!A41 -> (d) | G4: 3.4 | H4: ='3'!A53 -> (d) | J4: 4.4 | K4: ='4'!A49 -> (a) | M4: 5.4 | N4: ='5'!A58 -> (b) | P4: 6.4 | Q4: ='6'!A62 -> (c) | S4: 7.4 | T4: ='7'!A46 -> (c) | V4: 8.4 | W4: ='8'!A47 -> (b) | Y4: 9.4 | Z4: ='9'!A39 -> (b) | AB4: 10.4 | AC4: ='10'!A48 -> (d) | AE4: 11.4 | AF4: ='11'!A39 -> (d) | AH4: 12.4 | AI4: ='12'!A39 -> (b) | AK4: 13.4 | AL4: ='13'!A78 -> (c) | AN4: 14.4 | AO4: ='14'!A68 -> (a) | AQ4: 15.4 | AR4: ='15'!A40 -> (b) | AT4: 16.4 | AU4: ='16'!A40 -> (d) | AW4: 17.4 | AX4: ='17'!A40 -> (c) | AZ4: 18.4 | BA4: ='18'!A40 -> (a) | BC4: 19.4 | BD4: ='19'!A45 -> (d) | BF4: 20.4 | BG4: ='20'!A41 -> (c) | BI4: 21.4 | BJ4: ='21'!A44 -> (d) | BL4: 22.4 | BM4: ='22'!A54 -> (c) | BO4: 23.4 | BP4: ='23'!A46 -> (b) | BR4: 24.4 | BS4: ='24'!A47 -> (c) | BU4: 25.4 | BV4: ='25'!A39 -> (d) | BX4: 26.4 | BY4: ='26'!A39 -> (d)
A5: 1.5 | B5: ='1'!A64 -> (d) | D5: 2.5 | E5: ='2'!A62 -> (b) | G5: 3.5 | H5: ='3'!A74 -> (a) | J5: 4.5 | K5: ='4'!A65 -> (d) | M5: 5.5 | N5: ='5'!A83 -> (d) | P5: 6.5 | Q5: ='6'!A79 -> (d) | S5: 7.5 | T5: ='7'!A56 -> (d) | V5: 8.5 | W5: ='8'!A69 -> (d) | Y5: 9.5 | Z5: ='9'!A50 -> (b) | AB5: 10.5 | AC5: ='10'!A66 -> (a) | AE5: 11.5 | AF5: ='11'!A49 -> (c) | AH5: 12.5 | AI5: ='12'!A49 -> (c) | AK5: 13.5 | AL5: ='13'!A98 -> (d) | AN5: 14.5 | AO5: ='14'!A78 -> (c) | AQ5: 15.5 | AR5: ='15'!A56 -> (b) | AT5: 16.5 | AU5: ='16'!A50 -> (d) | AW5: 17.5 | AX5: ='17'!A52 -> (b) | AZ5: 18.5 | BA5: ='18'!A50 -> (c) | BC5: 19.5 | BD5: ='19'!A55 -> (c) | BF5: 20.5 | BG5: ='20'!A51 -> (c) | BI5: 21.5 | BJ5: ='21'!A54 -> (b) | BL5: 22.5 | BM5: ='22'!A64 -> (b) | BO5: 23.5 | BP5: ='23'!A64 -> (a) | BR5: 24.5 | BS5: ='24'!A63 -> (c) | BU5: 25.5 | BV5: ='25'!A54 -> (d) | BX5: 26.5 | BY5: ='26'!A49 -> (c)
A6: 1.6 | B6: ='1'!A75 -> (a) | D6: 2.6 | E6: ='2'!A82 -> (b) | G6: 3.6 | H6: ='3'!A91 -> (d) | J6: 4.6 | K6: ='4'!A83 -> (c) | M6: 5.6 | N6: ='5'!A100 -> (a) | P6: 6.6 | Q6: ='6'!A89 -> (b) | S6: 7.6 | T6: ='7'!A66 -> (a) | V6: 8.6 | W6: ='8'!A99 -> (a) | Y6: 9.6 | Z6: ='9'!A62 -> (c) | AB6: 10.6 | AC6: ='10'!A76 -> (d) | AE6: 11.6 | AF6: ='11'!A62 -> (d) | AH6: 12.6 | AI6: ='12'!A60 -> (c) | AK6: 13.6 | AL6: ='13'!A121 -> (a) | AN6: 14.6 | AO6: ='14'!A88 -> (a) | AQ6: 15.6 | AR6: ='15'!A66 -> (d) | AT6: 16.6 | AU6: ='16'!A60 -> (c) | AW6: 17.6 | AX6: ='17'!A77 -> (c) | AZ6: 18.6 | BA6: ='18'!A60 -> (c) | BC6: 19.6 | BD6: ='19'!A65 -> (d) | BF6: 20.6 | BG6: ='20'!A61 -> (a) | BI6: 21.6 | BJ6: ='21'!A64 -> (c) | BL6: 22.6 | BM6: ='22'!A74 -> (a) | BO6: 23.6 | BP6: ='23'!A81 -> (d) | BR6: 24.6 | BS6: ='24'!A73 -> (a) | BU6: 25.6 | BV6: ='25'!A64 -> (d) | BX6: 26.6 | BY6: ='26'!A66 -> (a)
A7: 1.7 | B7: ='1'!A85 -> (b) | D7: 2.7 | E7: ='2'!A92 -> (b) | G7: 3.7 | H7: ='3'!A113 -> (c) | J7: 4.7 | K7: ='4'!A104 -> (d) | M7: 5.7 | N7: ='5'!A112 -> (d) | P7: 6.7 | Q7: ='6'!A105 -> (b) | S7: 7.7 | T7: ='7'!A76 -> (d) | V7: 8.7 | W7: ='8'!A123 -> (d) | Y7: 9.7 | Z7: ='9'!A80 -> (a) | AB7: 10.7 | AC7: ='10'!A86 -> (b) | AE7: 11.7 | AF7: ='11'!A73 -> (b) | AH7: 12.7 | AI7: ='12'!A71 -> (d) | AK7: 13.7 | AL7: ='13'!A131 -> (c) | AN7: 14.7 | AO7: ='14'!A98 -> (b) | AQ7: 15.7 | AR7: ='15'!A76 -> (b) | AT7: 16.7 | AU7: ='16'!A70 -> (b) | AW7: 17.7 | AX7: ='17'!A99 -> (d) | AZ7: 18.7 | BA7: ='18'!A71 -> (d) | BC7: 19.7 | BD7: ='19'!A76 -> (a) | BF7: 20.7 | BG7: ='20'!A71 -> (a) | BI7: 21.7 | BJ7: ='21'!A74 -> (b) | BL7: 22.7 | BM7: ='22'!A86 -> (a) | BO7: 23.7 | BP7: ='23'!A91 -> (c) | BR7: 24.7 | BS7: ='24'!A84 -> (d) | BU7: 25.7 | BV7: ='25'!A75 -> (b) | BX7: 26.7 | BY7: ='26'!A76 -> (c)
A8: 1.8 | B8: ='1'!A97 -> (b) | D8: 2.8 | E8: ='2'!A104 -> (a) | G8: 3.8 | H8: ='3'!A134 -> (c) | J8: 4.8 | K8: ='4'!A123 -> (d) | M8: 5.8 | N8: ='5'!A130 -> (c) | P8: 6.8 | Q8: ='6'!A115 -> (d) | S8: 7.8 | T8: ='7'!A86 -> (a) | V8: 8.8 | W8: ='8'!A133 -> (b) | Y8: 9.8 | Z8: ='9'!A95 -> (d) | AB8: 10.8 | AC8: ='10'!A96 -> (c) | AE8: 11.8 | AF8: ='11'!A91 -> (d) | AH8: 12.8 | AI8: ='12'!A81 -> (b) | AK8: 13.8 | AL8: ='13'!A141 -> (c) | AN8: 14.8 | AO8: ='14'!A108 -> (c) | AQ8: 15.8 | AR8: ='15'!A86 -> (c) | AT8: 16.8 | AU8: ='16'!A80 -> (d) | AW8: 17.8 | AX8: ='17'!A122 -> (d) | AZ8: 18.8 | BA8: ='18'!A91 -> (c) | BC8: 19.8 | BD8: ='19'!A92 -> (d) | BF8: 20.8 | BG8: ='20'!A81 -> (c) | BI8: 21.8 | BJ8: ='21'!A84 -> (d) | BL8: 22.8 | BM8: ='22'!A111 -> (b) | BO8: 23.8 | BP8: ='23'!A101 -> (d) | BR8: 24.8 | BS8: ='24'!A99 -> (c) | BU8: 25.8 | BV8: ='25'!A85 -> (b) | BX8: 26.8 | BY8: ='26'!A86 -> (d)
A9: 1.9 | B9: ='1'!A112 -> (c) | D9: 2.9 | E9: ='2'!A122 -> (d) | G9: 3.9 | H9: ='3'!A144 -> (d) | J9: 4.9 | K9: ='4'!A133 -> (a) | M9: 5.9 | N9: ='5'!A141 -> (a) | P9: 6.9 | Q9: ='6'!A126 -> (b) | S9: 7.9 | T9: ='7'!A99 -> (a) | V9: 8.9 | W9: ='8'!A143 -> (d) | Y9: 9.9 | Z9: ='9'!A105 -> (b) | AB9: 10.9 | AC9: ='10'!A106 -> (a) | AE9: 11.9 | AF9: ='11'!A108 -> (a) | AH9: 12.9 | AI9: ='12'!A91 -> (c) | AK9: 13.9 | AL9: ='13'!A151 -> (d) | AN9: 14.9 | AO9: ='14'!A120 -> (c) | AQ9: 15.9 | AR9: ='15'!A97 -> (d) | AT9: 16.9 | AU9: ='16'!A90 -> (a) | AW9: 17.9 | AX9: ='17'!A145 -> (d) | AZ9: 18.9 | BA9: ='18'!A114 -> (b) | BC9: 19.9 | BD9: ='19'!A104 -> (b) | BF9: 20.9 | BG9: ='20'!A91 -> (d) | BI9: 21.9 | BJ9: ='21'!A95 -> (a) | BL9: 22.9 | BM9: ='22'!A122 -> (d) | BO9: 23.9 | BP9: ='23'!A111 -> (b) | BR9: 24.9 | BS9: ='24'!A109 -> (b) | BU9: 25.9 | BV9: ='25'!A95 -> (c) | BX9: 26.9 | BY9: ='26'!A96 -> (a)
A10: 1.10 | B10: ='1'!A123 -> (c) | D10: 2.10 | E10: ='2'!A140 -> (c) | G10: 3.10 | H10: ='3'!A154 -> (b) | J10: 4.10 | K10: ='4'!A143 -> (b) | M10: 5.10 | N10: ='5'!A152 -> (c) | P10: 6.10 | Q10: ='6'!A145 -> (b) | S10: 7.10 | T10: ='7'!A112 -> (d) | V10: 8.10 | W10: ='8'!A154 -> (a) | Y10: 9.10 | Z10: ='9'!A115 -> (a) | AB10: 10.10 | AC10: ='10'!A117 -> (d) | AE10: 11.10 | AF10: ='11'!A118 -> (a) | AH10: 12.10 | AI10: ='12'!A101 -> (d) | AK10: 13.10 | AL10: ='13'!A162 -> (d) | AN10: 14.10 | AO10: ='14'!A143 -> (d) | AQ10: 15.10 | AR10: ='15'!A107 -> (c) | AT10: 16.10 | AU10: ='16'!A100 -> (b) | AW10: 17.10 | AX10: ='17'!A166 -> (a) | AZ10: 18.10 | BA10: ='18'!A136 -> (c) | BC10: 19.10 | BD10: ='19'!A114 -> (b) | BF10: 20.10 | BG10: ='20'!A101 -> (c) | BI10: 21.10 | BJ10: ='21'!A111 -> (c) | BL10: 22.10 | BM10: ='22'!A133 -> (a) | BO10: 23.10 | BP10: ='23'!A119 -> (b) | BR10: 24.10 | BS10: ='24'!A119 -> (c) | BU10: 25.10 | BV10: ='25'!A105 -> (c) | BX10: 26.10 | BY10: ='26'!A106 -> (d)
A11: 1.11 | B11: ='1'!A133 -> (d) | D11: 2.11 | E11: ='2'!A152 -> (a) | G11: 3.11 | H11: ='3'!A164 -> (c) | J11: 4.11 | K11: ='4'!A153 -> (b) | M11: 5.11 | N11: ='5'!A163 -> (b) | P11: 6.11 | Q11: ='6'!A155 -> (c) | S11: 7.11 | T11: ='7'!A122 -> (b) | V11: 8.11 | W11: ='8'!A164 -> (c) | Y11: 9.11 | Z11: ='9'!A125 -> (c) | AB11: 10.11 | AC11: ='10'!A127 -> (a) | AE11: 11.11 | AF11: ='11'!A128 -> (c) | AH11: 12.11 | AI11: ='12'!A111 -> (a) | AK11: 13.11 | AL11: ='13'!A172 -> (c) | AN11: 14.11 | AO11: ='14'!A166 -> (b) | AQ11: 15.11 | AR11: ='15'!A117 -> (a) | AT11: 16.11 | AU11: ='16'!A110 -> (b) | AW11: 17.11 | AX11: ='17'!A185 -> (d) | AZ11: 18.11 | BA11: ='18'!A146 -> (c) | BC11: 19.11 | BD11: ='19'!A125 -> (c) | BF11: 20.11 | BG11: ='20'!A111 -> (a) | BI11: 21.11 | BJ11: ='21'!A121 -> (b) | BL11: 22.11 | BM11: ='22'!A143 -> (b) | BO11: 23.11 | BP11: ='23'!A134 -> (a) | BR11: 24.11 | BS11: ='24'!A127 -> (c) | BU11: 25.11 | BV11: ='25'!A120 -> (d) | BX11: 26.11 | BY11: ='26'!A117 -> (b)
A12: 1.12 | B12: ='1'!A144 -> (c) | D12: 2.12 | E12: ='2'!A162 -> (d) | G12: 3.12 | H12: ='3'!A175 -> (a) | J12: 4.12 | K12: ='4'!A169 -> (d) | M12: 5.12 | N12: ='5'!A173 -> (c) | P12: 6.12 | Q12: ='6'!A165 -> (b) | S12: 7.12 | T12: ='7'!A132 -> (a) | V12: 8.12 | W12: ='8'!A174 -> (a) | Y12: 9.12 | Z12: ='9'!A135 -> (d) | AB12: 10.12 | AC12: ='10'!A137 -> (c) | AE12: 11.12 | AF12: ='11'!A138 -> (b) | AH12: 12.12 | AI12: ='12'!A121 -> (c) | AK12: 13.12 | AL12: ='13'!A183 -> (b) | AN12: 14.12 | AO12: ='14'!A176 -> (c) | AQ12: 15.12 | AR12: ='15'!A127 -> (b) | AT12: 16.12 | AU12: ='16'!A120 -> (d) | AW12: 17.12 | AX12: ='17'!A195 -> (c) | AZ12: 18.12 | BA12: ='18'!A156 -> (d) | BC12: 19.12 | BD12: ='19'!A136 -> (a) | BF12: 20.12 | BG12: ='20'!A121 -> (c) | BI12: 21.12 | BJ12: ='21'!A132 -> (b) | BL12: 22.12 | BM12: ='22'!A153 -> (a) | BO12: 23.12 | BP12: ='23'!A144 -> (c) | BR12: 24.12 | BS12: ='24'!A137 -> (b) | BU12: 25.12 | BV12: ='25'!A130 -> (d) | BX12: 26.12 | BY12: ='26'!A127 -> (d)
A13: 1.13 | B13: ='1'!A163 -> (d) | D13: 2.13 | E13: ='2'!A173 -> (b) | G13: 3.13 | H13: ='3'!A186 -> (b) | J13: 4.13 | K13: ='4'!A188 -> (c) | M13: 5.13 | N13: ='5'!A183 -> (d) | P13: 6.13 | Q13: ='6'!A176 -> (a) | S13: 7.13 | T13: ='7'!A142 -> (c) | V13: 8.13 | W13: ='8'!A184 -> (b) | Y13: 9.13 | Z13: ='9'!A145 -> (c) | AB13: 10.13 | AC13: ='10'!A147 -> (b) | AE13: 11.13 | AF13: ='11'!A149 -> (d) | AH13: 12.13 | AI13: ='12'!A131 -> (d) | AK13: 13.13 | AL13: ='13'!A217 -> (a) | AN13: 14.13 | AO13: ='14'!A186 -> (d) | AQ13: 15.13 | AR13: ='15'!A142 -> (d) | AT13: 16.13 | AU13: ='16'!A130 -> (c) | AW13: 17.13 | AX13: ='17'!A206 -> (a) | AZ13: 18.13 | BA13: ='18'!A167 -> (c) | BC13: 19.13 | BD13: ='19'!A146 -> (c) | BF13: 20.13 | BG13: ='20'!A131 -> (a) | BI13: 21.13 | BJ13: ='21'!A142 -> (b) | BL13: 22.13 | BM13: ='22'!A163 -> (b) | BO13: 23.13 | BP13: ='23'!A155 -> (d) | BR13: 24.13 | BS13: ='24'!A148 -> (b) | BU13: 25.13 | BV13: ='25'!A140 -> (a) | BX13: 26.13 | BY13: ='26'!A137 -> (b)
A14: 1.14 | B14: ='1'!A182 -> (a) | D14: 2.14 | E14: ='2'!A183 -> (a) | G14: 3.14 | H14: ='3'!A197 -> (a) | J14: 4.14 | K14: ='4'!A198 -> (a) | M14: 5.14 | N14: ='5'!A193 -> (a) | P14: 6.14 | Q14: ='6'!A186 -> (c) | S14: 7.14 | T14: ='7'!A155 -> (b) | V14: 8.14 | W14: ='8'!A196 -> (c) | Y14: 9.14 | Z14: ='9'!A155 -> (a) | AB14: 10.14 | AC14: ='10'!A157 -> (a) | AE14: 11.14 | AF14: ='11'!A159 -> (b) | AH14: 12.14 | AI14: ='12'!A141 -> (b) | AK14: 13.14 | AL14: ='13'!A250 -> (b) | AN14: 14.14 | AO14: ='14'!A196 -> (b) | AQ14: 15.14 | AR14: ='15'!A161 -> (a) | AT14: 16.14 | AU14: ='16'!A140 -> (b) | AW14: 17.14 | AX14: ='17'!A228 -> (b) | AZ14: 18.14 | BA14: ='18'!A178 -> (b) | BC14: 19.14 | BD14: ='19'!A160 -> (c) | BF14: 20.14 | BG14: ='20'!A142 -> (c) | BI14: 21.14 | BJ14: ='21'!A152 -> (c) | BL14: 22.14 | BM14: ='22'!A173 -> (a) | BO14: 23.14 | BP14: ='23'!A165 -> (b) | BR14: 24.14 | BS14: ='24'!A159 -> (a) | BU14: 25.14 | BV14: ='25'!A150 -> (b) | BX14: 26.14 | BY14: ='26'!A147 -> (d)
A15: 1.15 | B15: ='1'!A201 -> (c) | D15: 2.15 | E15: ='2'!A193 -> (c) | G15: 3.15 | H15: ='3'!A208 -> (d) | J15: 4.15 | K15: ='4'!A209 -> (d) | M15: 5.15 | N15: ='5'!A203 -> (b) | P15: 6.15 | Q15: ='6'!A206 -> (d) | S15: 7.15 | T15: ='7'!A169 -> (b) | V15: 8.15 | W15: ='8'!A210 -> (b) | Y15: 9.15 | Z15: ='9'!A165 -> (a) | AB15: 10.15 | AC15: ='10'!A167 -> (b) | AE15: 11.15 | AF15: ='11'!A170 -> (d) | AH15: 12.15 | AI15: ='12'!A151 -> (a) | AK15: 13.15 | AL15: ='13'!A261 -> (d) | AN15: 14.15 | AO15: ='14'!A206 -> (c) | AQ15: 15.15 | AR15: ='15'!A172 -> (d) | AT15: 16.15 | AU15: ='16'!A152 -> (a) | AW15: 17.15 | AX15: ='17'!A250 -> (c) | AZ15: 18.15 | BA15: ='18'!A188 -> (c) | BC15: 19.15 | BD15: ='19'!A176 -> (a) | BF15: 20.15 | BG15: ='20'!A152 -> (d) | BI15: 21.15 | BJ15: ='21'!A169 -> (c) | BL15: 22.15 | BM15: ='22'!A184 -> (c) | BO15: 23.15 | BP15: ='23'!A175 -> (c) | BR15: 24.15 | BS15: ='24'!A169 -> (d) | BU15: 25.15 | BV15: ='25'!A160 -> (a) | BX15: 26.15 | BY15: ='26'!A158 -> (c)
A16: 1.16 | B16: ='1'!A220 -> (d) | D16: 2.16 | E16: ='2'!A203 -> (a) | G16: 3.16 | H16: ='3'!A218 -> (d) | J16: 4.16 | K16: ='4'!A219 -> (c) | M16: 5.16 | N16: ='5'!A213 -> (b) | P16: 6.16 | Q16: ='6'!A216 -> (a) | S16: 7.16 | T16: ='7'!A195 -> (b) | V16: 8.16 | W16: ='8'!A240 -> (c) | Y16: 9.16 | Z16: ='9'!A175 -> (d) | AB16: 10.16 | AC16: ='10'!A178 -> (c) | AE16: 11.16 | AF16: ='11'!A189 -> (c) | AH16: 12.16 | AI16: ='12'!A161 -> (d) | AK16: 13.16 | AL16: ='13'!A278 -> (b) | AN16: 14.16 | AO16: ='14'!A217 -> (c) | AQ16: 15.16 | AR16: ='15'!A182 -> (d) | AT16: 16.16 | AU16: ='16'!A162 -> (c) | AW16: 17.16 | AX16: ='17'!A277 -> (a) | AZ16: 18.16 | BA16: ='18'!A199 -> (a) | BC16: 19.16 | BD16: ='19'!A191 -> (a) | BF16: 20.16 | BG16: ='20'!A171 -> (a) | BI16: 21.16 | BJ16: ='21'!A188 -> (d) | BL16: 22.16 | BM16: ='22'!A195 -> (d) | BO16: 23.16 | BP16: ='23'!A194 -> (d) | BR16: 24.16 | BS16: ='24'!A179 -> (b) | BU16: 25.16 | BV16: ='25'!A170 -> (d) | BX16: 26.16 | BY16: ='26'!A180 -> (d)
A17: 1.17 | B17: ='1'!A231 -> (a) | D17: 2.17 | E17: ='2'!A213 -> (c) | G17: 3.17 | H17: ='3'!A228 -> (b) | J17: 4.17 | K17: ='4'!A229 -> (b) | M17: 5.17 | N17: ='5'!A223 -> (c) | P17: 6.17 | Q17: ='6'!A226 -> (b) | S17: 7.17 | T17: ='7'!A221 -> (a) | V17: 8.17 | W17: ='8'!A268 -> (b) | Y17: 9.17 | Z17: ='9'!A186 -> (b) | AB17: 10.17 | AC17: ='10'!A197 -> (a) | AE17: 11.17 | AF17: ='11'!A210 -> (c) | AH17: 12.17 | AI17: ='12'!A171 -> (b) | AK17: 13.17 | AL17: ='13'!A298 -> (b) | AN17: 14.17 | AO17: ='14'!A235 -> (b) | AQ17: 15.17 | AR17: ='15'!A192 -> (b) | AT17: 16.17 | AU17: ='16'!A172 -> (a) | AW17: 17.17 | AX17: ='17'!A302 -> (d) | AZ17: 18.17 | BA17: ='18'!A222 -> (d) | BC17: 19.17 | BD17: ='19'!A201 -> (c) | BF17: 20.17 | BG17: ='20'!A181 -> (b) | BI17: 21.17 | BJ17: ='21'!A201 -> (d) | BL17: 22.17 | BM17: ='22'!A206 -> (b) | BO17: 23.17 | BP17: ='23'!A211 -> (a) | BR17: 24.17 | BS17: ='24'!A190 -> (c) | BU17: 25.17 | BV17: ='25'!A180 -> (a) | BX17: 26.17 | BY17: ='26'!A190 -> (d)
A18: 1.18 | B18: ='1'!A242 -> (c) | D18: 2.18 | E18: ='2'!A227 -> (d) | G18: 3.18 | H18: ='3'!A238 -> (c) | J18: 4.18 | K18: ='4'!A240 -> (d) | M18: 5.18 | N18: ='5'!A233 -> (a) | P18: 6.18 | Q18: ='6'!A243 -> (b) | S18: 7.18 | T18: ='7'!A232 -> (d) | V18: 8.18 | W18: ='8'!A279 -> (a) | Y18: 9.18 | Z18: ='9'!A196 -> (d) | AB18: 10.18 | AC18: ='10'!A207 -> (d) | AE18: 11.18 | AF18: ='11'!A227 -> (d) | AH18: 12.18 | AI18: ='12'!A188 -> (d) | AK18: 13.18 | AL18: ='13'!A332 -> (c) | AN18: 14.18 | AO18: ='14'!A257 -> (d) | AQ18: 15.18 | AR18: ='15'!A214 -> (a) | AT18: 16.18 | AU18: ='16'!A182 -> (b) | AW18: 17.18 | AX18: ='17'!A312 -> (b) | AZ18: 18.18 | BA18: ='18'!A232 -> (c) | BC18: 19.18 | BD18: ='19'!A215 -> (b) | BF18: 20.18 | BG18: ='20'!A191 -> (b) | BI18: 21.18 | BJ18: ='21'!A211 -> (a) | BL18: 22.18 | BM18: ='22'!A216 -> (a) | BO18: 23.18 | BP18: ='23'!A231 -> (a) | BR18: 24.18 | BS18: ='24'!A200 -> (d) | BU18: 25.18 | BV18: ='25'!A191 -> (d) | BX18: 26.18 | BY18: ='26'!A200 -> (c)
A19: 1.19 | B19: ='1'!A254 -> (b) | D19: 2.19 | E19: ='2'!A238 -> (d) | G19: 3.19 | H19: ='3'!A249 -> (b) | J19: 4.19 | K19: ='4'!A251 -> (d) | M19: 5.19 | N19: ='5'!A244 -> (d) | P19: 6.19 | Q19: ='6'!A254 -> (c) | S19: 7.19 | T19: ='7'!A242 -> (a) | V19: 8.19 | W19: ='8'!A289 -> (d) | Y19: 9.19 | Z19: ='9'!A206 -> (a) | AB19: 10.19 | AC19: ='10'!A225 -> (d) | AE19: 11.19 | AF19: ='11'!A246 -> (a) | AH19: 12.19 | AI19: ='12'!A213 -> (a) | AK19: 13.19 | AL19: ='13'!A342 -> (d) | AN19: 14.19 | AO19: ='14'!A268 -> (a) | AQ19: 15.19 | AR19: ='15'!A236 -> (d) | AT19: 16.19 | AU19: ='16'!A192 -> (c) | AW19: 17.19 | AX19: ='17'!A322 -> (b) | AZ19: 18.19 | BA19: ='18'!A242 -> (d) | BC19: 19.19 | BD19: ='19'!A235 -> (c) | BF19: 20.19 | BG19: ='20'!A202 -> (d) | BI19: 21.19 | BJ19: ='21'!A221 -> (d) | BL19: 22.19 | BM19: ='22'!A226 -> (b) | BO19: 23.19 | BP19: ='23'!A241 -> (b) | BR19: 24.19 | BS19: ='24'!A210 -> (c) | BU19: 25.19 | BV19: ='25'!A201 -> (b) | BX19: 26.19 | BY19: ='26'!A210 -> (b)
A20: 1.20 | B20: ='1'!A271 -> (b) | D20: 2.20 | E20: ='2'!A248 -> (b) | G20: 3.20 | H20: ='3'!A261 -> (b) | J20: 4.20 | K20: ='4'!A264 -> (a) | M20: 5.20 | N20: ='5'!A254 -> (c) | P20: 6.20 | Q20: ='6'!A264 -> (d) | S20: 7.20 | T20: ='7'!A252 -> (c) | V20: 8.20 | W20: ='8'!A299 -> (c) | Y20: 9.20 | Z20: ='9'!A216 -> (b) | AB20: 10.20 | AC20: ='10'!A237 -> (b) | AE20: 11.20 | AF20: ='11'!A256 -> (b) | AH20: 12.20 | AI20: ='12'!A236 -> (c) | AK20: 13.20 | AL20: ='13'!A355 -> (c) | AN20: 14.20 | AO20: ='14'!A279 -> (b) | AQ20: 15.20 | AR20: ='15'!A254 -> (c) | AT20: 16.20 | AU20: ='16'!A202 -> (d) | AW20: 17.20 | AX20: ='17'!A333 -> (d) | AZ20: 18.20 | BA20: ='18'!A253 -> (b) | BC20: 19.20 | BD20: ='19'!A245 -> (d) | BF20: 20.20 | BG20: ='20'!A216 -> (b) | BI20: 21.20 | BJ20: ='21'!A231 -> (b) | BL20: 22.20 | BM20: ='22'!A236 -> (b) | BO20: 23.20 | BP20: ='23'!A257 -> (a) | BR20: 24.20 | BS20: ='24'!A236 -> (d) | BU20: 25.20 | BV20: ='25'!A211 -> (d) | BX20: 26.20 | BY20: ='26'!A221 -> (d)
B22: 1 | C22: 2 | D22: 3 | E22: 4 | F22: 5 | G22: 6 | H22: 7 | I22: 8 | J22: 9 | K22: 10 | L22: 11 | M22: 12 | N22: 13 | O22: 14 | P22: 15 | Q22: 16 | R22: 17 | S22: 18 | T22: 19 | U22: 20 | V22: 21 | W22: 22 | X22: 23 | Y22: 24 | Z22: 25 | AA22: 26 | AC22: Totale | AD22: %
A23: (a) | B23: =COUNTIF(B$1:B$20,"(a)") -> 5 | C23: =COUNTIF(E$1:E$20,"(a)") -> 5 | D23: =COUNTIF(H$1:H$20,"(a)") -> 5 | E23: =COUNTIF(K$1:K$20,"(a)") -> 5 | F23: =COUNTIF(N$1:N$20,"(a)") -> 5 | G23: =COUNTIF(Q$1:Q$20,"(a)") -> 3 | H23: =COUNTIF(T$1:T$20,"(a)") -> 7 | I23: =COUNTIF(W$1:W$20,"(a)") -> 4 | J23: =COUNTIF(Z$1:Z$20,"(a)") -> 6 | K23: =COUNTIF(AC$1:AC$20,"(a)") -> 6 | L23: =COUNTIF(AF$1:AF$20,"(a)") -> 4 | M23: =COUNTIF(AI$1:AI$20,"(a)") -> 5 | N23: =COUNTIF(AL$1:AL$20,"(a)") -> 3 | O23: =COUNTIF(AO$1:AO$20,"(a)") -> 3 | P23: =COUNTIF(AR$1:AR$20,"(a)") -> 4 | Q23: =COUNTIF(AU$1:AU$20,"(a)") -> 4 | R23: =COUNTIF(AX$1:AX$20,"(a)") -> 3 | S23: =COUNTIF(BA$1:BA$20,"(a)") -> 4 | T23: =COUNTIF(BD$1:BD$20,"(a)") -> 5 | U23: =COUNTIF(BG$1:BG$20,"(a)") -> 6 | V23: =COUNTIF(BJ$1:BJ$20,"(a)") -> 2 | W23: =COUNTIF(BM$1:BM$20,"(a)") -> 7 | X23: =COUNTIF(BP$1:BP$20,"(a)") -> 6 | Y23: =COUNTIF(BS$1:BS$20,"(a)") -> 3 | Z23: =COUNTIF(BV$1:BV$20,"(a)") -> 3 | AA23: =COUNTIF(BY$1:BY$20,"(a)") -> 2 | AC23: =SUM(B23:AA23) -> 115 | AD23: =AC23/$AC$27 -> 0.22115385
A24: (b) | B24: =COUNTIF(B$1:B$20,"(b)") -> 5 | C24: =COUNTIF(E$1:E$20,"(b)") -> 6 | D24: =COUNTIF(H$1:H$20,"(b)") -> 6 | E24: =COUNTIF(K$1:K$20,"(b)") -> 4 | F24: =COUNTIF(N$1:N$20,"(b)") -> 5 | G24: =COUNTIF(Q$1:Q$20,"(b)") -> 7 | H24: =COUNTIF(T$1:T$20,"(b)") -> 6 | I24: =COUNTIF(W$1:W$20,"(b)") -> 6 | J24: =COUNTIF(Z$1:Z$20,"(b)") -> 6 | K24: =COUNTIF(AC$1:AC$20,"(b)") -> 4 | L24: =COUNTIF(AF$1:AF$20,"(b)") -> 4 | M24: =COUNTIF(AI$1:AI$20,"(b)") -> 5 | N24: =COUNTIF(AL$1:AL$20,"(b)") -> 5 | O24: =COUNTIF(AO$1:AO$20,"(b)") -> 7 | P24: =COUNTIF(AR$1:AR$20,"(b)") -> 6 | Q24: =COUNTIF(AU$1:AU$20,"(b)") -> 7 | R24: =COUNTIF(AX$1:AX$20,"(b)") -> 6 | S24: =COUNTIF(BA$1:BA$20,"(b)") -> 4 | T24: =COUNTIF(BD$1:BD$20,"(b)") -> 5 | U24: =COUNTIF(BG$1:BG$20,"(b)") -> 3 | V24: =COUNTIF(BJ$1:BJ$20,"(b)") -> 7 | W24: =COUNTIF(BM$1:BM$20,"(b)") -> 8 | X24: =COUNTIF(BP$1:BP$20,"(b)") -> 5 | Y24: =COUNTIF(BS$1:BS$20,"(b)") -> 6 | Z24: =COUNTIF(BV$1:BV$20,"(b)") -> 5 | AA24: =COUNTIF(BY$1:BY$20,"(b)") -> 6 | AC24: =SUM(B24:AA24) -> 144 | AD24: =AC24/$AC$27 -> 0.27692308
A25: (c) | B25: =COUNTIF(B$1:B$20,"(c)") -> 5 | C25: =COUNTIF(E$1:E$20,"(c)") -> 4 | D25: =COUNTIF(H$1:H$20,"(c)") -> 4 | E25: =COUNTIF(K$1:K$20,"(c)") -> 4 | F25: =COUNTIF(N$1:N$20,"(c)") -> 6 | G25: =COUNTIF(Q$1:Q$20,"(c)") -> 6 | H25: =COUNTIF(T$1:T$20,"(c)") -> 3 | I25: =COUNTIF(W$1:W$20,"(c)") -> 5 | J25: =COUNTIF(Z$1:Z$20,"(c)") -> 4 | K25: =COUNTIF(AC$1:AC$20,"(c)") -> 4 | L25: =COUNTIF(AF$1:AF$20,"(c)") -> 5 | M25: =COUNTIF(AI$1:AI$20,"(c)") -> 5 | N25: =COUNTIF(AL$1:AL$20,"(c)") -> 7 | O25: =COUNTIF(AO$1:AO$20,"(c)") -> 7 | P25: =COUNTIF(AR$1:AR$20,"(c)") -> 3 | Q25: =COUNTIF(AU$1:AU$20,"(c)") -> 4 | R25: =COUNTIF(AX$1:AX$20,"(c)") -> 4 | S25: =COUNTIF(BA$1:BA$20,"(c)") -> 8 | T25: =COUNTIF(BD$1:BD$20,"(c)") -> 6 | U25: =COUNTIF(BG$1:BG$20,"(c)") -> 7 | V25: =COUNTIF(BJ$1:BJ$20,"(c)") -> 5 | W25: =COUNTIF(BM$1:BM$20,"(c)") -> 3 | X25: =COUNTIF(BP$1:BP$20,"(c)") -> 5 | Y25: =COUNTIF(BS$1:BS$20,"(c)") -> 7 | Z25: =COUNTIF(BV$1:BV$20,"(c)") -> 2 | AA25: =COUNTIF(BY$1:BY$20,"(c)") -> 4 | AC25: =SUM(B25:AA25) -> 127 | AD25: =AC25/$AC$27 -> 0.24423077
A26: (d) | B26: =COUNTIF(B$1:B$20,"(d)") -> 5 | C26: =COUNTIF(E$1:E$20,"(d)") -> 5 | D26: =COUNTIF(H$1:H$20,"(d)") -> 5 | E26: =COUNTIF(K$1:K$20,"(d)") -> 7 | F26: =COUNTIF(N$1:N$20,"(d)") -> 4 | G26: =COUNTIF(Q$1:Q$20,"(d)") -> 4 | H26: =COUNTIF(T$1:T$20,"(d)") -> 4 | I26: =COUNTIF(W$1:W$20,"(d)") -> 5 | J26: =COUNTIF(Z$1:Z$20,"(d)") -> 4 | K26: =COUNTIF(AC$1:AC$20,"(d)") -> 6 | L26: =COUNTIF(AF$1:AF$20,"(d)") -> 7 | M26: =COUNTIF(AI$1:AI$20,"(d)") -> 5 | N26: =COUNTIF(AL$1:AL$20,"(d)") -> 5 | O26: =COUNTIF(AO$1:AO$20,"(d)") -> 3 | P26: =COUNTIF(AR$1:AR$20,"(d)") -> 7 | Q26: =COUNTIF(AU$1:AU$20,"(d)") -> 5 | R26: =COUNTIF(AX$1:AX$20,"(d)") -> 7 | S26: =COUNTIF(BA$1:BA$20,"(d)") -> 4 | T26: =COUNTIF(BD$1:BD$20,"(d)") -> 4 | U26: =COUNTIF(BG$1:BG$20,"(d)") -> 4 | V26: =COUNTIF(BJ$1:BJ$20,"(d)") -> 6 | W26: =COUNTIF(BM$1:BM$20,"(d)") -> 2 | X26: =COUNTIF(BP$1:BP$20,"(d)") -> 4 | Y26: =COUNTIF(BS$1:BS$20,"(d)") -> 4 | Z26: =COUNTIF(BV$1:BV$20,"(d)") -> 10 | AA26: =COUNTIF(BY$1:BY$20,"(d)") -> 8 | AC26: =SUM(B26:AA26) -> 134 | AD26: =AC26/$AC$27 -> 0.25769231
B27: =SUM(B23:B26) -> 20 | C27: =SUM(C23:C26) -> 20 | D27: =SUM(D23:D26) -> 20 | E27: =SUM(E23:E26) -> 20 | F27: =SUM(F23:F26) -> 20 | G27: =SUM(G23:G26) -> 20 | H27: =SUM(H23:H26) -> 20 | I27: =SUM(I23:I26) -> 20 | ... AA27: =SUM(AA23:AA26) -> 20 | AC27: =SUM(AC23:AC26) -> 520 | AD27: =SUM(AD23:AD26) -> 1
